Workbook

Sheet Index
A1: 2026 | B1: 2025 | C1: 2024 | D1: Other
A2: 2026 | B2: 2025 | C2: 2024 | D2: [Chart1] Monthly Dollars by Sales Representative and Year
A3: 2026 AM Totals | B3: 2025 Adam | C3: 2024 Adam | D3: 2023
A4: 2026 Breakdown | B4: 2025 AM Totals | C4: 2024 AM | D4: Commission Data
A5: 2026 Brett | B5: 2025 Breakdown | C5: 2024 Breakdown | D5: OPs Callback
A6: 2026 Drew | B6: 2025 Brett | C6: 2024 Brett | D6: Paid 2026
A7: 2026 James | B7: 2025 Chris | C7: 2024 Brian | D7: Reports
A8: 2026 Mike | B8: 2025 Drew | C8: 2024 Chris | D8: Surveys
A9: 2026 Surveys | B9: 2025 Geoff | C9: 2024 Insurance vs Retail
B10: 2025 James | C10: 2024 James
B11: 2025 Mike | C11: 2024 Jared
B12: 2025 Will | C12: 2024 Mike
C13: 2024 Schedule
C14: 2024 Will

Sheet 2026
A1: Project # (2164) | B1: Job # | C1: Name | D1: Type | E1: Date | F1: ="Contract Amt $" & TEXT(SUM(F2:F308),"#,##0.00") -> Contract Amt $757,244.55 | G1: Projected Start Date | H1: Projected End Date | I1: AM | J1: ="Invoiced Total $" & TEXT(SUM(J2:J308),"#,##0.00") -> Invoiced Total $253,885.39 | K1: ="Amount Paid $" & TEXT(SUM(K2:K308),"#,##0.00") -> Amount Paid $177,028.67 | L1: ="Change Orders $" & TEXT(SUM(L2:L308),"#,##0.00") -> Change Orders $3,881.10 | M1: ="Cost $" & TEXT(SUM(M2:M308),"#,##0.00") -> Cost $142,694.65 | N1: ="GP $" & TEXT(SUM(N2:N308),"#,##0.00") -> GP $49,902.58 | O1: =AVERAGEIFS(O2:O317, O2:O317, "<>", S2:S317, TRUE) -> 0.66535131 | P1: =AVERAGEIFS(P2:P317, P2:P317, "<>", S2:S317, TRUE) -> 0.67675882 | Q1: =AVERAGEIFS(Q2:Q317, Q2:Q317, "<>", S2:S317, TRUE) -> 0.55698002 | R1: Billed | S1: Paid in Full | T1: Comm Owed | U1: Status | V1: Updated this week | W1: GP | X1: Invoiced | Y1: Contract | Z1: Change Orders | AA1: =IFERROR(__xludf.DUMMYFUNCTION("ARRAYFORMULA({ ""Manager""; IF(A2:A1000="""","""", IF(IFERROR(VALUE(A2:A1000),0)>=1857, ""Drew"", IF( REGEXMATCH( LOWER( TRIM( SUBSTITUTE( SUBSTITUTE( CLEAN(I2:I1000), "&" CHAR(160),"" "" ), CHAR(9),"""" ) ) ), ""^drew$"" ), ""Drew"","""" ) ) ) })"),"Manager") -> Manager | AB1: Amount Paid | AC1: Date of Last Payment
A2: 2162 | B2: 20265001 | C2: Riley Spradlin | E2: 46028 | F2: 49298.62 | G2: 04/02/2026 | H2: 04/02/2026 | I2: Drew | J2: 17603 | K2: 17603 | L2: =if(S2=TRUE,K2-F2,"") | M2: 34751.69 | N2: =if(S2=TRUE,K2-M2,"") | O2: =IF($R2, IFERROR(IF((F2+L2)>0, (F2+L2-M2)/(F2+L2), ""), ""), "") -> 0.29507783 | P2: =IFERROR(__xludf.DUMMYFUNCTION("IF(AND($R2, NOT(REGEXMATCH(UPPER($C2), ""INS""))), IFERROR(IF((F2+L2)>0, (F2+L2-M2)/(F2+L2), """"), """"), """")"),0.29507783382171754) -> 0.29507783 | Q2: =IFERROR(__xludf.DUMMYFUNCTION("IF(AND($R2, REGEXMATCH(UPPER($C2), ""INS"")), IFERROR(IF((F2+L2)>0, (F2+L2-M2)/(F2+L2), """"), """"), """")"),"") | R2: TRUE | S2: FALSE | T2: FALSE | U2: In Billing | V2: FALSE | W2: =O2 -> 0.29507783 | X2: =J2 -> 17603 | Y2: =F2 -> 49298.62 | Z2: =L2 | AA2: =IFERROR(__xludf.DUMMYFUNCTION("""COMPUTED_VALUE"""),"Drew") -> Drew | AB2: =K2 -> 17603
A3: 2154 | B3: 20265002 | C3: Matthew Patton | E3: 46030 | F3: 540 | G3: 03/05/2026 | H3: 03/05/2026 | I3: Brett | J3: 540 | K3: 540 | L3: =if(S3=TRUE,K3-F3,"") -> 0 | M3: 274.35 | N3: =if(S3=TRUE,K3-M3,"") -> 265.65 | O3: =IF($R3, IFERROR(IF((F3+L3)>0, (F3+L3-M3)/(F3+L3), ""), ""), "") -> 0.49194444 | P3: =IFERROR(__xludf.DUMMYFUNCTION("IF(AND($R3, NOT(REGEXMATCH(UPPER($C3), ""INS""))), IFERROR(IF((F3+L3)>0, (F3+L3-M3)/(F3+L3), """"), """"), """")"),0.4919444444444444) -> 0.49194444 | Q3: =IFERROR(__xludf.DUMMYFUNCTION("IF(AND($R3, REGEXMATCH(UPPER($C3), ""INS"")), IFERROR(IF((F3+L3)>0, (F3+L3-M3)/(F3+L3), """"), """"), """")"),"") | R3: TRUE | S3: TRUE | T3: FALSE | U3: In Billing | V3: FALSE | W3: =O3 -> 0.49194444 | X3: =J3 -> 540 | Y3: =F3 -> 540 | Z3: =L3 -> 0 | AA3: =IFERROR(__xludf.DUMMYFUNCTION("""COMPUTED_VALUE"""),"Drew") -> Drew | AB3: =K3 -> 540
A4: 2177 | B4: 20265003 | C4: Marshall Wagner | E4: 46034 | F4: 1182.7 | G4: 01/22/2026 | H4: 01/22/2026 | I4: James | J4: 1182.7 | K4: 1182.7 | L4: =if(S4=TRUE,K4-F4,"") -> 0 | M4: 694.62 | N4: =if(S4=TRUE,K4-M4,"") -> 488.08 | O4: =IF($R4, IFERROR(IF((F4+L4)>0, (F4+L4-M4)/(F4+L4), ""), ""), "") -> 0.41268284 | P4: =IFERROR(__xludf.DUMMYFUNCTION("IF(AND($R4, NOT(REGEXMATCH(UPPER($C4), ""INS""))), IFERROR(IF((F4+L4)>0, (F4+L4-M4)/(F4+L4), """"), """"), """")"),0.4126828443392238) -> 0.41268284 | Q4: =IFERROR(__xludf.DUMMYFUNCTION("IF(AND($R4, REGEXMATCH(UPPER($C4), ""INS"")), IFERROR(IF((F4+L4)>0, (F4+L4-M4)/(F4+L4), """"), """"), """")"),"") | R4: TRUE | S4: TRUE | T4: FALSE | U4: In Billing | V4: FALSE | W4: =O4 -> 0.41268284 | X4: =J4 -> 1182.7 | Y4: =F4 -> 1182.7 | Z4: =L4 -> 0 | AA4: =IFERROR(__xludf.DUMMYFUNCTION("""COMPUTED_VALUE"""),"Drew") -> Drew | AB4: =K4 -> 1182.7
A5: 2173 | B5: 20265004 | C5: Donald Mcghee | E5: 46034 | F5: 522.92 | I5: James | J5: 809.77 | L5: =if(S5=TRUE,K5-F5,"") | M5: 524.7 | N5: =if(S5=TRUE,K5-M5,"") | O5: =IF($R5, IFERROR(IF((F5+L5)>0, (F5+L5-M5)/(F5+L5), ""), ""), "") -> -0.0034039624 | P5: =IFERROR(__xludf.DUMMYFUNCTION("IF(AND($R5, NOT(REGEXMATCH(UPPER($C5), ""INS""))), IFERROR(IF((F5+L5)>0, (F5+L5-M5)/(F5+L5), """"), """"), """")"),-0.003403962365180308) -> -0.0034039624 | Q5: =IFERROR(__xludf.DUMMYFUNCTION("IF(AND($R5, REGEXMATCH(UPPER($C5), ""INS"")), IFERROR(IF((F5+L5)>0, (F5+L5-M5)/(F5+L5), """"), """"), """")"),"") | R5: TRUE | S5: FALSE | T5: FALSE | U5: In Billing | V5: FALSE | W5: =O5 -> -0.0034039624 | X5: =J5 -> 809.77 | Y5: =F5 -> 522.92 | Z5: =L5 | AA5: =IFERROR(__xludf.DUMMYFUNCTION("""COMPUTED_VALUE"""),"Drew") -> Drew | AB5: =K5
A6: 2134 | B6: 20265005 | C6: Shari Dill | E6: 46035 | F6: 2746.93 | G6: 04/02/2026 | H6: 04/02/2026 | I6: James | J6: 2746.93 | K6: 2746.93 | L6: =if(S6=TRUE,K6-F6,"") -> 0 | M6: 2027.7 | N6: =if(S6=TRUE,K6-M6,"") -> 719.23 | O6: =IF($R6, IFERROR(IF((F6+L6)>0, (F6+L6-M6)/(F6+L6), ""), ""), "") -> 0.26183048 | P6: =IFERROR(__xludf.DUMMYFUNCTION("IF(AND($R6, NOT(REGEXMATCH(UPPER($C6), ""INS""))), IFERROR(IF((F6+L6)>0, (F6+L6-M6)/(F6+L6), """"), """"), """")"),0.2618304798447721) -> 0.26183048 | Q6: =IFERROR(__xludf.DUMMYFUNCTION("IF(AND($R6, REGEXMATCH(UPPER($C6), ""INS"")), IFERROR(IF((F6+L6)>0, (F6+L6-M6)/(F6+L6), """"), """"), """")"),"") | R6: TRUE | S6: TRUE | T6: FALSE | U6: Job Scheduled | V6: FALSE | W6: =O6 -> 0.26183048 | X6: =J6 -> 2746.93 | Y6: =F6 -> 2746.93 | Z6: =L6 -> 0 | AA6: =IFERROR(__xludf.DUMMYFUNCTION("""COMPUTED_VALUE"""),"Drew") -> Drew | AB6: =K6 -> 2746.93
A7: 2176 | B7: 20265006 | C7: Nancy Avila | E7: 46045 | F7: 550 | I7: Brett | J7: 550 | K7: 550 | L7: =if(S7=TRUE,K7-F7,"") -> 0 | M7: 250 | N7: =if(S7=TRUE,K7-M7,"") -> 300 | O7: =IF($R7, IFERROR(IF((F7+L7)>0, (F7+L7-M7)/(F7+L7), ""), ""), "") -> 0.54545455 | P7: =IFERROR(__xludf.DUMMYFUNCTION("IF(AND($R7, NOT(REGEXMATCH(UPPER($C7), ""INS""))), IFERROR(IF((F7+L7)>0, (F7+L7-M7)/(F7+L7), """"), """"), """")"),0.5454545454545454) -> 0.54545455 | Q7: =IFERROR(__xludf.DUMMYFUNCTION("IF(AND($R7, REGEXMATCH(UPPER($C7), ""INS"")), IFERROR(IF((F7+L7)>0, (F7+L7-M7)/(F7+L7), """"), """"), """")"),"") | R7: TRUE | S7: TRUE | T7: FALSE | U7: In Billing | V7: FALSE | W7: =O7 -> 0.54545455 | X7: =J7 -> 550 | Y7: =F7 -> 550 | Z7: =L7 -> 0 | AA7: =IFERROR(__xludf.DUMMYFUNCTION("""COMPUTED_VALUE"""),"Drew") -> Drew | AB7: =K7 -> 550
A8: 2197 | B8: 20265007 | C8: James Combs | E8: 46049 | F8: 240 | G8: 01/27/2026 | H8: 01/27/2026 | I8: Adam | J8: 240 | K8: 240 | L8: =if(S8=TRUE,K8-F8,"") -> 0 | M8: 0 | N8: =if(S8=TRUE,K8-M8,"") -> 240 | O8: =IF($R8, IFERROR(IF((F8+L8)>0, (F8+L8-M8)/(F8+L8), ""), ""), "") -> 1 | P8: =IFERROR(__xludf.DUMMYFUNCTION("IF(AND($R8, NOT(REGEXMATCH(UPPER($C8), ""INS""))), IFERROR(IF((F8+L8)>0, (F8+L8-M8)/(F8+L8), """"), """"), """")"),1.0) -> 1 | Q8: =IFERROR(__xludf.DUMMYFUNCTION("IF(AND($R8, REGEXMATCH(UPPER($C8), ""INS"")), IFERROR(IF((F8+L8)>0, (F8+L8-M8)/(F8+L8), """"), """"), """")"),"") | R8: TRUE | S8: TRUE | T8: TRUE | U8: In Billing | V8: FALSE | W8: =O8 -> 1 | X8: =J8 -> 240 | Y8: =F8 -> 240 | Z8: =L8 -> 0 | AA8: =IFERROR(__xludf.DUMMYFUNCTION("""COMPUTED_VALUE"""),"Drew") -> Drew | AB8: =K8 -> 240
A9: 2159 | B9: 20265008 | C9: Jonathan Vernon | E9: 46051 | F9: 9689.68 | I9: James | L9: =if(S9=TRUE,K9-F9,"") | N9: =if(S9=TRUE,K9-M9,"") | O9: =IF($R9, IFERROR(IF((F9+L9)>0, (F9+L9-M9)/(F9+L9), ""), ""), "") | P9: =IFERROR(__xludf.DUMMYFUNCTION("IF(AND($R9, NOT(REGEXMATCH(UPPER($C9), ""INS""))), IFERROR(IF((F9+L9)>0, (F9+L9-M9)/(F9+L9), """"), """"), """")"),"") | Q9: =IFERROR(__xludf.DUMMYFUNCTION("IF(AND($R9, REGEXMATCH(UPPER($C9), ""INS"")), IFERROR(IF((F9+L9)>0, (F9+L9-M9)/(F9+L9), """"), """"), """")"),"") | R9: FALSE | S9: FALSE | T9: FALSE | U9: Materials Ordered | V9: FALSE | W9: =O9 | X9: =J9 | Y9: =F9 -> 9689.68 | Z9: =L9 | AA9: =IFERROR(__xludf.DUMMYFUNCTION("""COMPUTED_VALUE"""),"Drew") -> Drew | AB9: =K9
A10: 2214 | B10: 20265009 | C10: Christian Life Center Emergency Repairs | E10: 46057 | F10: 0 | G10: 02/12/2026 | H10: 02/12/2026 | I10: Chris | J10: 20646.65 | L10: =if(S10=TRUE,K10-F10,"") | M10: 5661.19 | N10: =if(S10=TRUE,K10-M10,"") | O10: =IF($R10, IFERROR(IF((F10+L10)>0, (F10+L10-M10)/(F10+L10), ""), ""), "") | P10: =IFERROR(__xludf.DUMMYFUNCTION("IF(AND($R10, NOT(REGEXMATCH(UPPER($C10), ""INS""))), IFERROR(IF((F10+L10)>0, (F10+L10-M10)/(F10+L10), """"), """"), """")"),"") | Q10: =IFERROR(__xludf.DUMMYFUNCTION("IF(AND($R10, REGEXMATCH(UPPER($C10), ""INS"")), IFERROR(IF((F10+L10)>0, (F10+L10-M10)/(F10+L10), """"), """"), """")"),"") | R10: TRUE | S10: FALSE | T10: FALSE | U10: Job Scheduled | V10: FALSE | W10: =O10 | X10: =J10 -> 20646.65 | Y10: =F10 -> 0 | Z10: =L10 | AA10: =IFERROR(__xludf.DUMMYFUNCTION("""COMPUTED_VALUE"""),"Drew") -> Drew | AB10: =K10
A11: 2192 | B11: 20265010 | C11: Tyler Hunt | E11: 46057 | F11: 32265.41 | G11: 03/19/2026 | H11: 03/19/2026 | I11: James | J11: 32595.41 | K11: 32265.41 | L11: =if(S11=TRUE,K11-F11,"") -> 0 | M11: 20681.57 | N11: =if(S11=TRUE,K11-M11,"") -> 11583.84 | O11: =IF($R11, IFERROR(IF((F11+L11)>0, (F11+L11-M11)/(F11+L11), ""), ""), "") -> 0.35901729 | P11: =IFERROR(__xludf.DUMMYFUNCTION("IF(AND($R11, NOT(REGEXMATCH(UPPER($C11), ""INS""))), IFERROR(IF((F11+L11)>0, (F11+L11-M11)/(F11+L11), """"), """"), """")"),0.3590172881733101) -> 0.35901729 | Q11: =IFERROR(__xludf.DUMMYFUNCTION("IF(AND($R11, REGEXMATCH(UPPER($C11), ""INS"")), IFERROR(IF((F11+L11)>0, (F11+L11-M11)/(F11+L11), """"), """"), """")"),"") | R11: TRUE | S11: TRUE | T11: FALSE | U11: In Billing | V11: FALSE | W11: =O11 -> 0.35901729 | X11: =J11 -> 32595.41 | Y11: =F11 -> 32265.41 | Z11: =L11 -> 0 | AA11: =IFERROR(__xludf.DUMMYFUNCTION("""COMPUTED_VALUE"""),"Drew") -> Drew | AB11: =K11 -> 32265.41
A12: 2168 | B12: 20265011 | C12: August Boehnlein | E12: 46058 | F12: 24299.55 | I12: James | L12: =if(S12=TRUE,K12-F12,"") | N12: =if(S12=TRUE,K12-M12,"") | O12: =IF($R12, IFERROR(IF((F12+L12)>0, (F12+L12-M12)/(F12+L12), ""), ""), "") | P12: =IFERROR(__xludf.DUMMYFUNCTION("IF(AND($R12, NOT(REGEXMATCH(UPPER($C12), ""INS""))), IFERROR(IF((F12+L12)>0, (F12+L12-M12)/(F12+L12), """"), """"), """")"),"") | Q12: =IFERROR(__xludf.DUMMYFUNCTION("IF(AND($R12, REGEXMATCH(UPPER($C12), ""INS"")), IFERROR(IF((F12+L12)>0, (F12+L12-M12)/(F12+L12), """"), """"), """")"),"") | R12: FALSE | S12: FALSE | T12: FALSE | U12: Project On Hold | V12: FALSE | W12: =O12 | X12: =J12 | Y12: =F12 -> 24299.55 | Z12: =L12 | AA12: =IFERROR(__xludf.DUMMYFUNCTION("""COMPUTED_VALUE"""),"Drew") -> Drew | AB12: =K12
A13: 2201 | B13: 20265012 | C13: Deborah Tippie | E13: 46062 | F13: 506.25 | I13: Mike | J13: 506.25 | K13: 506.25 | L13: =if(S13=TRUE,K13-F13,"") -> 0 | N13: =if(S13=TRUE,K13-M13,"") -> 506.25 | O13: =IF($R13, IFERROR(IF((F13+L13)>0, (F13+L13-M13)/(F13+L13), ""), ""), "") -> 1 | P13: =IFERROR(__xludf.DUMMYFUNCTION("IF(AND($R13, NOT(REGEXMATCH(UPPER($C13), ""INS""))), IFERROR(IF((F13+L13)>0, (F13+L13-M13)/(F13+L13), """"), """"), """")"),1.0) -> 1 | Q13: =IFERROR(__xludf.DUMMYFUNCTION("IF(AND($R13, REGEXMATCH(UPPER($C13), ""INS"")), IFERROR(IF((F13+L13)>0, (F13+L13-M13)/(F13+L13), """"), """"), """")"),"") | R13: TRUE | S13: TRUE | T13: FALSE | U13: In Billing | V13: FALSE | W13: =O13 -> 1 | X13: =J13 -> 506.25 | Y13: =F13 -> 506.25 | Z13: =L13 -> 0 | AA13: =IFERROR(__xludf.DUMMYFUNCTION("""COMPUTED_VALUE"""),"Drew") -> Drew | AB13: =K13 -> 506.25
A14: 2012 | B14: 20265013 | C14: INS - Jeremiah Jenkins | E14: 45950 | F14: 0 | G14: 04/09/2026 | H14: 04/09/2026 | I14: James | J14: 17579.32 | K14: 17579.32 | L14: =if(S14=TRUE,K14-F14,"") -> 17579.32 | M14: 15575.98 | N14: =if(S14=TRUE,K14-M14,"") -> 2003.34 | O14: =IF($R14, IFERROR(IF((F14+L14)>0, (F14+L14-M14)/(F14+L14), ""), ""), "") -> 0.11396004 | P14: =IFERROR(__xludf.DUMMYFUNCTION("IF(AND($R14, NOT(REGEXMATCH(UPPER($C14), ""INS""))), IFERROR(IF((F14+L14)>0, (F14+L14-M14)/(F14+L14), """"), """"), """")"),"") | Q14: =IFERROR(__xludf.DUMMYFUNCTION("IF(AND($R14, REGEXMATCH(UPPER($C14), ""INS"")), IFERROR(IF((F14+L14)>0, (F14+L14-M14)/(F14+L14), """"), """"), """")"),0.11396003940994305) -> 0.11396004 | R14: TRUE | S14: TRUE | T14: FALSE | U14: In Progress | V14: FALSE | W14: =O14 -> 0.11396004 | X14: =J14 -> 17579.32 | Y14: =F14 -> 0 | Z14: =L14 -> 17579.32 | AA14: =IFERROR(__xludf.DUMMYFUNCTION("""COMPUTED_VALUE"""),"Drew") -> Drew | AB14: =K14 -> 17579.32
A15: 2229 | B15: 20265014 | C15: INS - Floyd Cain Jr. | E15: 46066 | F15: 0 | I15: James | L15: =if(S15=TRUE,K15-F15,"") | N15: =if(S15=TRUE,K15-M15,"") | O15: =IF($R15, IFERROR(IF((F15+L15)>0, (F15+L15-M15)/(F15+L15), ""), ""), "") | P15: =IFERROR(__xludf.DUMMYFUNCTION("IF(AND($R15, NOT(REGEXMATCH(UPPER($C15), ""INS""))), IFERROR(IF((F15+L15)>0, (F15+L15-M15)/(F15+L15), """"), """"), """")"),"") | Q15: =IFERROR(__xludf.DUMMYFUNCTION("IF(AND($R15, REGEXMATCH(UPPER($C15), ""INS"")), IFERROR(IF((F15+L15)>0, (F15+L15-M15)/(F15+L15), """"), """"), """")"),"") | R15: FALSE | S15: FALSE | T15: FALSE | U15: Approved | V15: FALSE | W15: =O15 | X15: =J15 | Y15: =F15 -> 0 | Z15: =L15 | AA15: =IFERROR(__xludf.DUMMYFUNCTION("""COMPUTED_VALUE"""),"Drew") -> Drew | AB15: =K15
A16: 2180 | B16: 20265015 | C16: Robert Kissell | E16: 46067 | F16: 11560 | I16: Brett | J16: 14167.06 | K16: 14167.06 | L16: =if(S16=TRUE,K16-F16,"") -> 2607.06 | M16: 8890.44 | N16: =if(S16=TRUE,K16-M16,"") -> 5276.62 | O16: =IF($R16, IFERROR(IF((F16+L16)>0, (F16+L16-M16)/(F16+L16), ""), ""), "") -> 0.37245695 | P16: =IFERROR(__xludf.DUMMYFUNCTION("IF(AND($R16, NOT(REGEXMATCH(UPPER($C16), ""INS""))), IFERROR(IF((F16+L16)>0, (F16+L16-M16)/(F16+L16), """"), """"), """")"),0.3724569529598942) -> 0.37245695 | Q16: =IFERROR(__xludf.DUMMYFUNCTION("IF(AND($R16, REGEXMATCH(UPPER($C16), ""INS"")), IFERROR(IF((F16+L16)>0, (F16+L16-M16)/(F16+L16), """"), """"), """")"),"") | R16: TRUE | S16: TRUE | T16: FALSE | U16: In Billing | V16: FALSE | W16: =O16 -> 0.37245695 | X16: =J16 -> 14167.06 | Y16: =F16 -> 11560 | Z16: =L16 -> 2607.06 | AA16: =IFERROR(__xludf.DUMMYFUNCTION("""COMPUTED_VALUE"""),"Drew") -> Drew | AB16: =K16 -> 14167.06
A17: 2221 | B17: 20265016 | C17: Jason Rutan | E17: 46072 | F17: 19468.5 | G17: 04/16/2026 | H17: 04/16/2026 | I17: James | L17: =if(S17=TRUE,K17-F17,"") | N17: =if(S17=TRUE,K17-M17,"") | O17: =IF($R17, IFERROR(IF((F17+L17)>0, (F17+L17-M17)/(F17+L17), ""), ""), "") | P17: =IFERROR(__xludf.DUMMYFUNCTION("IF(AND($R17, NOT(REGEXMATCH(UPPER($C17), ""INS""))), IFERROR(IF((F17+L17)>0, (F17+L17-M17)/(F17+L17), """"), """"), """")"),"") | Q17: =IFERROR(__xludf.DUMMYFUNCTION("IF(AND($R17, REGEXMATCH(UPPER($C17), ""INS"")), IFERROR(IF((F17+L17)>0, (F17+L17-M17)/(F17+L17), """"), """"), """")"),"") | R17: FALSE | S17: FALSE | T17: FALSE | U17: Job Scheduled | V17: FALSE | W17: =O17 | X17: =J17 | Y17: =F17 -> 19468.5 | Z17: =L17 | AA17: =IFERROR(__xludf.DUMMYFUNCTION("""COMPUTED_VALUE"""),"Drew") -> Drew | AB17: =K17
A18: 2052 | B18: 20265017 | C18: Kristen Adams | E18: 46077 | F18: 28121.11 | G18: 04/16/2026 | H18: 04/16/2026 | I18: James | J18: 28320.73 | K18: 28320.73 | L18: =if(S18=TRUE,K18-F18,"") -> 199.62 | M18: 14742.02 | N18: =if(S18=TRUE,K18-M18,"") -> 13578.71 | O18: =IF($R18, IFERROR(IF((F18+L18)>0, (F18+L18-M18)/(F18+L18), ""), ""), "") | P18: =IFERROR(__xludf.DUMMYFUNCTION("IF(AND($R18, NOT(REGEXMATCH(UPPER($C18), ""INS""))), IFERROR(IF((F18+L18)>0, (F18+L18-M18)/(F18+L18), """"), """"), """")"),"") | Q18: =IFERROR(__xludf.DUMMYFUNCTION("IF(AND($R18, REGEXMATCH(UPPER($C18), ""INS"")), IFERROR(IF((F18+L18)>0, (F18+L18-M18)/(F18+L18), """"), """"), """")"),"") | R18: FALSE | S18: TRUE | T18: TRUE | U18: Job Scheduled | V18: FALSE | W18: =O18 | X18: =J18 -> 28320.73 | Y18: =F18 -> 28121.11 | Z18: =L18 -> 199.62 | AA18: =IFERROR(__xludf.DUMMYFUNCTION("""COMPUTED_VALUE"""),"Drew") -> Drew | AB18: =K18 -> 28320.73
A19: 2196 | B19: 20265018 | C19: CHIP - Carol Steed | E19: 46077 | F19: 11265 | G19: 04/16/2026 | H19: 04/16/2026 | I19: James | L19: =if(S19=TRUE,K19-F19,"") | M19: 11562.46 | N19: =if(S19=TRUE,K19-M19,"") | O19: =IF($R19, IFERROR(IF((F19+L19)>0, (F19+L19-M19)/(F19+L19), ""), ""), "") | P19: =IFERROR(__xludf.DUMMYFUNCTION("IF(AND($R19, NOT(REGEXMATCH(UPPER($C19), ""INS""))), IFERROR(IF((F19+L19)>0, (F19+L19-M19)/(F19+L19), """"), """"), """")"),"") | Q19: =IFERROR(__xludf.DUMMYFUNCTION("IF(AND($R19, REGEXMATCH(UPPER($C19), ""INS"")), IFERROR(IF((F19+L19)>0, (F19+L19-M19)/(F19+L19), """"), """"), """")"),"") | R19: FALSE | S19: FALSE | T19: FALSE | U19: Job Scheduled | V19: FALSE | W19: =O19 | X19: =J19 | Y19: =F19 -> 11265 | Z19: =L19 | AA19: =IFERROR(__xludf.DUMMYFUNCTION("""COMPUTED_VALUE"""),"Drew") -> Drew | AB19: =K19
A20: 2209 | B20: 20265019 | C20: Amy Hoff | E20: 46079 | F20: 5480 | G20: 04/16/2026 | H20: 04/16/2026 | I20: Brett | L20: =if(S20=TRUE,K20-F20,"") | N20: =if(S20=TRUE,K20-M20,"") | O20: =IF($R20, IFERROR(IF((F20+L20)>0, (F20+L20-M20)/(F20+L20), ""), ""), "") | P20: =IFERROR(__xludf.DUMMYFUNCTION("IF(AND($R20, NOT(REGEXMATCH(UPPER($C20), ""INS""))), IFERROR(IF((F20+L20)>0, (F20+L20-M20)/(F20+L20), """"), """"), """")"),"") | Q20: =IFERROR(__xludf.DUMMYFUNCTION("IF(AND($R20, REGEXMATCH(UPPER($C20), ""INS"")), IFERROR(IF((F20+L20)>0, (F20+L20-M20)/(F20+L20), """"), """"), """")"),"") | R20: FALSE | S20: FALSE | T20: FALSE | U20: Job Scheduled | V20: FALSE | W20: =O20 | X20: =J20 | Y20: =F20 -> 5480 | Z20: =L20 | AA20: =IFERROR(__xludf.DUMMYFUNCTION("""COMPUTED_VALUE"""),"Drew") -> Drew | AB20: =K20
A21: 2266 | B21: 20265020 | C21: Gianghua Gao | E21: 46080 | F21: 590 | I21: Brett | J21: 590 | K21: 590 | L21: =if(S21=TRUE,K21-F21,"") -> 0 | N21: =if(S21=TRUE,K21-M21,"") -> 590 | O21: =IF($R21, IFERROR(IF((F21+L21)>0, (F21+L21-M21)/(F21+L21), ""), ""), "") -> 1 | P21: =IFERROR(__xludf.DUMMYFUNCTION("IF(AND($R21, NOT(REGEXMATCH(UPPER($C21), ""INS""))), IFERROR(IF((F21+L21)>0, (F21+L21-M21)/(F21+L21), """"), """"), """")"),1.0) -> 1 | Q21: =IFERROR(__xludf.DUMMYFUNCTION("IF(AND($R21, REGEXMATCH(UPPER($C21), ""INS"")), IFERROR(IF((F21+L21)>0, (F21+L21-M21)/(F21+L21), """"), """"), """")"),"") | R21: TRUE | S21: TRUE | T21: FALSE | U21: In Billing | V21: FALSE | W21: =O21 -> 1 | X21: =J21 -> 590 | Y21: =F21 -> 590 | Z21: =L21 -> 0 | AA21: =IFERROR(__xludf.DUMMYFUNCTION("""COMPUTED_VALUE"""),"Drew") -> Drew | AB21: =K21 -> 590
A22: 2002 | B22: 20265021 | C22: Mary Peitsmeyer | E22: 46081 | F22: 17780.69 | G22: 04/16/2026 | H22: 04/16/2026 | I22: Drew | L22: =if(S22=TRUE,K22-F22,"") | N22: =if(S22=TRUE,K22-M22,"") | O22: =IF($R22, IFERROR(IF((F22+L22)>0, (F22+L22-M22)/(F22+L22), ""), ""), "") | P22: =IFERROR(__xludf.DUMMYFUNCTION("IF(AND($R22, NOT(REGEXMATCH(UPPER($C22), ""INS""))), IFERROR(IF((F22+L22)>0, (F22+L22-M22)/(F22+L22), """"), """"), """")"),"") | Q22: =IFERROR(__xludf.DUMMYFUNCTION("IF(AND($R22, REGEXMATCH(UPPER($C22), ""INS"")), IFERROR(IF((F22+L22)>0, (F22+L22-M22)/(F22+L22), """"), """"), """")"),"") | R22: FALSE | S22: FALSE | T22: FALSE | U22: Job Scheduled | V22: FALSE | W22: =O22 | X22: =J22 | Y22: =F22 -> 17780.69 | Z22: =L22 | AA22: =IFERROR(__xludf.DUMMYFUNCTION("""COMPUTED_VALUE"""),"Drew") -> Drew | AB22: =K22
A23: 2257 | B23: 20265022 | C23: James Lintz | E23: 46083 | F23: 590 | G23: 03/12/2026 | H23: 03/12/2026 | I23: Brett | J23: 590 | K23: 590 | L23: =if(S23=TRUE,K23-F23,"") -> 0 | N23: =if(S23=TRUE,K23-M23,"") -> 590 | O23: =IF($R23, IFERROR(IF((F23+L23)>0, (F23+L23-M23)/(F23+L23), ""), ""), "") -> 1 | P23: =IFERROR(__xludf.DUMMYFUNCTION("IF(AND($R23, NOT(REGEXMATCH(UPPER($C23), ""INS""))), IFERROR(IF((F23+L23)>0, (F23+L23-M23)/(F23+L23), """"), """"), """")"),1.0) -> 1 | Q23: =IFERROR(__xludf.DUMMYFUNCTION("IF(AND($R23, REGEXMATCH(UPPER($C23), ""INS"")), IFERROR(IF((F23+L23)>0, (F23+L23-M23)/(F23+L23), """"), """"), """")"),"") | R23: TRUE | S23: TRUE | T23: FALSE | U23: In Billing | V23: FALSE | W23: =O23 -> 1 | X23: =J23 -> 590 | Y23: =F23 -> 590 | Z23: =L23 -> 0 | AA23: =IFERROR(__xludf.DUMMYFUNCTION("""COMPUTED_VALUE"""),"Drew") -> Drew | AB23: =K23 -> 590
A24: 2284 | B24: 20265023 | C24: Jessica Lansford | E24: 46085 | F24: 271.5 | I24: Adam | J24: 271.5 | K24: 271.5 | L24: =if(S24=TRUE,K24-F24,"") -> 0 | M24: 11.25 | N24: =if(S24=TRUE,K24-M24,"") -> 260.25 | O24: =IF($R24, IFERROR(IF((F24+L24)>0, (F24+L24-M24)/(F24+L24), ""), ""), "") -> 0.95856354 | P24: =IFERROR(__xludf.DUMMYFUNCTION("IF(AND($R24, NOT(REGEXMATCH(UPPER($C24), ""INS""))), IFERROR(IF((F24+L24)>0, (F24+L24-M24)/(F24+L24), """"), """"), """")"),0.9585635359116023) -> 0.95856354 | Q24: =IFERROR(__xludf.DUMMYFUNCTION("IF(AND($R24, REGEXMATCH(UPPER($C24), ""INS"")), IFERROR(IF((F24+L24)>0, (F24+L24-M24)/(F24+L24), """"), """"), """")"),"") | R24: TRUE | S24: TRUE | T24: TRUE | U24: In Billing | V24: FALSE | W24: =O24 -> 0.95856354 | X24: =J24 -> 271.5 | Y24: =F24 -> 271.5 | Z24: =L24 -> 0 | AA24: =IFERROR(__xludf.DUMMYFUNCTION("""COMPUTED_VALUE"""),"Drew") -> Drew | AB24: =K24 -> 271.5
A25: 2287 | B25: 20265024 | C25: William Barrett | E25: 46086 | F25: 506.25 | I25: James | J25: 506.25 | K25: 506.25 | L25: =if(S25=TRUE,K25-F25,"") -> 0 | M25: 250 | N25: =if(S25=TRUE,K25-M25,"") -> 256.25 | O25: =IF($R25, IFERROR(IF((F25+L25)>0, (F25+L25-M25)/(F25+L25), ""), ""), "") -> 0.50617284 | P25: =IFERROR(__xludf.DUMMYFUNCTION("IF(AND($R25, NOT(REGEXMATCH(UPPER($C25), ""INS""))), IFERROR(IF((F25+L25)>0, (F25+L25-M25)/(F25+L25), """"), """"), """")"),0.5061728395061729) -> 0.50617284 | Q25: =IFERROR(__xludf.DUMMYFUNCTION("IF(AND($R25, REGEXMATCH(UPPER($C25), ""INS"")), IFERROR(IF((F25+L25)>0, (F25+L25-M25)/(F25+L25), """"), """"), """")"),"") | R25: TRUE | S25: TRUE | T25: FALSE | U25: In Billing | V25: FALSE | W25: =O25 -> 0.50617284 | X25: =J25 -> 506.25 | Y25: =F25 -> 506.25 | Z25: =L25 -> 0 | AA25: =IFERROR(__xludf.DUMMYFUNCTION("""COMPUTED_VALUE"""),"Drew") -> Drew | AB25: =K25 -> 506.25
A26: 1261 | B26: 20265025 | C26: Becky Fiessinger | E26: 46088 | F26: 24570 | G26: 04/09/2026 | H26: 04/09/2026 | I26: Brett | J26: 25560 | K26: 25560 | L26: =if(S26=TRUE,K26-F26,"") -> 990 | M26: 16161.23 | N26: =if(S26=TRUE,K26-M26,"") -> 9398.77 | O26: =IF($R26, IFERROR(IF((F26+L26)>0, (F26+L26-M26)/(F26+L26), ""), ""), "") -> 0.36771401 | P26: =IFERROR(__xludf.DUMMYFUNCTION("IF(AND($R26, NOT(REGEXMATCH(UPPER($C26), ""INS""))), IFERROR(IF((F26+L26)>0, (F26+L26-M26)/(F26+L26), """"), """"), """")"),0.3677140062597809) -> 0.36771401 | Q26: =IFERROR(__xludf.DUMMYFUNCTION("IF(AND($R26, REGEXMATCH(UPPER($C26), ""INS"")), IFERROR(IF((F26+L26)>0, (F26+L26-M26)/(F26+L26), """"), """"), """")"),"") | R26: TRUE | S26: TRUE | T26: FALSE | U26: Job Review | V26: FALSE | W26: =O26 -> 0.36771401 | X26: =J26 -> 25560 | Y26: =F26 -> 24570 | Z26: =L26 -> 990 | AA26: =IFERROR(__xludf.DUMMYFUNCTION("""COMPUTED_VALUE"""),"") | AB26: =K26 -> 25560
A27: 2102 | B27: 20265026 | C27: INS - Josh Gates | E27: 46088 | F27: 0 | I27: James | L27: =if(S27=TRUE,K27-F27,"") | N27: =if(S27=TRUE,K27-M27,"") | O27: =IF($R27, IFERROR(IF((F27+L27)>0, (F27+L27-M27)/(F27+L27), ""), ""), "") | P27: =IFERROR(__xludf.DUMMYFUNCTION("IF(AND($R27, NOT(REGEXMATCH(UPPER($C27), ""INS""))), IFERROR(IF((F27+L27)>0, (F27+L27-M27)/(F27+L27), """"), """"), """")"),"") | Q27: =IFERROR(__xludf.DUMMYFUNCTION("IF(AND($R27, REGEXMATCH(UPPER($C27), ""INS"")), IFERROR(IF((F27+L27)>0, (F27+L27-M27)/(F27+L27), """"), """"), """")"),"") | R27: FALSE | S27: FALSE | T27: FALSE | U27: Approved | V27: FALSE | W27: =O27 | X27: =J27 | Y27: =F27 -> 0 | Z27: =L27 | AA27: =IFERROR(__xludf.DUMMYFUNCTION("""COMPUTED_VALUE"""),"Drew") -> Drew | AB27: =K27
A28: 2288 | B28: 20265027 | C28: John Baumann | E28: 46090 | F28: 0 | I28: Chris | L28: =if(S28=TRUE,K28-F28,"") | N28: =if(S28=TRUE,K28-M28,"") | O28: =IF($R28, IFERROR(IF((F28+L28)>0, (F28+L28-M28)/(F28+L28), ""), ""), "") | P28: =IFERROR(__xludf.DUMMYFUNCTION("IF(AND($R28, NOT(REGEXMATCH(UPPER($C28), ""INS""))), IFERROR(IF((F28+L28)>0, (F28+L28-M28)/(F28+L28), """"), """"), """")"),"") | Q28: =IFERROR(__xludf.DUMMYFUNCTION("IF(AND($R28, REGEXMATCH(UPPER($C28), ""INS"")), IFERROR(IF((F28+L28)>0, (F28+L28-M28)/(F28+L28), """"), """"), """")"),"") | R28: FALSE | S28: FALSE | T28: FALSE | U28: Approved | V28: FALSE | W28: =O28 | X28: =J28 | Y28: =F28 -> 0 | Z28: =L28 | AA28: =IFERROR(__xludf.DUMMYFUNCTION("""COMPUTED_VALUE"""),"Drew") -> Drew | AB28: =K28
A29: 2293 | B29: 20265028 | C29: Andrew Wasouf | E29: 46090 | F29: 593.72 | G29: 03/27/2026 | H29: 03/27/2026 | I29: James | J29: 593.72 | K29: 593.72 | L29: =if(S29=TRUE,K29-F29,"") -> 0 | M29: 293 | N29: =if(S29=TRUE,K29-M29,"") -> 300.72 | O29: =IF($R29, IFERROR(IF((F29+L29)>0, (F29+L29-M29)/(F29+L29), ""), ""), "") -> 0.50650138 | P29: =IFERROR(__xludf.DUMMYFUNCTION("IF(AND($R29, NOT(REGEXMATCH(UPPER($C29), ""INS""))), IFERROR(IF((F29+L29)>0, (F29+L29-M29)/(F29+L29), """"), """"), """")"),0.5065013811224146) -> 0.50650138 | Q29: =IFERROR(__xludf.DUMMYFUNCTION("IF(AND($R29, REGEXMATCH(UPPER($C29), ""INS"")), IFERROR(IF((F29+L29)>0, (F29+L29-M29)/(F29+L29), """"), """"), """")"),"") | R29: TRUE | S29: TRUE | T29: FALSE | U29: In Billing | V29: FALSE | W29: =O29 -> 0.50650138 | X29: =J29 -> 593.72 | Y29: =F29 -> 593.72 | Z29: =L29 -> 0 | AA29: =IFERROR(__xludf.DUMMYFUNCTION("""COMPUTED_VALUE"""),"Drew") -> Drew | AB29: =K29 -> 593.72
A30: 2175 | B30: 20265029 | C30: Joe Fiorita | E30: 46091 | F30: 630 | G30: 04/16/2026 | H30: 04/16/2026 | I30: Brett | J30: 630 | L30: =if(S30=TRUE,K30-F30,"") | M30: 290.67 | N30: =if(S30=TRUE,K30-M30,"") | O30: =IF($R30, IFERROR(IF((F30+L30)>0, (F30+L30-M30)/(F30+L30), ""), ""), "") -> 0.53861905 | P30: =IFERROR(__xludf.DUMMYFUNCTION("IF(AND($R30, NOT(REGEXMATCH(UPPER($C30), ""INS""))), IFERROR(IF((F30+L30)>0, (F30+L30-M30)/(F30+L30), """"), """"), """")"),0.5386190476190476) -> 0.53861905 | Q30: =IFERROR(__xludf.DUMMYFUNCTION("IF(AND($R30, REGEXMATCH(UPPER($C30), ""INS"")), IFERROR(IF((F30+L30)>0, (F30+L30-M30)/(F30+L30), """"), """"), """")"),"") | R30: TRUE | S30: FALSE | T30: FALSE | U30: Job Scheduled | V30: FALSE | W30: =O30 -> 0.53861905 | X30: =J30 -> 630 | Y30: =F30 -> 630 | Z30: =L30 | AA30: =IFERROR(__xludf.DUMMYFUNCTION("""COMPUTED_VALUE"""),"Drew") -> Drew | AB30: =K30
A31: 2301 | B31: 20265030 | C31: INS - Randy Brinkman | E31: 46092 | F31: 0 | I31: James | L31: =if(S31=TRUE,K31-F31,"") | N31: =if(S31=TRUE,K31-M31,"") | O31: =IF($R31, IFERROR(IF((F31+L31)>0, (F31+L31-M31)/(F31+L31), ""), ""), "") | P31: =IFERROR(__xludf.DUMMYFUNCTION("IF(AND($R31, NOT(REGEXMATCH(UPPER($C31), ""INS""))), IFERROR(IF((F31+L31)>0, (F31+L31-M31)/(F31+L31), """"), """"), """")"),"") | Q31: =IFERROR(__xludf.DUMMYFUNCTION("IF(AND($R31, REGEXMATCH(UPPER($C31), ""INS"")), IFERROR(IF((F31+L31)>0, (F31+L31-M31)/(F31+L31), """"), """"), """")"),"") | R31: FALSE | S31: FALSE | T31: FALSE | U31: Approved | V31: FALSE | W31: =O31 | X31: =J31 | Y31: =F31 -> 0 | Z31: =L31 | AA31: =IFERROR(__xludf.DUMMYFUNCTION("""COMPUTED_VALUE"""),"Drew") -> Drew | AB31: =K31
A32: 1344 | B32: 20265031 | C32: INS - Pastor David Douglas's home | E32: 46094 | F32: 33908.02 | I32: Chris | L32: =if(S32=TRUE,K32-F32,"") | N32: =if(S32=TRUE,K32-M32,"") | O32: =IF($R32, IFERROR(IF((F32+L32)>0, (F32+L32-M32)/(F32+L32), ""), ""), "") | P32: =IFERROR(__xludf.DUMMYFUNCTION("IF(AND($R32, NOT(REGEXMATCH(UPPER($C32), ""INS""))), IFERROR(IF((F32+L32)>0, (F32+L32-M32)/(F32+L32), """"), """"), """")"),"") | Q32: =IFERROR(__xludf.DUMMYFUNCTION("IF(AND($R32, REGEXMATCH(UPPER($C32), ""INS"")), IFERROR(IF((F32+L32)>0, (F32+L32-M32)/(F32+L32), """"), """"), """")"),"") | R32: FALSE | S32: FALSE | T32: FALSE | U32: Job Review | V32: FALSE | W32: =O32 | X32: =J32 | Y32: =F32 -> 33908.02 | Z32: =L32 | AA32: =IFERROR(__xludf.DUMMYFUNCTION("""COMPUTED_VALUE"""),"") | AB32: =K32
A33: 2312 | B33: 20265032 | C33: Rachel Conrad | E33: 46094 | F33: 0 | I33: James | L33: =if(S33=TRUE,K33-F33,"") | N33: =if(S33=TRUE,K33-M33,"") | O33: =IF($R33, IFERROR(IF((F33+L33)>0, (F33+L33-M33)/(F33+L33), ""), ""), "") | P33: =IFERROR(__xludf.DUMMYFUNCTION("IF(AND($R33, NOT(REGEXMATCH(UPPER($C33), ""INS""))), IFERROR(IF((F33+L33)>0, (F33+L33-M33)/(F33+L33), """"), """"), """")"),"") | Q33: =IFERROR(__xludf.DUMMYFUNCTION("IF(AND($R33, REGEXMATCH(UPPER($C33), ""INS"")), IFERROR(IF((F33+L33)>0, (F33+L33-M33)/(F33+L33), """"), """"), """")"),"") | R33: FALSE | S33: FALSE | T33: FALSE | U33: Approved | V33: FALSE | W33: =O33 | X33: =J33 | Y33: =F33 -> 0 | Z33: =L33 | AA33: =IFERROR(__xludf.DUMMYFUNCTION("""COMPUTED_VALUE"""),"Drew") -> Drew | AB33: =K33
A34: 2318 | B34: 20265033 | C34: Ralph Lowe | E34: 46094 | F34: 0 | I34: James | L34: =if(S34=TRUE,K34-F34,"") | N34: =if(S34=TRUE,K34-M34,"") | O34: =IF($R34, IFERROR(IF((F34+L34)>0, (F34+L34-M34)/(F34+L34), ""), ""), "") | P34: =IFERROR(__xludf.DUMMYFUNCTION("IF(AND($R34, NOT(REGEXMATCH(UPPER($C34), ""INS""))), IFERROR(IF((F34+L34)>0, (F34+L34-M34)/(F34+L34), """"), """"), """")"),"") | Q34: =IFERROR(__xludf.DUMMYFUNCTION("IF(AND($R34, REGEXMATCH(UPPER($C34), ""INS"")), IFERROR(IF((F34+L34)>0, (F34+L34-M34)/(F34+L34), """"), """"), """")"),"") | R34: FALSE | S34: FALSE | T34: FALSE | U34: Approved | V34: FALSE | W34: =O34 | X34: =J34 | Y34: =F34 -> 0 | Z34: =L34 | AA34: =IFERROR(__xludf.DUMMYFUNCTION("""COMPUTED_VALUE"""),"Drew") -> Drew | AB34: =K34
A35: 2329 | B35: 20265034 | C35: INS - Alicia Luedeke | E35: 46095 | F35: 15106.78 | G35: 04/07/2026 | H35: 04/07/2026 | I35: James | J35: 8340.95 | L35: =if(S35=TRUE,K35-F35,"") | N35: =if(S35=TRUE,K35-M35,"") | O35: =IF($R35, IFERROR(IF((F35+L35)>0, (F35+L35-M35)/(F35+L35), ""), ""), "") -> 1 | P35: =IFERROR(__xludf.DUMMYFUNCTION("IF(AND($R35, NOT(REGEXMATCH(UPPER($C35), ""INS""))), IFERROR(IF((F35+L35)>0, (F35+L35-M35)/(F35+L35), """"), """"), """")"),"") | Q35: =IFERROR(__xludf.DUMMYFUNCTION("IF(AND($R35, REGEXMATCH(UPPER($C35), ""INS"")), IFERROR(IF((F35+L35)>0, (F35+L35-M35)/(F35+L35), """"), """"), """")"),1.0) -> 1 | R35: TRUE | S35: FALSE | T35: FALSE | U35: Job Review | V35: FALSE | W35: =O35 -> 1 | X35: =J35 -> 8340.95 | Y35: =F35 -> 15106.78 | Z35: =L35 | AA35: =IFERROR(__xludf.DUMMYFUNCTION("""COMPUTED_VALUE"""),"Drew") -> Drew | AB35: =K35
A36: 2341 | B36: 20265035 | C36: Grant Pace | E36: 46095 | F36: 17037.2 | G36: 04/30/2026 | H36: 04/29/2026 | I36: James | L36: =if(S36=TRUE,K36-F36,"") | N36: =if(S36=TRUE,K36-M36,"") | O36: =IF($R36, IFERROR(IF((F36+L36)>0, (F36+L36-M36)/(F36+L36), ""), ""), "") | P36: =IFERROR(__xludf.DUMMYFUNCTION("IF(AND($R36, NOT(REGEXMATCH(UPPER($C36), ""INS""))), IFERROR(IF((F36+L36)>0, (F36+L36-M36)/(F36+L36), """"), """"), """")"),"") | Q36: =IFERROR(__xludf.DUMMYFUNCTION("IF(AND($R36, REGEXMATCH(UPPER($C36), ""INS"")), IFERROR(IF((F36+L36)>0, (F36+L36-M36)/(F36+L36), """"), """"), """")"),"") | R36: FALSE | S36: FALSE | T36: FALSE | U36: Job Scheduled | V36: FALSE | W36: =O36 | X36: =J36 | Y36: =F36 -> 17037.2 | Z36: =L36 | AA36: =IFERROR(__xludf.DUMMYFUNCTION("""COMPUTED_VALUE"""),"Drew") -> Drew | AB36: =K36
A37: 2331 | B37: 20265036 | C37: INS - Brady Dowler | E37: 46095 | F37: 0 | I37: Drew | L37: =if(S37=TRUE,K37-F37,"") | N37: =if(S37=TRUE,K37-M37,"") | O37: =IF($R37, IFERROR(IF((F37+L37)>0, (F37+L37-M37)/(F37+L37), ""), ""), "") | P37: =IFERROR(__xludf.DUMMYFUNCTION("IF(AND($R37, NOT(REGEXMATCH(UPPER($C37), ""INS""))), IFERROR(IF((F37+L37)>0, (F37+L37-M37)/(F37+L37), """"), """"), """")"),"") | Q37: =IFERROR(__xludf.DUMMYFUNCTION("IF(AND($R37, REGEXMATCH(UPPER($C37), ""INS"")), IFERROR(IF((F37+L37)>0, (F37+L37-M37)/(F37+L37), """"), """"), """")"),"") | R37: FALSE | S37: FALSE | T37: FALSE | U37: Approved | V37: FALSE | W37: =O37 | X37: =J37 | Y37: =F37 -> 0 | Z37: =L37 | AA37: =IFERROR(__xludf.DUMMYFUNCTION("""COMPUTED_VALUE"""),"Drew") -> Drew | AB37: =K37
A38: 2361 | B38: 20265037 | C38: INS - Chris Browning | E38: 46096 | F38: 0 | I38: Chris | L38: =if(S38=TRUE,K38-F38,"") | N38: =if(S38=TRUE,K38-M38,"") | O38: =IF($R38, IFERROR(IF((F38+L38)>0, (F38+L38-M38)/(F38+L38), ""), ""), "") | P38: =IFERROR(__xludf.DUMMYFUNCTION("IF(AND($R38, NOT(REGEXMATCH(UPPER($C38), ""INS""))), IFERROR(IF((F38+L38)>0, (F38+L38-M38)/(F38+L38), """"), """"), """")"),"") | Q38: =IFERROR(__xludf.DUMMYFUNCTION("IF(AND($R38, REGEXMATCH(UPPER($C38), ""INS"")), IFERROR(IF((F38+L38)>0, (F38+L38-M38)/(F38+L38), """"), """"), """")"),"") | R38: FALSE | S38: FALSE | T38: FALSE | U38: Approved | V38: FALSE | W38: =O38 | X38: =J38 | Y38: =F38 -> 0 | Z38: =L38 | AA38: =IFERROR(__xludf.DUMMYFUNCTION("""COMPUTED_VALUE"""),"Drew") -> Drew | AB38: =K38
A39: 2353 | B39: 20265038 | C39: INS - Matt Clifton | E39: 46096 | F39: 24328.8 | G39: 04/27/2026 | H39: 04/28/2026 | I39: Chris | L39: =if(S39=TRUE,K39-F39,"") | N39: =if(S39=TRUE,K39-M39,"") | O39: =IF($R39, IFERROR(IF((F39+L39)>0, (F39+L39-M39)/(F39+L39), ""), ""), "") | P39: =IFERROR(__xludf.DUMMYFUNCTION("IF(AND($R39, NOT(REGEXMATCH(UPPER($C39), ""INS""))), IFERROR(IF((F39+L39)>0, (F39+L39-M39)/(F39+L39), """"), """"), """")"),"") | Q39: =IFERROR(__xludf.DUMMYFUNCTION("IF(AND($R39, REGEXMATCH(UPPER($C39), ""INS"")), IFERROR(IF((F39+L39)>0, (F39+L39-M39)/(F39+L39), """"), """"), """")"),"") | R39: FALSE | S39: FALSE | T39: FALSE | U39: Job Scheduled | V39: FALSE | W39: =O39 | X39: =J39 | Y39: =F39 -> 24328.8 | Z39: =L39 | AA39: =IFERROR(__xludf.DUMMYFUNCTION("""COMPUTED_VALUE"""),"Drew") -> Drew | AB39: =K39
A40: 2364 | B40: 20265039 | C40: Jason Schaefer | E40: 46096 | F40: 0 | I40: James | L40: =if(S40=TRUE,K40-F40,"") | N40: =if(S40=TRUE,K40-M40,"") | O40: =IF($R40, IFERROR(IF((F40+L40)>0, (F40+L40-M40)/(F40+L40), ""), ""), "") | P40: =IFERROR(__xludf.DUMMYFUNCTION("IF(AND($R40, NOT(REGEXMATCH(UPPER($C40), ""INS""))), IFERROR(IF((F40+L40)>0, (F40+L40-M40)/(F40+L40), """"), """"), """")"),"") | Q40: =IFERROR(__xludf.DUMMYFUNCTION("IF(AND($R40, REGEXMATCH(UPPER($C40), ""INS"")), IFERROR(IF((F40+L40)>0, (F40+L40-M40)/(F40+L40), """"), """"), """")"),"") | R40: FALSE | S40: FALSE | T40: FALSE | U40: Approved | V40: FALSE | W40: =O40 | X40: =J40 | Y40: =F40 -> 0 | Z40: =L40 | AA40: =IFERROR(__xludf.DUMMYFUNCTION("""COMPUTED_VALUE"""),"Drew") -> Drew | AB40: =K40
A41: 2300 | B41: 20265040 | C41: Kathie Abke | E41: 46096 | F41: 1430 | G41: 04/16/2026 | H41: 04/16/2026 | I41: Brett | J41: 1430 | L41: =if(S41=TRUE,K41-F41,"") | N41: =if(S41=TRUE,K41-M41,"") | O41: =IF($R41, IFERROR(IF((F41+L41)>0, (F41+L41-M41)/(F41+L41), ""), ""), "") -> 1 | P41: =IFERROR(__xludf.DUMMYFUNCTION("IF(AND($R41, NOT(REGEXMATCH(UPPER($C41), ""INS""))), IFERROR(IF((F41+L41)>0, (F41+L41-M41)/(F41+L41), """"), """"), """")"),1.0) -> 1 | Q41: =IFERROR(__xludf.DUMMYFUNCTION("IF(AND($R41, REGEXMATCH(UPPER($C41), ""INS"")), IFERROR(IF((F41+L41)>0, (F41+L41-M41)/(F41+L41), """"), """"), """")"),"") | R41: TRUE | S41: FALSE | T41: FALSE | U41: Job Scheduled | V41: FALSE | W41: =O41 -> 1 | X41: =J41 -> 1430 | Y41: =F41 -> 1430 | Z41: =L41 | AA41: =IFERROR(__xludf.DUMMYFUNCTION("""COMPUTED_VALUE"""),"Drew") -> Drew | AB41: =K41
A42: 2333 | B42: 20265041 | C42: INS - Roben Hamilton | E42: 46096 | F42: 26541.18 | G42: 04/09/2026 | H42: 04/09/2026 | I42: James | J42: 15427.44 | K42: 15427.44 | L42: =if(S42=TRUE,K42-F42,"") | N42: =if(S42=TRUE,K42-M42,"") | O42: =IF($R42, IFERROR(IF((F42+L42)>0, (F42+L42-M42)/(F42+L42), ""), ""), "") -> 1 | P42: =IFERROR(__xludf.DUMMYFUNCTION("IF(AND($R42, NOT(REGEXMATCH(UPPER($C42), ""INS""))), IFERROR(IF((F42+L42)>0, (F42+L42-M42)/(F42+L42), """"), """"), """")"),"") | Q42: =IFERROR(__xludf.DUMMYFUNCTION("IF(AND($R42, REGEXMATCH(UPPER($C42), ""INS"")), IFERROR(IF((F42+L42)>0, (F42+L42-M42)/(F42+L42), """"), """"), """")"),1.0) -> 1 | R42: TRUE | S42: FALSE | T42: TRUE | U42: Job Review | V42: FALSE | W42: =O42 -> 1 | X42: =J42 -> 15427.44 | Y42: =F42 -> 26541.18 | Z42: =L42 | AA42: =IFERROR(__xludf.DUMMYFUNCTION("""COMPUTED_VALUE"""),"Drew") -> Drew | AB42: =K42 -> 15427.44
A43: 1691 | B43: 20265042 | C43: Steve And Margaret Callon | E43: 46096 | F43: 5376.37 | G43: 04/20/2026 | H43: 04/20/2026 | I43: Mike | L43: =if(S43=TRUE,K43-F43,"") | N43: =if(S43=TRUE,K43-M43,"") | O43: =IF($R43, IFERROR(IF((F43+L43)>0, (F43+L43-M43)/(F43+L43), ""), ""), "") | P43: =IFERROR(__xludf.DUMMYFUNCTION("IF(AND($R43, NOT(REGEXMATCH(UPPER($C43), ""INS""))), IFERROR(IF((F43+L43)>0, (F43+L43-M43)/(F43+L43), """"), """"), """")"),"") | Q43: =IFERROR(__xludf.DUMMYFUNCTION("IF(AND($R43, REGEXMATCH(UPPER($C43), ""INS"")), IFERROR(IF((F43+L43)>0, (F43+L43-M43)/(F43+L43), """"), """"), """")"),"") | R43: FALSE | S43: FALSE | T43: FALSE | U43: Job Scheduled | V43: FALSE | W43: =O43 | X43: =J43 | Y43: =F43 -> 5376.37 | Z43: =L43 | AA43: =IFERROR(__xludf.DUMMYFUNCTION("""COMPUTED_VALUE"""),"") | AB43: =K43
A44: 2340 | B44: 20265043 | C44: Russell Hawkins | E44: 46097 | F44: 896.38 | G44: 04/17/2026 | H44: 04/17/2026 | I44: Drew | L44: =if(S44=TRUE,K44-F44,"") | N44: =if(S44=TRUE,K44-M44,"") | O44: =IF($R44, IFERROR(IF((F44+L44)>0, (F44+L44-M44)/(F44+L44), ""), ""), "") | P44: =IFERROR(__xludf.DUMMYFUNCTION("IF(AND($R44, NOT(REGEXMATCH(UPPER($C44), ""INS""))), IFERROR(IF((F44+L44)>0, (F44+L44-M44)/(F44+L44), """"), """"), """")"),"") | Q44: =IFERROR(__xludf.DUMMYFUNCTION("IF(AND($R44, REGEXMATCH(UPPER($C44), ""INS"")), IFERROR(IF((F44+L44)>0, (F44+L44-M44)/(F44+L44), """"), """"), """")"),"") | R44: FALSE | S44: FALSE | T44: FALSE | U44: In Progress | V44: FALSE | W44: =O44 | X44: =J44 | Y44: =F44 -> 896.38 | Z44: =L44 | AA44: =IFERROR(__xludf.DUMMYFUNCTION("""COMPUTED_VALUE"""),"Drew") -> Drew | AB44: =K44
A45: 2347 | B45: 20265044 | C45: INS - Vicki Jones | E45: 46097 | F45: 0 | I45: James | L45: =if(S45=TRUE,K45-F45,"") | N45: =if(S45=TRUE,K45-M45,"") | O45: =IF($R45, IFERROR(IF((F45+L45)>0, (F45+L45-M45)/(F45+L45), ""), ""), "") | P45: =IFERROR(__xludf.DUMMYFUNCTION("IF(AND($R45, NOT(REGEXMATCH(UPPER($C45), ""INS""))), IFERROR(IF((F45+L45)>0, (F45+L45-M45)/(F45+L45), """"), """"), """")"),"") | Q45: =IFERROR(__xludf.DUMMYFUNCTION("IF(AND($R45, REGEXMATCH(UPPER($C45), ""INS"")), IFERROR(IF((F45+L45)>0, (F45+L45-M45)/(F45+L45), """"), """"), """")"),"") | R45: FALSE | S45: FALSE | T45: FALSE | U45: Approved | V45: FALSE | W45: =O45 | X45: =J45 | Y45: =F45 -> 0 | Z45: =L45 | AA45: =IFERROR(__xludf.DUMMYFUNCTION("""COMPUTED_VALUE"""),"Drew") -> Drew | AB45: =K45
A46: 2336 | B46: 20265045 | C46: Nate Beaman | E46: 46097 | F46: 0 | I46: James | L46: =if(S46=TRUE,K46-F46,"") | N46: =if(S46=TRUE,K46-M46,"") | O46: =IF($R46, IFERROR(IF((F46+L46)>0, (F46+L46-M46)/(F46+L46), ""), ""), "") | P46: =IFERROR(__xludf.DUMMYFUNCTION("IF(AND($R46, NOT(REGEXMATCH(UPPER($C46), ""INS""))), IFERROR(IF((F46+L46)>0, (F46+L46-M46)/(F46+L46), """"), """"), """")"),"") | Q46: =IFERROR(__xludf.DUMMYFUNCTION("IF(AND($R46, REGEXMATCH(UPPER($C46), ""INS"")), IFERROR(IF((F46+L46)>0, (F46+L46-M46)/(F46+L46), """"), """"), """")"),"") | R46: FALSE | S46: FALSE | T46: FALSE | U46: Approved | V46: FALSE | W46: =O46 | X46: =J46 | Y46: =F46 -> 0 | Z46: =L46 | AA46: =IFERROR(__xludf.DUMMYFUNCTION("""COMPUTED_VALUE"""),"Drew") -> Drew | AB46: =K46
A47: 2320 | B47: 20265046 | C47: INS - Dennis Fine | E47: 46097 | F47: 21350.56 | G47: 04/23/2026 | H47: 04/23/2026 | I47: James | J47: 18011.86 | K47: 13258.9 | L47: =if(S47=TRUE,K47-F47,"") | N47: =if(S47=TRUE,K47-M47,"") | O47: =IF($R47, IFERROR(IF((F47+L47)>0, (F47+L47-M47)/(F47+L47), ""), ""), "") -> 1 | P47: =IFERROR(__xludf.DUMMYFUNCTION("IF(AND($R47, NOT(REGEXMATCH(UPPER($C47), ""INS""))), IFERROR(IF((F47+L47)>0, (F47+L47-M47)/(F47+L47), """"), """"), """")"),"") | Q47: =IFERROR(__xludf.DUMMYFUNCTION("IF(AND($R47, REGEXMATCH(UPPER($C47), ""INS"")), IFERROR(IF((F47+L47)>0, (F47+L47-M47)/(F47+L47), """"), """"), """")"),1.0) -> 1 | R47: TRUE | S47: FALSE | T47: TRUE | U47: Job Scheduled | V47: FALSE | W47: =O47 -> 1 | X47: =J47 -> 18011.86 | Y47: =F47 -> 21350.56 | Z47: =L47 | AA47: =IFERROR(__xludf.DUMMYFUNCTION("""COMPUTED_VALUE"""),"Drew") -> Drew | AB47: =K47 -> 13258.9
A48: 2145 | B48: 20265047 | C48: INS - Mike Wallace | E48: 46097 | F48: 17330.84 | G48: 04/20/2026 | H48: 04/20/2026 | I48: James | L48: =if(S48=TRUE,K48-F48,"") | N48: =if(S48=TRUE,K48-M48,"") | O48: =IF($R48, IFERROR(IF((F48+L48)>0, (F48+L48-M48)/(F48+L48), ""), ""), "") | P48: =IFERROR(__xludf.DUMMYFUNCTION("IF(AND($R48, NOT(REGEXMATCH(UPPER($C48), ""INS""))), IFERROR(IF((F48+L48)>0, (F48+L48-M48)/(F48+L48), """"), """"), """")"),"") | Q48: =IFERROR(__xludf.DUMMYFUNCTION("IF(AND($R48, REGEXMATCH(UPPER($C48), ""INS"")), IFERROR(IF((F48+L48)>0, (F48+L48-M48)/(F48+L48), """"), """"), """")"),"") | R48: FALSE | S48: FALSE | T48: FALSE | U48: Job Scheduled | V48: FALSE | W48: =O48 | X48: =J48 | Y48: =F48 -> 17330.84 | Z48: =L48 | AA48: =IFERROR(__xludf.DUMMYFUNCTION("""COMPUTED_VALUE"""),"Drew") -> Drew | AB48: =K48
A49: 2351 | B49: 20265048 | C49: INS - Dan Koval | E49: 46097 | F49: 17202.16 | G49: 03/26/2026 | H49: 03/26/2026 | I49: Chris | L49: =if(S49=TRUE,K49-F49,"") | N49: =if(S49=TRUE,K49-M49,"") | O49: =IF($R49, IFERROR(IF((F49+L49)>0, (F49+L49-M49)/(F49+L49), ""), ""), "") | P49: =IFERROR(__xludf.DUMMYFUNCTION("IF(AND($R49, NOT(REGEXMATCH(UPPER($C49), ""INS""))), IFERROR(IF((F49+L49)>0, (F49+L49-M49)/(F49+L49), """"), """"), """")"),"") | Q49: =IFERROR(__xludf.DUMMYFUNCTION("IF(AND($R49, REGEXMATCH(UPPER($C49), ""INS"")), IFERROR(IF((F49+L49)>0, (F49+L49-M49)/(F49+L49), """"), """"), """")"),"") | R49: FALSE | S49: FALSE | T49: FALSE | U49: Approved | V49: FALSE | W49: =O49 | X49: =J49 | Y49: =F49 -> 17202.16 | Z49: =L49 | AA49: =IFERROR(__xludf.DUMMYFUNCTION("""COMPUTED_VALUE"""),"Drew") -> Drew | AB49: =K49
A50: 2381 | B50: 20265049 | C50: INS - Shavon Puckett | E50: 46097 | F50: 0 | I50: Drew | L50: =if(S50=TRUE,K50-F50,"") | N50: =if(S50=TRUE,K50-M50,"") | O50: =IF($R50, IFERROR(IF((F50+L50)>0, (F50+L50-M50)/(F50+L50), ""), ""), "") | P50: =IFERROR(__xludf.DUMMYFUNCTION("IF(AND($R50, NOT(REGEXMATCH(UPPER($C50), ""INS""))), IFERROR(IF((F50+L50)>0, (F50+L50-M50)/(F50+L50), """"), """"), """")"),"") | Q50: =IFERROR(__xludf.DUMMYFUNCTION("IF(AND($R50, REGEXMATCH(UPPER($C50), ""INS"")), IFERROR(IF((F50+L50)>0, (F50+L50-M50)/(F50+L50), """"), """"), """")"),"") | R50: FALSE | S50: FALSE | T50: FALSE | U50: Approved | V50: FALSE | W50: =O50 | X50: =J50 | Y50: =F50 -> 0 | Z50: =L50 | AA50: =IFERROR(__xludf.DUMMYFUNCTION("""COMPUTED_VALUE"""),"Drew") -> Drew | AB50: =K50
A51: 2239 | B51: 20265050 | C51: Nick Robinson | E51: 46097 | F51: 0 | I51: James | L51: =if(S51=TRUE,K51-F51,"") | N51: =if(S51=TRUE,K51-M51,"") | O51: =IF($R51, IFERROR(IF((F51+L51)>0, (F51+L51-M51)/(F51+L51), ""), ""), "") | P51: =IFERROR(__xludf.DUMMYFUNCTION("IF(AND($R51, NOT(REGEXMATCH(UPPER($C51), ""INS""))), IFERROR(IF((F51+L51)>0, (F51+L51-M51)/(F51+L51), """"), """"), """")"),"") | Q51: =IFERROR(__xludf.DUMMYFUNCTION("IF(AND($R51, REGEXMATCH(UPPER($C51), ""INS"")), IFERROR(IF((F51+L51)>0, (F51+L51-M51)/(F51+L51), """"), """"), """")"),"") | R51: FALSE | S51: FALSE | T51: FALSE | U51: Approved | V51: FALSE | W51: =O51 | X51: =J51 | Y51: =F51 -> 0 | Z51: =L51 | AA51: =IFERROR(__xludf.DUMMYFUNCTION("""COMPUTED_VALUE"""),"Drew") -> Drew | AB51: =K51
A52: 2378 | B52: 20265051 | C52: INS - Margaret Vancauwenbergh | E52: 46097 | F52: 0 | I52: James | L52: =if(S52=TRUE,K52-F52,"") | N52: =if(S52=TRUE,K52-M52,"") | O52: =IF($R52, IFERROR(IF((F52+L52)>0, (F52+L52-M52)/(F52+L52), ""), ""), "") | P52: =IFERROR(__xludf.DUMMYFUNCTION("IF(AND($R52, NOT(REGEXMATCH(UPPER($C52), ""INS""))), IFERROR(IF((F52+L52)>0, (F52+L52-M52)/(F52+L52), """"), """"), """")"),"") | Q52: =IFERROR(__xludf.DUMMYFUNCTION("IF(AND($R52, REGEXMATCH(UPPER($C52), ""INS"")), IFERROR(IF((F52+L52)>0, (F52+L52-M52)/(F52+L52), """"), """"), """")"),"") | R52: FALSE | S52: FALSE | T52: FALSE | U52: Approved | V52: FALSE | W52: =O52 | X52: =J52 | Y52: =F52 -> 0 | Z52: =L52 | AA52: =IFERROR(__xludf.DUMMYFUNCTION("""COMPUTED_VALUE"""),"Drew") -> Drew | AB52: =K52
A53: 2349 | B53: 20265052 | C53: Braden Fisher | E53: 46097 | F53: 16132.31 | G53: 05/06/2026 | H53: 05/05/2026 | I53: Drew | L53: =if(S53=TRUE,K53-F53,"") | N53: =if(S53=TRUE,K53-M53,"") | O53: =IF($R53, IFERROR(IF((F53+L53)>0, (F53+L53-M53)/(F53+L53), ""), ""), "") | P53: =IFERROR(__xludf.DUMMYFUNCTION("IF(AND($R53, NOT(REGEXMATCH(UPPER($C53), ""INS""))), IFERROR(IF((F53+L53)>0, (F53+L53-M53)/(F53+L53), """"), """"), """")"),"") | Q53: =IFERROR(__xludf.DUMMYFUNCTION("IF(AND($R53, REGEXMATCH(UPPER($C53), ""INS"")), IFERROR(IF((F53+L53)>0, (F53+L53-M53)/(F53+L53), """"), """"), """")"),"") | R53: FALSE | S53: FALSE | T53: FALSE | U53: Job Scheduled | V53: FALSE | W53: =O53 | X53: =J53 | Y53: =F53 -> 16132.31 | Z53: =L53 | AA53: =IFERROR(__xludf.DUMMYFUNCTION("""COMPUTED_VALUE"""),"Drew") -> Drew | AB53: =K53
A54: 2397 | B54: 20265053 | C54: INS - Doug Sears | E54: 46097 | F54: 0 | I54: James | L54: =if(S54=TRUE,K54-F54,"") | N54: =if(S54=TRUE,K54-M54,"") | O54: =IF($R54, IFERROR(IF((F54+L54)>0, (F54+L54-M54)/(F54+L54), ""), ""), "") | P54: =IFERROR(__xludf.DUMMYFUNCTION("IF(AND($R54, NOT(REGEXMATCH(UPPER($C54), ""INS""))), IFERROR(IF((F54+L54)>0, (F54+L54-M54)/(F54+L54), """"), """"), """")"),"") | Q54: =IFERROR(__xludf.DUMMYFUNCTION("IF(AND($R54, REGEXMATCH(UPPER($C54), ""INS"")), IFERROR(IF((F54+L54)>0, (F54+L54-M54)/(F54+L54), """"), """"), """")"),"") | R54: FALSE | S54: FALSE | T54: FALSE | U54: Approved | V54: FALSE | W54: =O54 | X54: =J54 | Y54: =F54 -> 0 | Z54: =L54 | AA54: =IFERROR(__xludf.DUMMYFUNCTION("""COMPUTED_VALUE"""),"Drew") -> Drew | AB54: =K54
A55: 1651 | B55: 20265054 | C55: Paulette Schields | E55: 46097 | F55: 0 | I55: Drew | L55: =if(S55=TRUE,K55-F55,"") | N55: =if(S55=TRUE,K55-M55,"") | O55: =IF($R55, IFERROR(IF((F55+L55)>0, (F55+L55-M55)/(F55+L55), ""), ""), "") | P55: =IFERROR(__xludf.DUMMYFUNCTION("IF(AND($R55, NOT(REGEXMATCH(UPPER($C55), ""INS""))), IFERROR(IF((F55+L55)>0, (F55+L55-M55)/(F55+L55), """"), """"), """")"),"") | Q55: =IFERROR(__xludf.DUMMYFUNCTION("IF(AND($R55, REGEXMATCH(UPPER($C55), ""INS"")), IFERROR(IF((F55+L55)>0, (F55+L55-M55)/(F55+L55), """"), """"), """")"),"") | R55: FALSE | S55: FALSE | T55: FALSE | U55: Approved | V55: FALSE | W55: =O55 | X55: =J55 | Y55: =F55 -> 0 | Z55: =L55 | AA55: =IFERROR(__xludf.DUMMYFUNCTION("""COMPUTED_VALUE"""),"Drew") -> Drew | AB55: =K55
A56: 2399 | B56: 20265055 | C56: INS - Joe Kendal | E56: 46097 | F56: 0 | I56: James | L56: =if(S56=TRUE,K56-F56,"") | N56: =if(S56=TRUE,K56-M56,"") | O56: =IF($R56, IFERROR(IF((F56+L56)>0, (F56+L56-M56)/(F56+L56), ""), ""), "") | P56: =IFERROR(__xludf.DUMMYFUNCTION("IF(AND($R56, NOT(REGEXMATCH(UPPER($C56), ""INS""))), IFERROR(IF((F56+L56)>0, (F56+L56-M56)/(F56+L56), """"), """"), """")"),"") | Q56: =IFERROR(__xludf.DUMMYFUNCTION("IF(AND($R56, REGEXMATCH(UPPER($C56), ""INS"")), IFERROR(IF((F56+L56)>0, (F56+L56-M56)/(F56+L56), """"), """"), """")"),"") | R56: FALSE | S56: FALSE | T56: FALSE | U56: Approved | V56: FALSE | W56: =O56 | X56: =J56 | Y56: =F56 -> 0 | Z56: =L56 | AA56: =IFERROR(__xludf.DUMMYFUNCTION("""COMPUTED_VALUE"""),"Drew") -> Drew | AB56: =K56
A57: 2325 | B57: 20265056 | C57: INS - Mike Hild Rental | E57: 46097 | F57: 1321.13 | G57: 04/13/2026 | H57: 04/13/2026 | I57: James | L57: =if(S57=TRUE,K57-F57,"") | N57: =if(S57=TRUE,K57-M57,"") | O57: =IF($R57, IFERROR(IF((F57+L57)>0, (F57+L57-M57)/(F57+L57), ""), ""), "") | P57: =IFERROR(__xludf.DUMMYFUNCTION("IF(AND($R57, NOT(REGEXMATCH(UPPER($C57), ""INS""))), IFERROR(IF((F57+L57)>0, (F57+L57-M57)/(F57+L57), """"), """"), """")"),"") | Q57: =IFERROR(__xludf.DUMMYFUNCTION("IF(AND($R57, REGEXMATCH(UPPER($C57), ""INS"")), IFERROR(IF((F57+L57)>0, (F57+L57-M57)/(F57+L57), """"), """"), """")"),"") | R57: FALSE | S57: FALSE | T57: FALSE | U57: In Progress | V57: FALSE | W57: =O57 | X57: =J57 | Y57: =F57 -> 1321.13 | Z57: =L57 | AA57: =IFERROR(__xludf.DUMMYFUNCTION("""COMPUTED_VALUE"""),"Drew") -> Drew | AB57: =K57
A58: 2362 | B58: 20265057 | C58: INS - Keith Thomas | E58: 46097 | F58: 24164.98 | G58: 04/22/2026 | H58: 04/23/2026 | I58: Chris | L58: =if(S58=TRUE,K58-F58,"") | N58: =if(S58=TRUE,K58-M58,"") | O58: =IF($R58, IFERROR(IF((F58+L58)>0, (F58+L58-M58)/(F58+L58), ""), ""), "") | P58: =IFERROR(__xludf.DUMMYFUNCTION("IF(AND($R58, NOT(REGEXMATCH(UPPER($C58), ""INS""))), IFERROR(IF((F58+L58)>0, (F58+L58-M58)/(F58+L58), """"), """"), """")"),"") | Q58: =IFERROR(__xludf.DUMMYFUNCTION("IF(AND($R58, REGEXMATCH(UPPER($C58), ""INS"")), IFERROR(IF((F58+L58)>0, (F58+L58-M58)/(F58+L58), """"), """"), """")"),"") | R58: FALSE | S58: FALSE | T58: FALSE | U58: Job Scheduled | V58: FALSE | W58: =O58 | X58: =J58 | Y58: =F58 -> 24164.98 | Z58: =L58 | AA58: =IFERROR(__xludf.DUMMYFUNCTION("""COMPUTED_VALUE"""),"Drew") -> Drew | AB58: =K58
A59: 2393 | B59: 20265058 | C59: INS - Mohammed Hussain | E59: 46098 | F59: 29397.84 | I59: Mike | L59: =if(S59=TRUE,K59-F59,"") | N59: =if(S59=TRUE,K59-M59,"") | O59: =IF($R59, IFERROR(IF((F59+L59)>0, (F59+L59-M59)/(F59+L59), ""), ""), "") | P59: =IFERROR(__xludf.DUMMYFUNCTION("IF(AND($R59, NOT(REGEXMATCH(UPPER($C59), ""INS""))), IFERROR(IF((F59+L59)>0, (F59+L59-M59)/(F59+L59), """"), """"), """")"),"") | Q59: =IFERROR(__xludf.DUMMYFUNCTION("IF(AND($R59, REGEXMATCH(UPPER($C59), ""INS"")), IFERROR(IF((F59+L59)>0, (F59+L59-M59)/(F59+L59), """"), """"), """")"),"") | R59: FALSE | S59: FALSE | T59: FALSE | U59: In Progress | V59: FALSE | W59: =O59 | X59: =J59 | Y59: =F59 -> 29397.84 | Z59: =L59 | AA59: =IFERROR(__xludf.DUMMYFUNCTION("""COMPUTED_VALUE"""),"Drew") -> Drew | AB59: =K59
A60: 2408 | B60: 20265059 | C60: INS - Matt Snider | E60: 46098 | F60: 0 | I60: James | L60: =if(S60=TRUE,K60-F60,"") | N60: =if(S60=TRUE,K60-M60,"") | O60: =IF($R60, IFERROR(IF((F60+L60)>0, (F60+L60-M60)/(F60+L60), ""), ""), "") | P60: =IFERROR(__xludf.DUMMYFUNCTION("IF(AND($R60, NOT(REGEXMATCH(UPPER($C60), ""INS""))), IFERROR(IF((F60+L60)>0, (F60+L60-M60)/(F60+L60), """"), """"), """")"),"") | Q60: =IFERROR(__xludf.DUMMYFUNCTION("IF(AND($R60, REGEXMATCH(UPPER($C60), ""INS"")), IFERROR(IF((F60+L60)>0, (F60+L60-M60)/(F60+L60), """"), """"), """")"),"") | R60: FALSE | S60: FALSE | T60: FALSE | U60: Approved | V60: FALSE | W60: =O60 | X60: =J60 | Y60: =F60 -> 0 | Z60: =L60 | AA60: =IFERROR(__xludf.DUMMYFUNCTION("""COMPUTED_VALUE"""),"Drew") -> Drew | AB60: =K60
A61: 2369 | B61: 20265060 | C61: INS - Randy Hawkins | E61: 46098 | F61: 0 | I61: James | L61: =if(S61=TRUE,K61-F61,"") | N61: =if(S61=TRUE,K61-M61,"") | O61: =IF($R61, IFERROR(IF((F61+L61)>0, (F61+L61-M61)/(F61+L61), ""), ""), "") | P61: =IFERROR(__xludf.DUMMYFUNCTION("IF(AND($R61, NOT(REGEXMATCH(UPPER($C61), ""INS""))), IFERROR(IF((F61+L61)>0, (F61+L61-M61)/(F61+L61), """"), """"), """")"),"") | Q61: =IFERROR(__xludf.DUMMYFUNCTION("IF(AND($R61, REGEXMATCH(UPPER($C61), ""INS"")), IFERROR(IF((F61+L61)>0, (F61+L61-M61)/(F61+L61), """"), """"), """")"),"") | R61: FALSE | S61: FALSE | T61: FALSE | U61: Approved | V61: FALSE | W61: =O61 | X61: =J61 | Y61: =F61 -> 0 | Z61: =L61 | AA61: =IFERROR(__xludf.DUMMYFUNCTION("""COMPUTED_VALUE"""),"Drew") -> Drew | AB61: =K61
A62: 2377 | B62: 20265061 | C62: INS - Bob Bradley | E62: 46099 | F62: 9210.97 | G62: 03/26/2026 | H62: 03/26/2026 | I62: James | L62: =if(S62=TRUE,K62-F62,"") | N62: =if(S62=TRUE,K62-M62,"") | O62: =IF($R62, IFERROR(IF((F62+L62)>0, (F62+L62-M62)/(F62+L62), ""), ""), "") | P62: =IFERROR(__xludf.DUMMYFUNCTION("IF(AND($R62, NOT(REGEXMATCH(UPPER($C62), ""INS""))), IFERROR(IF((F62+L62)>0, (F62+L62-M62)/(F62+L62), """"), """"), """")"),"") | Q62: =IFERROR(__xludf.DUMMYFUNCTION("IF(AND($R62, REGEXMATCH(UPPER($C62), ""INS"")), IFERROR(IF((F62+L62)>0, (F62+L62-M62)/(F62+L62), """"), """"), """")"),"") | R62: FALSE | S62: FALSE | T62: FALSE | U62: Job Scheduled | V62: FALSE | W62: =O62 | X62: =J62 | Y62: =F62 -> 9210.97 | Z62: =L62 | AA62: =IFERROR(__xludf.DUMMYFUNCTION("""COMPUTED_VALUE"""),"Drew") -> Drew | AB62: =K62
A63: 2322 | B63: 20265062 | C63: Michelle Strickland | E63: 46099 | F63: 0 | I63: Brett | L63: =if(S63=TRUE,K63-F63,"") | N63: =if(S63=TRUE,K63-M63,"") | O63: =IF($R63, IFERROR(IF((F63+L63)>0, (F63+L63-M63)/(F63+L63), ""), ""), "") | P63: =IFERROR(__xludf.DUMMYFUNCTION("IF(AND($R63, NOT(REGEXMATCH(UPPER($C63), ""INS""))), IFERROR(IF((F63+L63)>0, (F63+L63-M63)/(F63+L63), """"), """"), """")"),"") | Q63: =IFERROR(__xludf.DUMMYFUNCTION("IF(AND($R63, REGEXMATCH(UPPER($C63), ""INS"")), IFERROR(IF((F63+L63)>0, (F63+L63-M63)/(F63+L63), """"), """"), """")"),"") | R63: FALSE | S63: FALSE | T63: FALSE | U63: Approved | V63: FALSE | W63: =O63 | X63: =J63 | Y63: =F63 -> 0 | Z63: =L63 | AA63: =IFERROR(__xludf.DUMMYFUNCTION("""COMPUTED_VALUE"""),"Drew") -> Drew | AB63: =K63
A64: 2390 | B64: 20265063 | C64: INS - John Stockstill | E64: 46099 | F64: 11601.56 | G64: 04/16/2026 | H64: 04/17/2026 | I64: James | L64: =if(S64=TRUE,K64-F64,"") | N64: =if(S64=TRUE,K64-M64,"") | O64: =IF($R64, IFERROR(IF((F64+L64)>0, (F64+L64-M64)/(F64+L64), ""), ""), "") | P64: =IFERROR(__xludf.DUMMYFUNCTION("IF(AND($R64, NOT(REGEXMATCH(UPPER($C64), ""INS""))), IFERROR(IF((F64+L64)>0, (F64+L64-M64)/(F64+L64), """"), """"), """")"),"") | Q64: =IFERROR(__xludf.DUMMYFUNCTION("IF(AND($R64, REGEXMATCH(UPPER($C64), ""INS"")), IFERROR(IF((F64+L64)>0, (F64+L64-M64)/(F64+L64), """"), """"), """")"),"") | R64: FALSE | S64: FALSE | T64: FALSE | U64: In Progress | V64: FALSE | W64: =O64 | X64: =J64 | Y64: =F64 -> 11601.56 | Z64: =L64 | AA64: =IFERROR(__xludf.DUMMYFUNCTION("""COMPUTED_VALUE"""),"Drew") -> Drew | AB64: =K64
A65: 2334 | B65: 20265064 | C65: INS - Robert Hope | E65: 46099 | F65: 0 | I65: James | L65: =if(S65=TRUE,K65-F65,"") | N65: =if(S65=TRUE,K65-M65,"") | O65: =IF($R65, IFERROR(IF((F65+L65)>0, (F65+L65-M65)/(F65+L65), ""), ""), "") | P65: =IFERROR(__xludf.DUMMYFUNCTION("IF(AND($R65, NOT(REGEXMATCH(UPPER($C65), ""INS""))), IFERROR(IF((F65+L65)>0, (F65+L65-M65)/(F65+L65), """"), """"), """")"),"") | Q65: =IFERROR(__xludf.DUMMYFUNCTION("IF(AND($R65, REGEXMATCH(UPPER($C65), ""INS"")), IFERROR(IF((F65+L65)>0, (F65+L65-M65)/(F65+L65), """"), """"), """")"),"") | R65: FALSE | S65: FALSE | T65: FALSE | U65: Approved | V65: FALSE | W65: =O65 | X65: =J65 | Y65: =F65 -> 0 | Z65: =L65 | AA65: =IFERROR(__xludf.DUMMYFUNCTION("""COMPUTED_VALUE"""),"Drew") -> Drew | AB65: =K65
A66: 2417 | B66: 20265065 | C66: Steve Liptak | E66: 46099 | F66: 1744.28 | I66: Mike | L66: =if(S66=TRUE,K66-F66,"") | N66: =if(S66=TRUE,K66-M66,"") | O66: =IF($R66, IFERROR(IF((F66+L66)>0, (F66+L66-M66)/(F66+L66), ""), ""), "") | P66: =IFERROR(__xludf.DUMMYFUNCTION("IF(AND($R66, NOT(REGEXMATCH(UPPER($C66), ""INS""))), IFERROR(IF((F66+L66)>0, (F66+L66-M66)/(F66+L66), """"), """"), """")"),"") | Q66: =IFERROR(__xludf.DUMMYFUNCTION("IF(AND($R66, REGEXMATCH(UPPER($C66), ""INS"")), IFERROR(IF((F66+L66)>0, (F66+L66-M66)/(F66+L66), """"), """"), """")"),"") | R66: FALSE | S66: FALSE | T66: FALSE | U66: Job Scheduled | V66: FALSE | W66: =O66 | X66: =J66 | Y66: =F66 -> 1744.28 | Z66: =L66 | AA66: =IFERROR(__xludf.DUMMYFUNCTION("""COMPUTED_VALUE"""),"Drew") -> Drew | AB66: =K66
A67: 2380 | B67: 20265066 | C67: INS - Steve Creager | E67: 46100 | F67: 1190 | G67: 05/08/2026 | H67: 05/08/2026 | I67: Brett | L67: =if(S67=TRUE,K67-F67,"") | N67: =if(S67=TRUE,K67-M67,"") | O67: =IF($R67, IFERROR(IF((F67+L67)>0, (F67+L67-M67)/(F67+L67), ""), ""), "") | P67: =IFERROR(__xludf.DUMMYFUNCTION("IF(AND($R67, NOT(REGEXMATCH(UPPER($C67), ""INS""))), IFERROR(IF((F67+L67)>0, (F67+L67-M67)/(F67+L67), """"), """"), """")"),"") | Q67: =IFERROR(__xludf.DUMMYFUNCTION("IF(AND($R67, REGEXMATCH(UPPER($C67), ""INS"")), IFERROR(IF((F67+L67)>0, (F67+L67-M67)/(F67+L67), """"), """"), """")"),"") | R67: FALSE | S67: FALSE | T67: FALSE | U67: Job Scheduled | V67: FALSE | W67: =O67 | X67: =J67 | Y67: =F67 -> 1190 | Z67: =L67 | AA67: =IFERROR(__xludf.DUMMYFUNCTION("""COMPUTED_VALUE"""),"Drew") -> Drew | AB67: =K67
A68: 2423 | B68: 20265067 | C68: INS - Adam Mott | E68: 46100 | F68: 0 | I68: Chris | L68: =if(S68=TRUE,K68-F68,"") | N68: =if(S68=TRUE,K68-M68,"") | O68: =IF($R68, IFERROR(IF((F68+L68)>0, (F68+L68-M68)/(F68+L68), ""), ""), "") | P68: =IFERROR(__xludf.DUMMYFUNCTION("IF(AND($R68, NOT(REGEXMATCH(UPPER($C68), ""INS""))), IFERROR(IF((F68+L68)>0, (F68+L68-M68)/(F68+L68), """"), """"), """")"),"") | Q68: =IFERROR(__xludf.DUMMYFUNCTION("IF(AND($R68, REGEXMATCH(UPPER($C68), ""INS"")), IFERROR(IF((F68+L68)>0, (F68+L68-M68)/(F68+L68), """"), """"), """")"),"") | R68: FALSE | S68: FALSE | T68: FALSE | U68: Approved | V68: FALSE | W68: =O68 | X68: =J68 | Y68: =F68 -> 0 | Z68: =L68 | AA68: =IFERROR(__xludf.DUMMYFUNCTION("""COMPUTED_VALUE"""),"Drew") -> Drew | AB68: =K68
A69: 2382 | B69: 20265068 | C69: INS - Jonathan Humphreys | E69: 46100 | F69: 0 | I69: James | L69: =if(S69=TRUE,K69-F69,"") | N69: =if(S69=TRUE,K69-M69,"") | O69: =IF($R69, IFERROR(IF((F69+L69)>0, (F69+L69-M69)/(F69+L69), ""), ""), "") | P69: =IFERROR(__xludf.DUMMYFUNCTION("IF(AND($R69, NOT(REGEXMATCH(UPPER($C69), ""INS""))), IFERROR(IF((F69+L69)>0, (F69+L69-M69)/(F69+L69), """"), """"), """")"),"") | Q69: =IFERROR(__xludf.DUMMYFUNCTION("IF(AND($R69, REGEXMATCH(UPPER($C69), ""INS"")), IFERROR(IF((F69+L69)>0, (F69+L69-M69)/(F69+L69), """"), """"), """")"),"") | R69: FALSE | S69: FALSE | T69: FALSE | U69: Approved | V69: FALSE | W69: =O69 | X69: =J69 | Y69: =F69 -> 0 | Z69: =L69 | AA69: =IFERROR(__xludf.DUMMYFUNCTION("""COMPUTED_VALUE"""),"Drew") -> Drew | AB69: =K69
A70: 2310 | B70: 20265069 | C70: Dana Roberts - siding repair | E70: 46100 | F70: 707.5 | G70: 04/16/2026 | H70: 04/16/2026 | I70: Brett | L70: =if(S70=TRUE,K70-F70,"") | N70: =if(S70=TRUE,K70-M70,"") | O70: =IF($R70, IFERROR(IF((F70+L70)>0, (F70+L70-M70)/(F70+L70), ""), ""), "") | P70: =IFERROR(__xludf.DUMMYFUNCTION("IF(AND($R70, NOT(REGEXMATCH(UPPER($C70), ""INS""))), IFERROR(IF((F70+L70)>0, (F70+L70-M70)/(F70+L70), """"), """"), """")"),"") | Q70: =IFERROR(__xludf.DUMMYFUNCTION("IF(AND($R70, REGEXMATCH(UPPER($C70), ""INS"")), IFERROR(IF((F70+L70)>0, (F70+L70-M70)/(F70+L70), """"), """"), """")"),"") | R70: FALSE | S70: FALSE | T70: FALSE | U70: Job Scheduled | V70: FALSE | W70: =O70 | X70: =J70 | Y70: =F70 -> 707.5 | Z70: =L70 | AA70: =IFERROR(__xludf.DUMMYFUNCTION("""COMPUTED_VALUE"""),"Drew") -> Drew | AB70: =K70
A71: 2313 | B71: 20265070 | C71: INS - Ashley Dean | E71: 46100 | F71: 0 | G71: 03/26/2026 | H71: 03/26/2026 | I71: Brett | J71: 750 | L71: =if(S71=TRUE,K71-F71,"") | N71: =if(S71=TRUE,K71-M71,"") | O71: =IF($R71, IFERROR(IF((F71+L71)>0, (F71+L71-M71)/(F71+L71), ""), ""), "") | P71: =IFERROR(__xludf.DUMMYFUNCTION("IF(AND($R71, NOT(REGEXMATCH(UPPER($C71), ""INS""))), IFERROR(IF((F71+L71)>0, (F71+L71-M71)/(F71+L71), """"), """"), """")"),"") | Q71: =IFERROR(__xludf.DUMMYFUNCTION("IF(AND($R71, REGEXMATCH(UPPER($C71), ""INS"")), IFERROR(IF((F71+L71)>0, (F71+L71-M71)/(F71+L71), """"), """"), """")"),"") | R71: TRUE | S71: FALSE | T71: FALSE | U71: Job Scheduled | V71: FALSE | W71: =O71 | X71: =J71 -> 750 | Y71: =F71 -> 0 | Z71: =L71 | AA71: =IFERROR(__xludf.DUMMYFUNCTION("""COMPUTED_VALUE"""),"Drew") -> Drew | AB71: =K71
A72: 2304 | B72: 20265071 | C72: INS - Steve Elrich | E72: 46100 | F72: 25681.99 | G72: 05/11/2026 | H72: 05/11/2026 | I72: James | L72: =if(S72=TRUE,K72-F72,"") | N72: =if(S72=TRUE,K72-M72,"") | O72: =IF($R72, IFERROR(IF((F72+L72)>0, (F72+L72-M72)/(F72+L72), ""), ""), "") | P72: =IFERROR(__xludf.DUMMYFUNCTION("IF(AND($R72, NOT(REGEXMATCH(UPPER($C72), ""INS""))), IFERROR(IF((F72+L72)>0, (F72+L72-M72)/(F72+L72), """"), """"), """")"),"") | Q72: =IFERROR(__xludf.DUMMYFUNCTION("IF(AND($R72, REGEXMATCH(UPPER($C72), ""INS"")), IFERROR(IF((F72+L72)>0, (F72+L72-M72)/(F72+L72), """"), """"), """")"),"") | R72: FALSE | S72: FALSE | T72: FALSE | U72: Job Scheduled | V72: FALSE | W72: =O72 | X72: =J72 | Y72: =F72 -> 25681.99 | Z72: =L72 | AA72: =IFERROR(__xludf.DUMMYFUNCTION("""COMPUTED_VALUE"""),"Drew") -> Drew | AB72: =K72
A73: 2330 | B73: 20265072 | C73: Justin Oeder | E73: 46101 | F73: 607.5 | I73: Brett | J73: 607.5 | L73: =if(S73=TRUE,K73-F73,"") | M73: 250 | N73: =if(S73=TRUE,K73-M73,"") | O73: =IF($R73, IFERROR(IF((F73+L73)>0, (F73+L73-M73)/(F73+L73), ""), ""), "") -> 0.58847737 | P73: =IFERROR(__xludf.DUMMYFUNCTION("IF(AND($R73, NOT(REGEXMATCH(UPPER($C73), ""INS""))), IFERROR(IF((F73+L73)>0, (F73+L73-M73)/(F73+L73), """"), """"), """")"),0.588477366255144) -> 0.58847737 | Q73: =IFERROR(__xludf.DUMMYFUNCTION("IF(AND($R73, REGEXMATCH(UPPER($C73), ""INS"")), IFERROR(IF((F73+L73)>0, (F73+L73-M73)/(F73+L73), """"), """"), """")"),"") | R73: TRUE | S73: FALSE | T73: FALSE | U73: In Billing | V73: FALSE | W73: =O73 -> 0.58847737 | X73: =J73 -> 607.5 | Y73: =F73 -> 607.5 | Z73: =L73 | AA73: =IFERROR(__xludf.DUMMYFUNCTION("""COMPUTED_VALUE"""),"Drew") -> Drew | AB73: =K73
A74: 2432 | B74: 20265073 | C74: INS - Patricia Howard | E74: 46101 | F74: 9068.42 | G74: 05/12/2026 | H74: 05/12/2026 | I74: Mike | L74: =if(S74=TRUE,K74-F74,"") | N74: =if(S74=TRUE,K74-M74,"") | O74: =IF($R74, IFERROR(IF((F74+L74)>0, (F74+L74-M74)/(F74+L74), ""), ""), "") | P74: =IFERROR(__xludf.DUMMYFUNCTION("IF(AND($R74, NOT(REGEXMATCH(UPPER($C74), ""INS""))), IFERROR(IF((F74+L74)>0, (F74+L74-M74)/(F74+L74), """"), """"), """")"),"") | Q74: =IFERROR(__xludf.DUMMYFUNCTION("IF(AND($R74, REGEXMATCH(UPPER($C74), ""INS"")), IFERROR(IF((F74+L74)>0, (F74+L74-M74)/(F74+L74), """"), """"), """")"),"") | R74: FALSE | S74: FALSE | T74: FALSE | U74: Job Scheduled | V74: FALSE | W74: =O74 | X74: =J74 | Y74: =F74 -> 9068.42 | Z74: =L74 | AA74: =IFERROR(__xludf.DUMMYFUNCTION("""COMPUTED_VALUE"""),"Drew") -> Drew | AB74: =K74
A75: 2398 | B75: 20265074 | C75: INS - Brad Burtus | E75: 46101 | F75: 0 | G75: 03/26/2026 | H75: 03/26/2026 | I75: Brett | J75: 550 | L75: =if(S75=TRUE,K75-F75,"") | N75: =if(S75=TRUE,K75-M75,"") | O75: =IF($R75, IFERROR(IF((F75+L75)>0, (F75+L75-M75)/(F75+L75), ""), ""), "") | P75: =IFERROR(__xludf.DUMMYFUNCTION("IF(AND($R75, NOT(REGEXMATCH(UPPER($C75), ""INS""))), IFERROR(IF((F75+L75)>0, (F75+L75-M75)/(F75+L75), """"), """"), """")"),"") | Q75: =IFERROR(__xludf.DUMMYFUNCTION("IF(AND($R75, REGEXMATCH(UPPER($C75), ""INS"")), IFERROR(IF((F75+L75)>0, (F75+L75-M75)/(F75+L75), """"), """"), """")"),"") | R75: TRUE | S75: FALSE | T75: FALSE | U75: Job Scheduled | V75: FALSE | W75: =O75 | X75: =J75 -> 550 | Y75: =F75 -> 0 | Z75: =L75 | AA75: =IFERROR(__xludf.DUMMYFUNCTION("""COMPUTED_VALUE"""),"Drew") -> Drew | AB75: =K75
A76: 2400 | B76: 20265075 | C76: INS - Maurice Docton | E76: 46101 | F76: 544.79 | I76: James | J76: 544.79 | K76: 600 | L76: =if(S76=TRUE,K76-F76,"") -> 55.21 | N76: =if(S76=TRUE,K76-M76,"") -> 600 | O76: =IF($R76, IFERROR(IF((F76+L76)>0, (F76+L76-M76)/(F76+L76), ""), ""), "") -> 1 | P76: =IFERROR(__xludf.DUMMYFUNCTION("IF(AND($R76, NOT(REGEXMATCH(UPPER($C76), ""INS""))), IFERROR(IF((F76+L76)>0, (F76+L76-M76)/(F76+L76), """"), """"), """")"),"") | Q76: =IFERROR(__xludf.DUMMYFUNCTION("IF(AND($R76, REGEXMATCH(UPPER($C76), ""INS"")), IFERROR(IF((F76+L76)>0, (F76+L76-M76)/(F76+L76), """"), """"), """")"),1.0) -> 1 | R76: TRUE | S76: TRUE | T76: FALSE | U76: In Billing | V76: FALSE | W76: =O76 -> 1 | X76: =J76 -> 544.79 | Y76: =F76 -> 544.79 | Z76: =L76 -> 55.21 | AA76: =IFERROR(__xludf.DUMMYFUNCTION("""COMPUTED_VALUE"""),"Drew") -> Drew | AB76: =K76 -> 600
A77: 2405 | B77: 20265076 | C77: Louden Saulbeamer | E77: 46101 | F77: 1190 | G77: 04/09/2026 | H77: 04/09/2026 | I77: Brett | J77: 1190 | L77: =if(S77=TRUE,K77-F77,"") | M77: 600 | N77: =if(S77=TRUE,K77-M77,"") | O77: =IF($R77, IFERROR(IF((F77+L77)>0, (F77+L77-M77)/(F77+L77), ""), ""), "") -> 0.49579832 | P77: =IFERROR(__xludf.DUMMYFUNCTION("IF(AND($R77, NOT(REGEXMATCH(UPPER($C77), ""INS""))), IFERROR(IF((F77+L77)>0, (F77+L77-M77)/(F77+L77), """"), """"), """")"),0.4957983193277311) -> 0.49579832 | Q77: =IFERROR(__xludf.DUMMYFUNCTION("IF(AND($R77, REGEXMATCH(UPPER($C77), ""INS"")), IFERROR(IF((F77+L77)>0, (F77+L77-M77)/(F77+L77), """"), """"), """")"),"") | R77: TRUE | S77: FALSE | T77: FALSE | U77: In Billing | V77: FALSE | W77: =O77 -> 0.49579832 | X77: =J77 -> 1190 | Y77: =F77 -> 1190 | Z77: =L77 | AA77: =IFERROR(__xludf.DUMMYFUNCTION("""COMPUTED_VALUE"""),"Drew") -> Drew | AB77: =K77
A78: 2436 | B78: 20265077 | C78: Stacey Underwood | E78: 46101 | F78: 0 | I78: James | L78: =if(S78=TRUE,K78-F78,"") | N78: =if(S78=TRUE,K78-M78,"") | O78: =IF($R78, IFERROR(IF((F78+L78)>0, (F78+L78-M78)/(F78+L78), ""), ""), "") | P78: =IFERROR(__xludf.DUMMYFUNCTION("IF(AND($R78, NOT(REGEXMATCH(UPPER($C78), ""INS""))), IFERROR(IF((F78+L78)>0, (F78+L78-M78)/(F78+L78), """"), """"), """")"),"") | Q78: =IFERROR(__xludf.DUMMYFUNCTION("IF(AND($R78, REGEXMATCH(UPPER($C78), ""INS"")), IFERROR(IF((F78+L78)>0, (F78+L78-M78)/(F78+L78), """"), """"), """")"),"") | R78: FALSE | S78: FALSE | T78: FALSE | U78: Approved | V78: FALSE | W78: =O78 | X78: =J78 | Y78: =F78 -> 0 | Z78: =L78 | AA78: =IFERROR(__xludf.DUMMYFUNCTION("""COMPUTED_VALUE"""),"Drew") -> Drew | AB78: =K78
A79: 2422 | B79: 20265078 | C79: Jim Ashburn | E79: 46101 | F79: 12821.96 | G79: 05/05/2026 | H79: 05/04/2026 | I79: Chris | L79: =if(S79=TRUE,K79-F79,"") | N79: =if(S79=TRUE,K79-M79,"") | O79: =IF($R79, IFERROR(IF((F79+L79)>0, (F79+L79-M79)/(F79+L79), ""), ""), "") | P79: =IFERROR(__xludf.DUMMYFUNCTION("IF(AND($R79, NOT(REGEXMATCH(UPPER($C79), ""INS""))), IFERROR(IF((F79+L79)>0, (F79+L79-M79)/(F79+L79), """"), """"), """")"),"") | Q79: =IFERROR(__xludf.DUMMYFUNCTION("IF(AND($R79, REGEXMATCH(UPPER($C79), ""INS"")), IFERROR(IF((F79+L79)>0, (F79+L79-M79)/(F79+L79), """"), """"), """")"),"") | R79: FALSE | S79: FALSE | T79: FALSE | U79: Job Scheduled | V79: FALSE | W79: =O79 | X79: =J79 | Y79: =F79 -> 12821.96 | Z79: =L79 | AA79: =IFERROR(__xludf.DUMMYFUNCTION("""COMPUTED_VALUE"""),"Drew") -> Drew | AB79: =K79
A80: 2315 | B80: 20265079 | C80: Paula Pinson | E80: 46102 | F80: 597.18 | G80: 04/10/2026 | H80: 04/10/2026 | I80: James | L80: =if(S80=TRUE,K80-F80,"") | N80: =if(S80=TRUE,K80-M80,"") | O80: =IF($R80, IFERROR(IF((F80+L80)>0, (F80+L80-M80)/(F80+L80), ""), ""), "") | P80: =IFERROR(__xludf.DUMMYFUNCTION("IF(AND($R80, NOT(REGEXMATCH(UPPER($C80), ""INS""))), IFERROR(IF((F80+L80)>0, (F80+L80-M80)/(F80+L80), """"), """"), """")"),"") | Q80: =IFERROR(__xludf.DUMMYFUNCTION("IF(AND($R80, REGEXMATCH(UPPER($C80), ""INS"")), IFERROR(IF((F80+L80)>0, (F80+L80-M80)/(F80+L80), """"), """"), """")"),"") | R80: FALSE | S80: FALSE | T80: FALSE | U80: In Billing | V80: FALSE | W80: =O80 | X80: =J80 | Y80: =F80 -> 597.18 | Z80: =L80 | AA80: =IFERROR(__xludf.DUMMYFUNCTION("""COMPUTED_VALUE"""),"Drew") -> Drew | AB80: =K80
A81: 2414 | B81: 20265080 | C81: Vince Baldasare - siding repair | E81: 46102 | F81: 1340 | G81: 04/16/2026 | H81: 04/16/2026 | I81: Brett | J81: 1340 | L81: =if(S81=TRUE,K81-F81,"") | M81: 597.35 | N81: =if(S81=TRUE,K81-M81,"") | O81: =IF($R81, IFERROR(IF((F81+L81)>0, (F81+L81-M81)/(F81+L81), ""), ""), "") -> 0.55421642 | P81: =IFERROR(__xludf.DUMMYFUNCTION("IF(AND($R81, NOT(REGEXMATCH(UPPER($C81), ""INS""))), IFERROR(IF((F81+L81)>0, (F81+L81-M81)/(F81+L81), """"), """"), """")"),0.5542164179104477) -> 0.55421642 | Q81: =IFERROR(__xludf.DUMMYFUNCTION("IF(AND($R81, REGEXMATCH(UPPER($C81), ""INS"")), IFERROR(IF((F81+L81)>0, (F81+L81-M81)/(F81+L81), """"), """"), """")"),"") | R81: TRUE | S81: FALSE | T81: FALSE | U81: Job Scheduled | V81: FALSE | W81: =O81 -> 0.55421642 | X81: =J81 -> 1340 | Y81: =F81 -> 1340 | Z81: =L81 | AA81: =IFERROR(__xludf.DUMMYFUNCTION("""COMPUTED_VALUE"""),"Drew") -> Drew | AB81: =K81
A82: 2457 | B82: 20265081 | C82: Amy Hirsch | E82: 46102 | F82: 0 | I82: James | L82: =if(S82=TRUE,K82-F82,"") | N82: =if(S82=TRUE,K82-M82,"") | O82: =IF($R82, IFERROR(IF((F82+L82)>0, (F82+L82-M82)/(F82+L82), ""), ""), "") | P82: =IFERROR(__xludf.DUMMYFUNCTION("IF(AND($R82, NOT(REGEXMATCH(UPPER($C82), ""INS""))), IFERROR(IF((F82+L82)>0, (F82+L82-M82)/(F82+L82), """"), """"), """")"),"") | Q82: =IFERROR(__xludf.DUMMYFUNCTION("IF(AND($R82, REGEXMATCH(UPPER($C82), ""INS"")), IFERROR(IF((F82+L82)>0, (F82+L82-M82)/(F82+L82), """"), """"), """")"),"") | R82: FALSE | S82: FALSE | T82: FALSE | U82: Approved | V82: FALSE | W82: =O82 | X82: =J82 | Y82: =F82 -> 0 | Z82: =L82 | AA82: =IFERROR(__xludf.DUMMYFUNCTION("""COMPUTED_VALUE"""),"Drew") -> Drew | AB82: =K82
A83: 2430 | B83: 20265082 | C83: Gregg Marshall | E83: 46102 | F83: 715 | G83: 04/07/2026 | H83: 04/07/2026 | I83: Drew | J83: 715 | K83: 715 | L83: =if(S83=TRUE,K83-F83,"") -> 0 | M83: 292.43 | N83: =if(S83=TRUE,K83-M83,"") -> 422.57 | O83: =IF($R83, IFERROR(IF((F83+L83)>0, (F83+L83-M83)/(F83+L83), ""), ""), "") -> 0.59100699 | P83: =IFERROR(__xludf.DUMMYFUNCTION("IF(AND($R83, NOT(REGEXMATCH(UPPER($C83), ""INS""))), IFERROR(IF((F83+L83)>0, (F83+L83-M83)/(F83+L83), """"), """"), """")"),0.591006993006993) -> 0.59100699 | Q83: =IFERROR(__xludf.DUMMYFUNCTION("IF(AND($R83, REGEXMATCH(UPPER($C83), ""INS"")), IFERROR(IF((F83+L83)>0, (F83+L83-M83)/(F83+L83), """"), """"), """")"),"") | R83: TRUE | S83: TRUE | T83: TRUE | U83: In Billing | V83: FALSE | W83: =O83 -> 0.59100699 | X83: =J83 -> 715 | Y83: =F83 -> 715 | Z83: =L83 -> 0 | AA83: =IFERROR(__xludf.DUMMYFUNCTION("""COMPUTED_VALUE"""),"Drew") -> Drew | AB83: =K83 -> 715
A84: 2458 | B84: 20265083 | C84: Belkis Siebert | E84: 46103 | F84: 18050.11 | G84: 05/19/2026 | H84: 05/19/2026 | I84: James | J84: 500 | K84: 500 | L84: =if(S84=TRUE,K84-F84,"") -> -17550.11 | N84: =if(S84=TRUE,K84-M84,"") -> 500 | O84: =IF($R84, IFERROR(IF((F84+L84)>0, (F84+L84-M84)/(F84+L84), ""), ""), "") -> 1 | P84: =IFERROR(__xludf.DUMMYFUNCTION("IF(AND($R84, NOT(REGEXMATCH(UPPER($C84), ""INS""))), IFERROR(IF((F84+L84)>0, (F84+L84-M84)/(F84+L84), """"), """"), """")"),1.0) -> 1 | Q84: =IFERROR(__xludf.DUMMYFUNCTION("IF(AND($R84, REGEXMATCH(UPPER($C84), ""INS"")), IFERROR(IF((F84+L84)>0, (F84+L84-M84)/(F84+L84), """"), """"), """")"),"") | R84: TRUE | S84: TRUE | T84: FALSE | U84: Job Scheduled | V84: FALSE | W84: =O84 -> 1 | X84: =J84 -> 500 | Y84: =F84 -> 18050.11 | Z84: =L84 -> -17550.11 | AA84: =IFERROR(__xludf.DUMMYFUNCTION("""COMPUTED_VALUE"""),"Drew") -> Drew | AB84: =K84 -> 500
A85: 2410 | B85: 20265084 | C85: INS - Gladys Stanley | E85: 46104 | F85: 0 | I85: Drew | L85: =if(S85=TRUE,K85-F85,"") | N85: =if(S85=TRUE,K85-M85,"") | O85: =IF($R85, IFERROR(IF((F85+L85)>0, (F85+L85-M85)/(F85+L85), ""), ""), "") | P85: =IFERROR(__xludf.DUMMYFUNCTION("IF(AND($R85, NOT(REGEXMATCH(UPPER($C85), ""INS""))), IFERROR(IF((F85+L85)>0, (F85+L85-M85)/(F85+L85), """"), """"), """")"),"") | Q85: =IFERROR(__xludf.DUMMYFUNCTION("IF(AND($R85, REGEXMATCH(UPPER($C85), ""INS"")), IFERROR(IF((F85+L85)>0, (F85+L85-M85)/(F85+L85), """"), """"), """")"),"") | R85: FALSE | S85: FALSE | T85: FALSE | U85: Approved | V85: FALSE | W85: =O85 | X85: =J85 | Y85: =F85 -> 0 | Z85: =L85 | AA85: =IFERROR(__xludf.DUMMYFUNCTION("""COMPUTED_VALUE"""),"Drew") -> Drew | AB85: =K85
A86: 2464 | B86: 20265085 | C86: Linda Bantner | E86: 46104 | F86: 761.25 | G86: 04/13/2026 | H86: 04/13/2026 | I86: James | J86: 761.25 | K86: 761.25 | L86: =if(S86=TRUE,K86-F86,"") -> 0 | N86: =if(S86=TRUE,K86-M86,"") -> 761.25 | O86: =IF($R86, IFERROR(IF((F86+L86)>0, (F86+L86-M86)/(F86+L86), ""), ""), "") -> 1 | P86: =IFERROR(__xludf.DUMMYFUNCTION("IF(AND($R86, NOT(REGEXMATCH(UPPER($C86), ""INS""))), IFERROR(IF((F86+L86)>0, (F86+L86-M86)/(F86+L86), """"), """"), """")"),1.0) -> 1 | Q86: =IFERROR(__xludf.DUMMYFUNCTION("IF(AND($R86, REGEXMATCH(UPPER($C86), ""INS"")), IFERROR(IF((F86+L86)>0, (F86+L86-M86)/(F86+L86), """"), """"), """")"),"") | R86: TRUE | S86: TRUE | T86: FALSE | U86: In Billing | V86: FALSE | W86: =O86 -> 1 | X86: =J86 -> 761.25 | Y86: =F86 -> 761.25 | Z86: =L86 -> 0 | AA86: =IFERROR(__xludf.DUMMYFUNCTION("""COMPUTED_VALUE"""),"Drew") -> Drew | AB86: =K86 -> 761.25
A87: 2326 | B87: 20265086 | C87: Jacob Dereshkevich | E87: 46104 | F87: 3330.79 | G87: 04/16/2026 | H87: 04/16/2026 | I87: James | J87: 3330.79 | L87: =if(S87=TRUE,K87-F87,"") | M87: 1885.24 | N87: =if(S87=TRUE,K87-M87,"") | O87: =IF($R87, IFERROR(IF((F87+L87)>0, (F87+L87-M87)/(F87+L87), ""), ""), "") -> 0.43399614 | P87: =IFERROR(__xludf.DUMMYFUNCTION("IF(AND($R87, NOT(REGEXMATCH(UPPER($C87), ""INS""))), IFERROR(IF((F87+L87)>0, (F87+L87-M87)/(F87+L87), """"), """"), """")"),0.4339961390540983) -> 0.43399614 | Q87: =IFERROR(__xludf.DUMMYFUNCTION("IF(AND($R87, REGEXMATCH(UPPER($C87), ""INS"")), IFERROR(IF((F87+L87)>0, (F87+L87-M87)/(F87+L87), """"), """"), """")"),"") | R87: TRUE | S87: FALSE | T87: FALSE | U87: Job Scheduled | V87: FALSE | W87: =O87 -> 0.43399614 | X87: =J87 -> 3330.79 | Y87: =F87 -> 3330.79 | Z87: =L87 | AA87: =IFERROR(__xludf.DUMMYFUNCTION("""COMPUTED_VALUE"""),"Drew") -> Drew | AB87: =K87
A88: 2466 | B88: 20265087 | C88: INS - Heather Brodess | E88: 46105 | F88: 954.97 | I88: Chris | L88: =if(S88=TRUE,K88-F88,"") | M88: 436 | N88: =if(S88=TRUE,K88-M88,"") | O88: =IF($R88, IFERROR(IF((F88+L88)>0, (F88+L88-M88)/(F88+L88), ""), ""), "") | P88: =IFERROR(__xludf.DUMMYFUNCTION("IF(AND($R88, NOT(REGEXMATCH(UPPER($C88), ""INS""))), IFERROR(IF((F88+L88)>0, (F88+L88-M88)/(F88+L88), """"), """"), """")"),"") | Q88: =IFERROR(__xludf.DUMMYFUNCTION("IF(AND($R88, REGEXMATCH(UPPER($C88), ""INS"")), IFERROR(IF((F88+L88)>0, (F88+L88-M88)/(F88+L88), """"), """"), """")"),"") | R88: FALSE | S88: FALSE | T88: FALSE | U88: Job Scheduled | V88: FALSE | W88: =O88 | X88: =J88 | Y88: =F88 -> 954.97 | Z88: =L88 | AA88: =IFERROR(__xludf.DUMMYFUNCTION("""COMPUTED_VALUE"""),"Drew") -> Drew | AB88: =K88
A89: 2404 | B89: 20265088 | C89: INS - Cheryl DeBrosse | E89: 46105 | F89: 4204.85 | G89: 04/23/2026 | H89: 04/23/2026 | I89: James | J89: 4204.85 | L89: =if(S89=TRUE,K89-F89,"") | N89: =if(S89=TRUE,K89-M89,"") | O89: =IF($R89, IFERROR(IF((F89+L89)>0, (F89+L89-M89)/(F89+L89), ""), ""), "") -> 1 | P89: =IFERROR(__xludf.DUMMYFUNCTION("IF(AND($R89, NOT(REGEXMATCH(UPPER($C89), ""INS""))), IFERROR(IF((F89+L89)>0, (F89+L89-M89)/(F89+L89), """"), """"), """")"),"") | Q89: =IFERROR(__xludf.DUMMYFUNCTION("IF(AND($R89, REGEXMATCH(UPPER($C89), ""INS"")), IFERROR(IF((F89+L89)>0, (F89+L89-M89)/(F89+L89), """"), """"), """")"),1.0) -> 1 | R89: TRUE | S89: FALSE | T89: FALSE | U89: Job Scheduled | V89: FALSE | W89: =O89 -> 1 | X89: =J89 -> 4204.85 | Y89: =F89 -> 4204.85 | Z89: =L89 | AA89: =IFERROR(__xludf.DUMMYFUNCTION("""COMPUTED_VALUE"""),"Drew") -> Drew | AB89: =K89
A90: 2444 | B90: 20265089 | C90: John Cox | E90: 46105 | F90: 1375.7 | G90: 04/07/2026 | H90: 04/07/2026 | I90: Drew | J90: 1375.7 | K90: 1375.7 | L90: =if(S90=TRUE,K90-F90,"") -> 0 | M90: 680.42 | N90: =if(S90=TRUE,K90-M90,"") -> 695.28 | O90: =IF($R90, IFERROR(IF((F90+L90)>0, (F90+L90-M90)/(F90+L90), ""), ""), "") -> 0.50540089 | P90: =IFERROR(__xludf.DUMMYFUNCTION("IF(AND($R90, NOT(REGEXMATCH(UPPER($C90), ""INS""))), IFERROR(IF((F90+L90)>0, (F90+L90-M90)/(F90+L90), """"), """"), """")"),0.5054008868212547) -> 0.50540089 | Q90: =IFERROR(__xludf.DUMMYFUNCTION("IF(AND($R90, REGEXMATCH(UPPER($C90), ""INS"")), IFERROR(IF((F90+L90)>0, (F90+L90-M90)/(F90+L90), """"), """"), """")"),"") | R90: TRUE | S90: TRUE | T90: FALSE | U90: In Billing | V90: FALSE | W90: =O90 -> 0.50540089 | X90: =J90 -> 1375.7 | Y90: =F90 -> 1375.7 | Z90: =L90 -> 0 | AA90: =IFERROR(__xludf.DUMMYFUNCTION("""COMPUTED_VALUE"""),"Drew") -> Drew | AB90: =K90 -> 1375.7
A91: 2465 | B91: 20265090 | C91: Charles Shelley | E91: 46106 | F91: 1393.5 | G91: 04/09/2026 | H91: 04/09/2026 | I91: Drew | L91: =if(S91=TRUE,K91-F91,"") | N91: =if(S91=TRUE,K91-M91,"") | O91: =IF($R91, IFERROR(IF((F91+L91)>0, (F91+L91-M91)/(F91+L91), ""), ""), "") | P91: =IFERROR(__xludf.DUMMYFUNCTION("IF(AND($R91, NOT(REGEXMATCH(UPPER($C91), ""INS""))), IFERROR(IF((F91+L91)>0, (F91+L91-M91)/(F91+L91), """"), """"), """")"),"") | Q91: =IFERROR(__xludf.DUMMYFUNCTION("IF(AND($R91, REGEXMATCH(UPPER($C91), ""INS"")), IFERROR(IF((F91+L91)>0, (F91+L91-M91)/(F91+L91), """"), """"), """")"),"") | R91: FALSE | S91: FALSE | T91: FALSE | U91: Job Review | V91: FALSE | W91: =O91 | X91: =J91 | Y91: =F91 -> 1393.5 | Z91: =L91 | AA91: =IFERROR(__xludf.DUMMYFUNCTION("""COMPUTED_VALUE"""),"Drew") -> Drew | AB91: =K91
A92: 2462 | B92: 20265091 | C92: Kyle Knoop | E92: 46106 | F92: 0 | I92: Brett | L92: =if(S92=TRUE,K92-F92,"") | N92: =if(S92=TRUE,K92-M92,"") | O92: =IF($R92, IFERROR(IF((F92+L92)>0, (F92+L92-M92)/(F92+L92), ""), ""), "") | P92: =IFERROR(__xludf.DUMMYFUNCTION("IF(AND($R92, NOT(REGEXMATCH(UPPER($C92), ""INS""))), IFERROR(IF((F92+L92)>0, (F92+L92-M92)/(F92+L92), """"), """"), """")"),"") | Q92: =IFERROR(__xludf.DUMMYFUNCTION("IF(AND($R92, REGEXMATCH(UPPER($C92), ""INS"")), IFERROR(IF((F92+L92)>0, (F92+L92-M92)/(F92+L92), """"), """"), """")"),"") | R92: FALSE | S92: FALSE | T92: FALSE | U92: Approved | V92: FALSE | W92: =O92 | X92: =J92 | Y92: =F92 -> 0 | Z92: =L92 | AA92: =IFERROR(__xludf.DUMMYFUNCTION("""COMPUTED_VALUE"""),"Drew") -> Drew | AB92: =K92
A93: 2409 | B93: 20265092 | C93: Adam Bushmich | E93: 46106 | F93: 690 | G93: 04/16/2026 | H93: 04/16/2026 | I93: Brett | J93: 690 | L93: =if(S93=TRUE,K93-F93,"") | M93: 280 | N93: =if(S93=TRUE,K93-M93,"") | O93: =IF($R93, IFERROR(IF((F93+L93)>0, (F93+L93-M93)/(F93+L93), ""), ""), "") -> 0.5942029 | P93: =IFERROR(__xludf.DUMMYFUNCTION("IF(AND($R93, NOT(REGEXMATCH(UPPER($C93), ""INS""))), IFERROR(IF((F93+L93)>0, (F93+L93-M93)/(F93+L93), """"), """"), """")"),0.5942028985507246) -> 0.5942029 | Q93: =IFERROR(__xludf.DUMMYFUNCTION("IF(AND($R93, REGEXMATCH(UPPER($C93), ""INS"")), IFERROR(IF((F93+L93)>0, (F93+L93-M93)/(F93+L93), """"), """"), """")"),"") | R93: TRUE | S93: FALSE | T93: FALSE | U93: Job Scheduled | V93: FALSE | W93: =O93 -> 0.5942029 | X93: =J93 -> 690 | Y93: =F93 -> 690 | Z93: =L93 | AA93: =IFERROR(__xludf.DUMMYFUNCTION("""COMPUTED_VALUE"""),"Drew") -> Drew | AB93: =K93
A94: 2474 | B94: 20265093 | C94: INS - Aaron Hansgen | E94: 46106 | F94: 0 | I94: Brett | L94: =if(S94=TRUE,K94-F94,"") | N94: =if(S94=TRUE,K94-M94,"") | O94: =IF($R94, IFERROR(IF((F94+L94)>0, (F94+L94-M94)/(F94+L94), ""), ""), "") | P94: =IFERROR(__xludf.DUMMYFUNCTION("IF(AND($R94, NOT(REGEXMATCH(UPPER($C94), ""INS""))), IFERROR(IF((F94+L94)>0, (F94+L94-M94)/(F94+L94), """"), """"), """")"),"") | Q94: =IFERROR(__xludf.DUMMYFUNCTION("IF(AND($R94, REGEXMATCH(UPPER($C94), ""INS"")), IFERROR(IF((F94+L94)>0, (F94+L94-M94)/(F94+L94), """"), """"), """")"),"") | R94: FALSE | S94: FALSE | T94: FALSE | U94: Approved | V94: FALSE | W94: =O94 | X94: =J94 | Y94: =F94 -> 0 | Z94: =L94 | AA94: =IFERROR(__xludf.DUMMYFUNCTION("""COMPUTED_VALUE"""),"Drew") -> Drew | AB94: =K94
A95: 2478 | B95: 20265094 | C95: INS - Kendal Fritz | E95: 46107 | F95: 925.75 | G95: 04/07/2026 | H95: 04/07/2026 | I95: Chris | L95: =if(S95=TRUE,K95-F95,"") | N95: =if(S95=TRUE,K95-M95,"") | O95: =IF($R95, IFERROR(IF((F95+L95)>0, (F95+L95-M95)/(F95+L95), ""), ""), "") | P95: =IFERROR(__xludf.DUMMYFUNCTION("IF(AND($R95, NOT(REGEXMATCH(UPPER($C95), ""INS""))), IFERROR(IF((F95+L95)>0, (F95+L95-M95)/(F95+L95), """"), """"), """")"),"") | Q95: =IFERROR(__xludf.DUMMYFUNCTION("IF(AND($R95, REGEXMATCH(UPPER($C95), ""INS"")), IFERROR(IF((F95+L95)>0, (F95+L95-M95)/(F95+L95), """"), """"), """")"),"") | R95: FALSE | S95: FALSE | T95: FALSE | U95: Job Review | V95: FALSE | W95: =O95 | X95: =J95 | Y95: =F95 -> 925.75 | Z95: =L95 | AA95: =IFERROR(__xludf.DUMMYFUNCTION("""COMPUTED_VALUE"""),"Drew") -> Drew | AB95: =K95
A96: 2291 | B96: 20265095 | C96: Eric Dean | E96: 46107 | F96: 7737.05 | G96: 04/07/2026 | H96: 04/07/2026 | I96: James | L96: =if(S96=TRUE,K96-F96,"") | M96: 5018.6 | N96: =if(S96=TRUE,K96-M96,"") | O96: =IF($R96, IFERROR(IF((F96+L96)>0, (F96+L96-M96)/(F96+L96), ""), ""), "") | P96: =IFERROR(__xludf.DUMMYFUNCTION("IF(AND($R96, NOT(REGEXMATCH(UPPER($C96), ""INS""))), IFERROR(IF((F96+L96)>0, (F96+L96-M96)/(F96+L96), """"), """"), """")"),"") | Q96: =IFERROR(__xludf.DUMMYFUNCTION("IF(AND($R96, REGEXMATCH(UPPER($C96), ""INS"")), IFERROR(IF((F96+L96)>0, (F96+L96-M96)/(F96+L96), """"), """"), """")"),"") | R96: FALSE | S96: FALSE | T96: FALSE | U96: Job Review | V96: FALSE | W96: =O96 | X96: =J96 | Y96: =F96 -> 7737.05 | Z96: =L96 | AA96: =IFERROR(__xludf.DUMMYFUNCTION("""COMPUTED_VALUE"""),"Drew") -> Drew | AB96: =K96
A97: 2498 | B97: 20265096 | C97: Derick Cruea | E97: 46108 | F97: 1278.13 | G97: 04/09/2026 | H97: 04/09/2026 | I97: Chris | J97: 1278.13 | L97: =if(S97=TRUE,K97-F97,"") | N97: =if(S97=TRUE,K97-M97,"") | O97: =IF($R97, IFERROR(IF((F97+L97)>0, (F97+L97-M97)/(F97+L97), ""), ""), "") -> 1 | P97: =IFERROR(__xludf.DUMMYFUNCTION("IF(AND($R97, NOT(REGEXMATCH(UPPER($C97), ""INS""))), IFERROR(IF((F97+L97)>0, (F97+L97-M97)/(F97+L97), """"), """"), """")"),1.0) -> 1 | Q97: =IFERROR(__xludf.DUMMYFUNCTION("IF(AND($R97, REGEXMATCH(UPPER($C97), ""INS"")), IFERROR(IF((F97+L97)>0, (F97+L97-M97)/(F97+L97), """"), """"), """")"),"") | R97: TRUE | S97: FALSE | T97: FALSE | U97: In Billing | V97: FALSE | W97: =O97 -> 1 | X97: =J97 -> 1278.13 | Y97: =F97 -> 1278.13 | Z97: =L97 | AA97: =IFERROR(__xludf.DUMMYFUNCTION("""COMPUTED_VALUE"""),"Drew") -> Drew | AB97: =K97
A98: 2446 | B98: 20265097 | C98: Michelle Perry | E98: 46108 | F98: 976.25 | G98: 04/13/2026 | H98: 04/13/2026 | I98: Chris | L98: =if(S98=TRUE,K98-F98,"") | N98: =if(S98=TRUE,K98-M98,"") | O98: =IF($R98, IFERROR(IF((F98+L98)>0, (F98+L98-M98)/(F98+L98), ""), ""), "") | P98: =IFERROR(__xludf.DUMMYFUNCTION("IF(AND($R98, NOT(REGEXMATCH(UPPER($C98), ""INS""))), IFERROR(IF((F98+L98)>0, (F98+L98-M98)/(F98+L98), """"), """"), """")"),"") | Q98: =IFERROR(__xludf.DUMMYFUNCTION("IF(AND($R98, REGEXMATCH(UPPER($C98), ""INS"")), IFERROR(IF((F98+L98)>0, (F98+L98-M98)/(F98+L98), """"), """"), """")"),"") | R98: FALSE | S98: FALSE | T98: FALSE | U98: Pending Inspection | V98: FALSE | W98: =O98 | X98: =J98 | Y98: =F98 -> 976.25 | Z98: =L98 | AA98: =IFERROR(__xludf.DUMMYFUNCTION("""COMPUTED_VALUE"""),"Drew") -> Drew | AB98: =K98
A99: 2290 | B99: 20265098 | C99: Dave Nelson | E99: 46111 | F99: 25136.83 | I99: Mike | J99: 25136.83 | L99: =if(S99=TRUE,K99-F99,"") | N99: =if(S99=TRUE,K99-M99,"") | O99: =IF($R99, IFERROR(IF((F99+L99)>0, (F99+L99-M99)/(F99+L99), ""), ""), "") -> 1 | P99: =IFERROR(__xludf.DUMMYFUNCTION("IF(AND($R99, NOT(REGEXMATCH(UPPER($C99), ""INS""))), IFERROR(IF((F99+L99)>0, (F99+L99-M99)/(F99+L99), """"), """"), """")"),1.0) -> 1 | Q99: =IFERROR(__xludf.DUMMYFUNCTION("IF(AND($R99, REGEXMATCH(UPPER($C99), ""INS"")), IFERROR(IF((F99+L99)>0, (F99+L99-M99)/(F99+L99), """"), """"), """")"),"") | R99: TRUE | S99: FALSE | T99: FALSE | U99: In Billing | V99: FALSE | W99: =O99 -> 1 | X99: =J99 -> 25136.83 | Y99: =F99 -> 25136.83 | Z99: =L99 | AA99: =IFERROR(__xludf.DUMMYFUNCTION("""COMPUTED_VALUE"""),"Drew") -> Drew | AB99: =K99
A100: 2264 | B100: 20265099 | C100: Braden Clark | E100: 46111 | F100: 577.51 | I100: James | J100: 577.51 | K100: 577.51 | L100: =if(S100=TRUE,K100-F100,"") -> 0 | M100: 11.74 | N100: =if(S100=TRUE,K100-M100,"") -> 565.77 | O100: =IF($R100, IFERROR(IF((F100+L100)>0, (F100+L100-M100)/(F100+L100), ""), ""), "") -> 0.97967135 | P100: =IFERROR(__xludf.DUMMYFUNCTION("IF(AND($R100, NOT(REGEXMATCH(UPPER($C100), ""INS""))), IFERROR(IF((F100+L100)>0, (F100+L100-M100)/(F100+L100), """"), """"), """")"),0.9796713476822912) -> 0.97967135 | Q100: =IFERROR(__xludf.DUMMYFUNCTION("IF(AND($R100, REGEXMATCH(UPPER($C100), ""INS"")), IFERROR(IF((F100+L100)>0, (F100+L100-M100)/(F100+L100), """"), """"), """")"),"") | R100: TRUE | S100: TRUE | T100: TRUE | U100: In Billing | V100: FALSE | W100: =O100 -> 0.97967135 | X100: =J100 -> 577.51 | Y100: =F100 -> 577.51 | Z100: =L100 -> 0 | AA100: =IFERROR(__xludf.DUMMYFUNCTION("""COMPUTED_VALUE"""),"Drew") -> Drew | AB100: =K100 -> 577.51
...

Sheet 2026 Breakdown

Sheet 2026 AM Totals
J1: Av per Contract | K1: Open Jobs
J2: =E2/B2 -> 255.75 | K2: =COUNTIFS('2026'!I:I,"Adam",'2026'!U:U,"<>In Billing") -> 0
J3: =E3/B3 -> 2658.74 | K3: =COUNTIFS('2026'!I:I,"Brett",'2026'!U:U,"<>In Billing") -> 18
J4: =E4/B4 -> 9023.86 | K4: =COUNTIFS('2026'!I:I,"Chris",'2026'!U:U,"<>In Billing") -> 14
J5: =E5/B5 -> 6467.3 | K5: =COUNTIFS('2026'!I:I,"Drew",'2026'!U:U,"<>In Billing") -> 11
J6: =E6/B6 -> 6319.3333 | K6: =COUNTIFS('2026'!I:I,"James",'2026'!U:U,"<>In Billing") -> 49
J7: =E7/B7 -> 6781.6147 | K7: =COUNTIFS('2026'!I:I,"Mike",'2026'!U:U,"<>In Billing") -> 12
J8: =AVERAGE(J2:J7) -> 5251.0997 | K8: =SUM(K2:K7) -> 104

Sheet 2026 Brett
J1: Commission Paid | K1: Commission Owed | L1: Owed has been paid | M1: Manual Override
J2: {=IFERROR(INDEX('Commission Data'!$D:$D,MATCH(1,('Commission Data'!$B:$B=A2)*('Commission Data'!$C:$C="Brett"),0)),0)} -> 27 | K2: {=IFERROR(INDEX('Commission Data'!$E:$E,MATCH(1,('Commission Data'!$B:$B=A2)*('Commission Data'!$C:$C="Brett"),0)),0)} -> 0 | L2: FALSE | M2: FALSE
J3: {=IFERROR(INDEX('Commission Data'!$D:$D,MATCH(1,('Commission Data'!$B:$B=A3)*('Commission Data'!$C:$C="Brett"),0)),0)} -> 27.5 | K3: {=IFERROR(INDEX('Commission Data'!$E:$E,MATCH(1,('Commission Data'!$B:$B=A3)*('Commission Data'!$C:$C="Brett"),0)),0)} -> 0 | L3: FALSE | M3: FALSE
J4: {=IFERROR(INDEX('Commission Data'!$D:$D,MATCH(1,('Commission Data'!$B:$B=A4)*('Commission Data'!$C:$C="Brett"),0)),0)} -> 708.35 | K4: {=IFERROR(INDEX('Commission Data'!$E:$E,MATCH(1,('Commission Data'!$B:$B=A4)*('Commission Data'!$C:$C="Brett"),0)),0)} -> 0 | L4: FALSE | M4: FALSE
J5: {=IFERROR(INDEX('Commission Data'!$D:$D,MATCH(1,('Commission Data'!$B:$B=A5)*('Commission Data'!$C:$C="Brett"),0)),0)} -> 0 | K5: {=IFERROR(INDEX('Commission Data'!$E:$E,MATCH(1,('Commission Data'!$B:$B=A5)*('Commission Data'!$C:$C="Brett"),0)),0)} -> 0 | L5: FALSE | M5: FALSE
J6: {=IFERROR(INDEX('Commission Data'!$D:$D,MATCH(1,('Commission Data'!$B:$B=A6)*('Commission Data'!$C:$C="Brett"),0)),0)} -> 29.5 | K6: {=IFERROR(INDEX('Commission Data'!$E:$E,MATCH(1,('Commission Data'!$B:$B=A6)*('Commission Data'!$C:$C="Brett"),0)),0)} -> 0 | L6: FALSE | M6: FALSE
J7: {=IFERROR(INDEX('Commission Data'!$D:$D,MATCH(1,('Commission Data'!$B:$B=A7)*('Commission Data'!$C:$C="Brett"),0)),0)} -> 29.5 | K7: {=IFERROR(INDEX('Commission Data'!$E:$E,MATCH(1,('Commission Data'!$B:$B=A7)*('Commission Data'!$C:$C="Brett"),0)),0)} -> 0 | L7: FALSE | M7: FALSE
J8: {=IFERROR(INDEX('Commission Data'!$D:$D,MATCH(1,('Commission Data'!$B:$B=A8)*('Commission Data'!$C:$C="Brett"),0)),0)} -> 1278 | K8: {=IFERROR(INDEX('Commission Data'!$E:$E,MATCH(1,('Commission Data'!$B:$B=A8)*('Commission Data'!$C:$C="Brett"),0)),0)} -> 0 | L8: FALSE | M8: FALSE
J9: {=IFERROR(INDEX('Commission Data'!$D:$D,MATCH(1,('Commission Data'!$B:$B=A9)*('Commission Data'!$C:$C="Brett"),0)),0)} -> 0 | K9: {=IFERROR(INDEX('Commission Data'!$E:$E,MATCH(1,('Commission Data'!$B:$B=A9)*('Commission Data'!$C:$C="Brett"),0)),0)} -> 0 | L9: FALSE | M9: FALSE
J10: {=IFERROR(INDEX('Commission Data'!$D:$D,MATCH(1,('Commission Data'!$B:$B=A10)*('Commission Data'!$C:$C="Brett"),0)),0)} -> 0 | K10: {=IFERROR(INDEX('Commission Data'!$E:$E,MATCH(1,('Commission Data'!$B:$B=A10)*('Commission Data'!$C:$C="Brett"),0)),0)} -> 0 | L10: FALSE | M10: FALSE
J11: {=IFERROR(INDEX('Commission Data'!$D:$D,MATCH(1,('Commission Data'!$B:$B=A11)*('Commission Data'!$C:$C="Brett"),0)),0)} -> 0 | K11: {=IFERROR(INDEX('Commission Data'!$E:$E,MATCH(1,('Commission Data'!$B:$B=A11)*('Commission Data'!$C:$C="Brett"),0)),0)} -> 0 | L11: FALSE | M11: FALSE
J12: {=IFERROR(INDEX('Commission Data'!$D:$D,MATCH(1,('Commission Data'!$B:$B=A12)*('Commission Data'!$C:$C="Brett"),0)),0)} -> 0 | K12: {=IFERROR(INDEX('Commission Data'!$E:$E,MATCH(1,('Commission Data'!$B:$B=A12)*('Commission Data'!$C:$C="Brett"),0)),0)} -> 0 | L12: FALSE | M12: FALSE
J13: {=IFERROR(INDEX('Commission Data'!$D:$D,MATCH(1,('Commission Data'!$B:$B=A13)*('Commission Data'!$C:$C="Brett"),0)),0)} -> 0 | K13: {=IFERROR(INDEX('Commission Data'!$E:$E,MATCH(1,('Commission Data'!$B:$B=A13)*('Commission Data'!$C:$C="Brett"),0)),0)} -> 0 | L13: FALSE | M13: FALSE
... J101: {=IFERROR(INDEX('Commission Data'!$D:$D,MATCH(1,('Commission Data'!$B:$B=A101)*('Commission Data'!$C:$C="Brett"),0)),0)} -> 0 | K101: {=IFERROR(INDEX('Commission Data'!$E:$E,MATCH(1,('Commission Data'!$B:$B=A101)*('Commission Data'!$C:$C="Brett"),0)),0)} -> 0 | L101: FALSE | M101: FALSE

Sheet 2026 Drew
J1: Commission Paid | K1: Commission Owed | L1: Owed has been paid | M1: Manual Override
J2: {=IFERROR(INDEX('Commission Data'!$D:$D,MATCH(1,('Commission Data'!$B:$B=A2)*('Commission Data'!$C:$C="Drew"),0)),0)} -> 176.03 | K2: {=IFERROR(INDEX('Commission Data'!$E:$E,MATCH(1,('Commission Data'!$B:$B=A2)*('Commission Data'!$C:$C="Drew"),0)),0)} -> 0 | L2: FALSE | M2: FALSE
J3: {=IFERROR(INDEX('Commission Data'!$D:$D,MATCH(1,('Commission Data'!$B:$B=A3)*('Commission Data'!$C:$C="Drew"),0)),0)} -> 5.4 | K3: {=IFERROR(INDEX('Commission Data'!$E:$E,MATCH(1,('Commission Data'!$B:$B=A3)*('Commission Data'!$C:$C="Drew"),0)),0)} -> 0 | L3: FALSE | M3: FALSE
J4: {=IFERROR(INDEX('Commission Data'!$D:$D,MATCH(1,('Commission Data'!$B:$B=A4)*('Commission Data'!$C:$C="Drew"),0)),0)} -> 11.83 | K4: {=IFERROR(INDEX('Commission Data'!$E:$E,MATCH(1,('Commission Data'!$B:$B=A4)*('Commission Data'!$C:$C="Drew"),0)),0)} -> 0 | L4: FALSE | M4: FALSE
J5: {=IFERROR(INDEX('Commission Data'!$D:$D,MATCH(1,('Commission Data'!$B:$B=A5)*('Commission Data'!$C:$C="Drew"),0)),0)} -> 0 | K5: {=IFERROR(INDEX('Commission Data'!$E:$E,MATCH(1,('Commission Data'!$B:$B=A5)*('Commission Data'!$C:$C="Drew"),0)),0)} -> 0 | L5: FALSE | M5: FALSE
J6: {=IFERROR(INDEX('Commission Data'!$D:$D,MATCH(1,('Commission Data'!$B:$B=A6)*('Commission Data'!$C:$C="Drew"),0)),0)} -> 27.47 | K6: {=IFERROR(INDEX('Commission Data'!$E:$E,MATCH(1,('Commission Data'!$B:$B=A6)*('Commission Data'!$C:$C="Drew"),0)),0)} -> 0 | L6: FALSE | M6: FALSE
J7: {=IFERROR(INDEX('Commission Data'!$D:$D,MATCH(1,('Commission Data'!$B:$B=A7)*('Commission Data'!$C:$C="Drew"),0)),0)} -> 5.5 | K7: {=IFERROR(INDEX('Commission Data'!$E:$E,MATCH(1,('Commission Data'!$B:$B=A7)*('Commission Data'!$C:$C="Drew"),0)),0)} -> 0 | L7: FALSE | M7: FALSE
J8: {=IFERROR(INDEX('Commission Data'!$D:$D,MATCH(1,('Commission Data'!$B:$B=A8)*('Commission Data'!$C:$C="Drew"),0)),0)} -> 0 | K8: {=IFERROR(INDEX('Commission Data'!$E:$E,MATCH(1,('Commission Data'!$B:$B=A8)*('Commission Data'!$C:$C="Drew"),0)),0)} -> 2.4 | L8: FALSE | M8: FALSE
J9: {=IFERROR(INDEX('Commission Data'!$D:$D,MATCH(1,('Commission Data'!$B:$B=A9)*('Commission Data'!$C:$C="Drew"),0)),0)} -> 0 | K9: {=IFERROR(INDEX('Commission Data'!$E:$E,MATCH(1,('Commission Data'!$B:$B=A9)*('Commission Data'!$C:$C="Drew"),0)),0)} -> 0 | L9: FALSE | M9: FALSE
J10: {=IFERROR(INDEX('Commission Data'!$D:$D,MATCH(1,('Commission Data'!$B:$B=A10)*('Commission Data'!$C:$C="Drew"),0)),0)} -> 0 | K10: {=IFERROR(INDEX('Commission Data'!$E:$E,MATCH(1,('Commission Data'!$B:$B=A10)*('Commission Data'!$C:$C="Drew"),0)),0)} -> 0 | L10: FALSE | M10: FALSE
J11: {=IFERROR(INDEX('Commission Data'!$D:$D,MATCH(1,('Commission Data'!$B:$B=A11)*('Commission Data'!$C:$C="Drew"),0)),0)} -> 322.65 | K11: {=IFERROR(INDEX('Commission Data'!$E:$E,MATCH(1,('Commission Data'!$B:$B=A11)*('Commission Data'!$C:$C="Drew"),0)),0)} -> 0 | L11: FALSE | M11: FALSE
J12: {=IFERROR(INDEX('Commission Data'!$D:$D,MATCH(1,('Commission Data'!$B:$B=A12)*('Commission Data'!$C:$C="Drew"),0)),0)} -> 0 | K12: {=IFERROR(INDEX('Commission Data'!$E:$E,MATCH(1,('Commission Data'!$B:$B=A12)*('Commission Data'!$C:$C="Drew"),0)),0)} -> 0 | L12: FALSE | M12: FALSE
J13: {=IFERROR(INDEX('Commission Data'!$D:$D,MATCH(1,('Commission Data'!$B:$B=A13)*('Commission Data'!$C:$C="Drew"),0)),0)} -> 5.06 | K13: {=IFERROR(INDEX('Commission Data'!$E:$E,MATCH(1,('Commission Data'!$B:$B=A13)*('Commission Data'!$C:$C="Drew"),0)),0)} -> 0 | L13: FALSE | M13: FALSE
... J400: {=IFERROR(INDEX('Commission Data'!$D:$D,MATCH(1,('Commission Data'!$B:$B=A400)*('Commission Data'!$C:$C="Drew"),0)),0)} -> 0 | K400: {=IFERROR(INDEX('Commission Data'!$E:$E,MATCH(1,('Commission Data'!$B:$B=A400)*('Commission Data'!$C:$C="Drew"),0)),0)} -> 0 | L400: FALSE | M400: FALSE

Sheet 2026 James
J1: Commission Paid | K1: Commission Owed | L1: Owed has been paid | M1: Manual Override
J2: {=IFERROR(INDEX('Commission Data'!$D:$D,MATCH(1,('Commission Data'!$B:$B=A2)*('Commission Data'!$C:$C="James"),0)),0)} -> 118.27 | K2: {=IFERROR(INDEX('Commission Data'!$E:$E,MATCH(1,('Commission Data'!$B:$B=A2)*('Commission Data'!$C:$C="James"),0)),0)} -> 0 | L2: FALSE | M2: FALSE
J3: {=IFERROR(INDEX('Commission Data'!$D:$D,MATCH(1,('Commission Data'!$B:$B=A3)*('Commission Data'!$C:$C="James"),0)),0)} -> 0 | K3: {=IFERROR(INDEX('Commission Data'!$E:$E,MATCH(1,('Commission Data'!$B:$B=A3)*('Commission Data'!$C:$C="James"),0)),0)} -> 0 | L3: FALSE | M3: FALSE
J4: {=IFERROR(INDEX('Commission Data'!$D:$D,MATCH(1,('Commission Data'!$B:$B=A4)*('Commission Data'!$C:$C="James"),0)),0)} -> 274.69 | K4: {=IFERROR(INDEX('Commission Data'!$E:$E,MATCH(1,('Commission Data'!$B:$B=A4)*('Commission Data'!$C:$C="James"),0)),0)} -> 0 | L4: FALSE | M4: FALSE
J5: {=IFERROR(INDEX('Commission Data'!$D:$D,MATCH(1,('Commission Data'!$B:$B=A5)*('Commission Data'!$C:$C="James"),0)),0)} -> 0 | K5: {=IFERROR(INDEX('Commission Data'!$E:$E,MATCH(1,('Commission Data'!$B:$B=A5)*('Commission Data'!$C:$C="James"),0)),0)} -> 0 | L5: FALSE | M5: FALSE
J6: {=IFERROR(INDEX('Commission Data'!$D:$D,MATCH(1,('Commission Data'!$B:$B=A6)*('Commission Data'!$C:$C="James"),0)),0)} -> 3226.54 | K6: {=IFERROR(INDEX('Commission Data'!$E:$E,MATCH(1,('Commission Data'!$B:$B=A6)*('Commission Data'!$C:$C="James"),0)),0)} -> 0 | L6: FALSE | M6: FALSE
J7: {=IFERROR(INDEX('Commission Data'!$D:$D,MATCH(1,('Commission Data'!$B:$B=A7)*('Commission Data'!$C:$C="James"),0)),0)} -> 0 | K7: {=IFERROR(INDEX('Commission Data'!$E:$E,MATCH(1,('Commission Data'!$B:$B=A7)*('Commission Data'!$C:$C="James"),0)),0)} -> 0 | L7: FALSE | M7: FALSE
J8: {=IFERROR(INDEX('Commission Data'!$D:$D,MATCH(1,('Commission Data'!$B:$B=A8)*('Commission Data'!$C:$C="James"),0)),0)} -> 1757.93 | K8: {=IFERROR(INDEX('Commission Data'!$E:$E,MATCH(1,('Commission Data'!$B:$B=A8)*('Commission Data'!$C:$C="James"),0)),0)} -> 0 | L8: FALSE | M8: FALSE
J9: {=IFERROR(INDEX('Commission Data'!$D:$D,MATCH(1,('Commission Data'!$B:$B=A9)*('Commission Data'!$C:$C="James"),0)),0)} -> 0 | K9: {=IFERROR(INDEX('Commission Data'!$E:$E,MATCH(1,('Commission Data'!$B:$B=A9)*('Commission Data'!$C:$C="James"),0)),0)} -> 0 | L9: FALSE | M9: FALSE
J10: {=IFERROR(INDEX('Commission Data'!$D:$D,MATCH(1,('Commission Data'!$B:$B=A10)*('Commission Data'!$C:$C="James"),0)),0)} -> 0 | K10: {=IFERROR(INDEX('Commission Data'!$E:$E,MATCH(1,('Commission Data'!$B:$B=A10)*('Commission Data'!$C:$C="James"),0)),0)} -> 0 | L10: FALSE | M10: FALSE
J11: {=IFERROR(INDEX('Commission Data'!$D:$D,MATCH(1,('Commission Data'!$B:$B=A11)*('Commission Data'!$C:$C="James"),0)),0)} -> 2428.01 | K11: {=IFERROR(INDEX('Commission Data'!$E:$E,MATCH(1,('Commission Data'!$B:$B=A11)*('Commission Data'!$C:$C="James"),0)),0)} -> 404.06 | L11: FALSE | M11: FALSE
J12: {=IFERROR(INDEX('Commission Data'!$D:$D,MATCH(1,('Commission Data'!$B:$B=A12)*('Commission Data'!$C:$C="James"),0)),0)} -> 0 | K12: {=IFERROR(INDEX('Commission Data'!$E:$E,MATCH(1,('Commission Data'!$B:$B=A12)*('Commission Data'!$C:$C="James"),0)),0)} -> 0 | L12: FALSE | M12: FALSE
J13: {=IFERROR(INDEX('Commission Data'!$D:$D,MATCH(1,('Commission Data'!$B:$B=A13)*('Commission Data'!$C:$C="James"),0)),0)} -> 50.63 | K13: {=IFERROR(INDEX('Commission Data'!$E:$E,MATCH(1,('Commission Data'!$B:$B=A13)*('Commission Data'!$C:$C="James"),0)),0)} -> 0 | L13: FALSE | M13: FALSE
... J201: {=IFERROR(INDEX('Commission Data'!$D:$D,MATCH(1,('Commission Data'!$B:$B=A201)*('Commission Data'!$C:$C="James"),0)),0)} -> 0 | K201: {=IFERROR(INDEX('Commission Data'!$E:$E,MATCH(1,('Commission Data'!$B:$B=A201)*('Commission Data'!$C:$C="James"),0)),0)} -> 0 | L201: FALSE | M201: FALSE

Sheet 2026 Mike
J1: Commission Paid | K1: Commission Owed | L1: Owed has been paid | M1: Manual Override
J2: {=IFERROR(INDEX('Commission Data'!$D:$D,MATCH(1,('Commission Data'!$B:$B=A2)*('Commission Data'!$C:$C="Mike"),0)),0)} -> 25.31 | K2: {=IFERROR(INDEX('Commission Data'!$E:$E,MATCH(1,('Commission Data'!$B:$B=A2)*('Commission Data'!$C:$C="Mike"),0)),0)} -> 0 | L2: FALSE | M2: FALSE
J3: {=IFERROR(INDEX('Commission Data'!$D:$D,MATCH(1,('Commission Data'!$B:$B=A3)*('Commission Data'!$C:$C="Mike"),0)),0)} -> 0 | K3: {=IFERROR(INDEX('Commission Data'!$E:$E,MATCH(1,('Commission Data'!$B:$B=A3)*('Commission Data'!$C:$C="Mike"),0)),0)} -> 0 | L3: FALSE | M3: FALSE
J4: {=IFERROR(INDEX('Commission Data'!$D:$D,MATCH(1,('Commission Data'!$B:$B=A4)*('Commission Data'!$C:$C="Mike"),0)),0)} -> 0 | K4: {=IFERROR(INDEX('Commission Data'!$E:$E,MATCH(1,('Commission Data'!$B:$B=A4)*('Commission Data'!$C:$C="Mike"),0)),0)} -> 0 | L4: FALSE | M4: FALSE
J5: {=IFERROR(INDEX('Commission Data'!$D:$D,MATCH(1,('Commission Data'!$B:$B=A5)*('Commission Data'!$C:$C="Mike"),0)),0)} -> 0 | K5: {=IFERROR(INDEX('Commission Data'!$E:$E,MATCH(1,('Commission Data'!$B:$B=A5)*('Commission Data'!$C:$C="Mike"),0)),0)} -> 0 | L5: FALSE | M5: FALSE
J6: {=IFERROR(INDEX('Commission Data'!$D:$D,MATCH(1,('Commission Data'!$B:$B=A6)*('Commission Data'!$C:$C="Mike"),0)),0)} -> 0 | K6: {=IFERROR(INDEX('Commission Data'!$E:$E,MATCH(1,('Commission Data'!$B:$B=A6)*('Commission Data'!$C:$C="Mike"),0)),0)} -> 0 | L6: FALSE | M6: FALSE
J7: {=IFERROR(INDEX('Commission Data'!$D:$D,MATCH(1,('Commission Data'!$B:$B=A7)*('Commission Data'!$C:$C="Mike"),0)),0)} -> 0 | K7: {=IFERROR(INDEX('Commission Data'!$E:$E,MATCH(1,('Commission Data'!$B:$B=A7)*('Commission Data'!$C:$C="Mike"),0)),0)} -> 0 | L7: FALSE | M7: FALSE
J8: {=IFERROR(INDEX('Commission Data'!$D:$D,MATCH(1,('Commission Data'!$B:$B=A8)*('Commission Data'!$C:$C="Mike"),0)),0)} -> 0 | K8: {=IFERROR(INDEX('Commission Data'!$E:$E,MATCH(1,('Commission Data'!$B:$B=A8)*('Commission Data'!$C:$C="Mike"),0)),0)} -> 0 | L8: FALSE | M8: FALSE
J9: {=IFERROR(INDEX('Commission Data'!$D:$D,MATCH(1,('Commission Data'!$B:$B=A9)*('Commission Data'!$C:$C="Mike"),0)),0)} -> 0 | K9: {=IFERROR(INDEX('Commission Data'!$E:$E,MATCH(1,('Commission Data'!$B:$B=A9)*('Commission Data'!$C:$C="Mike"),0)),0)} -> 0 | L9: FALSE | M9: FALSE
J10: {=IFERROR(INDEX('Commission Data'!$D:$D,MATCH(1,('Commission Data'!$B:$B=A10)*('Commission Data'!$C:$C="Mike"),0)),0)} -> 0 | K10: {=IFERROR(INDEX('Commission Data'!$E:$E,MATCH(1,('Commission Data'!$B:$B=A10)*('Commission Data'!$C:$C="Mike"),0)),0)} -> 0 | L10: FALSE | M10: FALSE
J11: {=IFERROR(INDEX('Commission Data'!$D:$D,MATCH(1,('Commission Data'!$B:$B=A11)*('Commission Data'!$C:$C="Mike"),0)),0)} -> 0 | K11: {=IFERROR(INDEX('Commission Data'!$E:$E,MATCH(1,('Commission Data'!$B:$B=A11)*('Commission Data'!$C:$C="Mike"),0)),0)} -> 0 | L11: FALSE | M11: FALSE
J12: {=IFERROR(INDEX('Commission Data'!$D:$D,MATCH(1,('Commission Data'!$B:$B=A12)*('Commission Data'!$C:$C="Mike"),0)),0)} -> 0 | K12: {=IFERROR(INDEX('Commission Data'!$E:$E,MATCH(1,('Commission Data'!$B:$B=A12)*('Commission Data'!$C:$C="Mike"),0)),0)} -> 0 | L12: FALSE | M12: FALSE
J13: {=IFERROR(INDEX('Commission Data'!$D:$D,MATCH(1,('Commission Data'!$B:$B=A13)*('Commission Data'!$C:$C="Mike"),0)),0)} -> 0 | K13: {=IFERROR(INDEX('Commission Data'!$E:$E,MATCH(1,('Commission Data'!$B:$B=A13)*('Commission Data'!$C:$C="Mike"),0)),0)} -> 0 | L13: FALSE | M13: FALSE
... J101: {=IFERROR(INDEX('Commission Data'!$D:$D,MATCH(1,('Commission Data'!$B:$B=A101)*('Commission Data'!$C:$C="Mike"),0)),0)} -> 0 | K101: {=IFERROR(INDEX('Commission Data'!$E:$E,MATCH(1,('Commission Data'!$B:$B=A101)*('Commission Data'!$C:$C="Mike"),0)),0)} -> 0 | L101: FALSE | M101: FALSE

Sheet Paid 2026
A1: 2026-01
A2: Job Number | B2: Name | C2: Contract Amount | D2: Change Orders | E2: Invoiced Total | F2: Cost | G2: GP | H2: GP % | I2: Paid in Full
A3: 20255005 | B3: INS - Stephanie Quintor | C3: 26697.13 | D3: 21916.54 | E3: 36000 | F3: 18394.18 | G3: 30219.49 | H3: 0.62162536 | I3: TRUE
A4: 20255063 | B4: INS - Glen Shelley | C4: 12550.85 | D4: 3160.77 | E4: 11109.02 | F4: 8075.9 | G4: 7635.72 | H4: 0.4859919 | I4: TRUE
A5: 20255069 | B5: INS - New Jasper Fire Station | C5: 127206.86 | D5: 34039.3 | E5: 130000 | F5: 60012.3 | G5: 101233.86 | H5: 0.62782183 | I5: TRUE
A6: 20255118 | B6: Dustin Dietz | C6: 19555.76 | D6: 997.24 | E6: 20553 | F6: 12209.75 | G6: 8343.25 | H6: 0.40593831 | I6: TRUE
A7: 20255136 | B7: INS - Paul Herzog | C7: 8277.77 | D7: -1277.77 | E7: 8277.77 | F7: 4791.7 | G7: 2208.3 | H7: 0.31547143 | I7: TRUE
A8: 20255174 | B8: Judy Shobe | C8: 29206.59 | D8: 1508.04 | E8: 29206.59 | F8: 16860.76 | G8: 13853.87 | H8: 0.45105118 | I8: TRUE
A9: 20255176 | B9: Ransae Hall | C9: 15486.94 | D9: 55 | E9: 15541.94 | F9: 8538.38 | G9: 7003.56 | H9: 0.45062328 | I9: TRUE
A10: 20255177 | B10: Daron Brown | C10: 9476.93 | E10: 9476.93 | F10: 6160.74 | G10: 3316.19 | H10: 0.34992239 | I10: TRUE
A11: 20255179 | B11: Ryan Walker | C11: 20025.57 | D11: 2376 | E11: 22401.57 | F11: 11413.68 | G11: 10987.89 | H11: 0.49049643 | I11: TRUE
A12: 20255183 | B12: Barb Spurgeon | C12: 1296.78 | D12: 150 | E12: 1296.78 | F12: 661.01 | G12: 785.77 | H12: 0.54311644 | I12: TRUE
A13: 20255191 | B13: Jeff Hobbs | C13: 27975 | D13: 1100 | E13: 29075 | F13: 17240.4 | G13: 11834.6 | H13: 0.40703697 | I13: TRUE
A14: 20255196 | B14: Frank Baxter | C14: 49280.61 | D14: -1127.69 | E14: 48252.92 | F14: 30699.18 | G14: 17453.74 | H14: 0.36246483 | I14: TRUE
A15: 20255199 | B15: Sherrill Silvers | C15: 4927.85 | D15: 55 | E15: 4982.85 | F15: 2042.46 | G15: 2940.39 | H15: 0.59010205 | I15: TRUE
A16: 20255202 | B16: Dayton Dreamcenter | C16: 5540 | E16: 5540 | F16: 2050 | G16: 3490 | H16: 0.6299639 | I16: TRUE
A17: 20255204 | B17: Dee Scherer | C17: 2520 | E17: 2520 | F17: 600 | G17: 1920 | H17: 0.76190476 | I17: TRUE
A18: 20255206 | B18: William Barrett | C18: 5766.66 | E18: 5766.66 | F18: 3459.99 | G18: 2306.67 | H18: 0.40000104 | I18: TRUE
A19: 20255220 | B19: Dan Moorhead | C19: 1102.09 | E19: 1102.09 | F19: 400 | G19: 702.09 | H19: 0.63705324 | I19: TRUE
A20: 20255229 | B20: Mary Mastronicola | C20: 240 | E20: 240 | F20: 0.01 | G20: 239.99 | H20: 0.99995833 | I20: TRUE

Sheet Commission Data
A1: Lead Number | B1: Job Number | C1: Salesperson | D1: Paid | E1: Owed | F1: Override Flag
A2: 1083 | B2: 20255003 | C2: James | D2: 1883.14 | E2: 0 | F2: FALSE
A3: 1095 | B3: 20255009 | C3: James | D3: 1740.43 | E3: 0 | F3: TRUE
A4: 1105 | B4: 20255010 | C4: Drew | D4: 572.18 | E4: 143.04 | F4: FALSE
A5: 1136 | B5: 20255014 | C5: James | D5: 169.52 | E5: 0 | F5: FALSE
A6: 1143 | B6: 20255015 | C6: James | D6: 678.51 | E6: 0 | F6: FALSE
A7: 1173 | B7: 20255017 | C7: Will | D7: 0 | E7: 0 | F7: FALSE
A8: 1170 | B8: 20255018 | C8: James | D8: 1393.23 | E8: 0 | F8: TRUE
A9: 1154 | B9: 20255019 | C9: Brett | D9: 929.91 | E9: 0 | F9: FALSE
A10: 1127 | B10: 20255020 | C10: Brett | D10: 1085.61 | E10: 0 | F10: FALSE
A11: 1139 | B11: 20255021 | C11: Drew | D11: 85.71 | E11: 0 | F11: FALSE
A12: 1179 | B12: 20255022 | C12: James | D12: 516.38 | E12: 0 | F12: FALSE
A13: 1159 | B13: 20255023 | C13: Drew | D13: 568.74 | E13: 0 | F13: FALSE
... A42: 1155 | B42: 20255057 | C42: Brett | D42: 935.61 | E42: 0 | F42: FALSE
A43: 1319 | B43: 20255058 | C43: Drew | D43: 61.31 | F43: FALSE
A44: 1360 | B44: 20255059 | C44: Drew | D44: 47 | E44: 0 | F44: FALSE
A45: 1350 | B45: 20255060 | C45: James | D45: 17.5 | E45: 0 | F45: FALSE
A46: 1286 | B46: 20255061 | C46: Brett | D46: 538.36 | E46: 0 | F46: FALSE
A47: 1356 | B47: 20255062 | C47: Drew | D47: 503.03 | E47: 0 | F47: FALSE
A48: 1153 | B48: 20255063 | C48: Brett | D48: 785.59 | E48: 0 | F48: FALSE
A49: 1333 | B49: 20255064 | C49: Drew | D49: 309.2 | E49: 0 | F49: FALSE
A50: 1225 | B50: 20255065 | C50: James | D50: 1955.84 | E50: 0 | F50: TRUE
A51: 1200 | B51: 20255066 | C51: Drew | D51: 1122.45 | E51: 0 | F51: FALSE
A52: 1327 | B52: 20255067 | C52: Drew | D52: 713.49 | E52: 0 | F52: FALSE
A53: 1273 | B53: 20255068 | C53: James | D53: 1131.93 | E53: 0 | F53: FALSE
A54: 1299 | B54: 20255069 | C54: Drew | D54: 8062.31 | E54: 0 | F54: FALSE
A55: 1309 | B55: 20255070 | C55: Drew | D55: 1040.55 | E55: 0 | F55: FALSE
... A472: 1691 | B472: 20265042 | C472: Drew | D472: 0 | E472: 0 | F472: FALSE

Sheet 2026 Surveys

Sheet 2025
A1: Project # | B1: Job # | C1: Name | D1: Type | E1: Date | F1: Contract Amt $3,015,547.20 | G1: Projected Start Date | H1: Projected End Date | I1: AM | J1: ="Invoiced Total $" & TEXT(SUM(J2:J233),"#,##0.00") -> Invoiced Total $3,306,820.45 | K1: ="Amount Paid $" & TEXT(SUM(K2:K233),"#,##0.00") -> Amount Paid $3,648,737.33 | L1: ="Change Orders $" & TEXT(SUM(L2:L233),"#,##0.00") -> Change Orders $233,887.95 | M1: ="Cost $" & TEXT(SUM(M2:M233),"#,##0.00") -> Cost $1,901,675.62 | N1: ="GP $" & TEXT(SUM(N2:N233),"#,##0.00") -> GP $1,277,104.64 | O1: =AVERAGEIFS(O2:O233, O2:O233, "<>", S2:S233, TRUE) -> 0.47682031 | P1: =AVERAGEIFS(P2:P233, P2:P233, "<>", S2:S233, TRUE) -> 0.46693985 | Q1: =AVERAGEIFS(Q2:Q233, Q2:Q233, "<>", S2:S233, TRUE) -> 0.55016782 | R1: Billed | S1: Paid in Full | T1: Comm Owed | U1: Status | V1: Updated this week | W1: GP | X1: Invoiced | Y1: Contract | Z1: Change Orders | AA1: =IFERROR(__xludf.DUMMYFUNCTION("ARRAYFORMULA({ ""Manager""; IF(A2:A389="""","""", IF(IFERROR(VALUE(A2:A389),0)>=1857, ""Drew"", IF( REGEXMATCH( LOWER( TRIM( SUBSTITUTE( SUBSTITUTE( CLEAN(I2:I389), "&" CHAR(160),"" "" ), CHAR(9),"""" ) ) ), ""^drew$"" ), ""Drew"","""" ) ) ) }) "),"Manager") -> Manager | AB1: Amount Paid | AC1: Date of Last Payment
A2: 1050 | B2: 20255001 | C2: Lauren Mccoy | D2: Roofing and Siding | E2: 45664.412 | F2: 1770 | G2: 45713 | H2: 45714 | I2: Mike | J2: 1770 | K2: 1770 | L2: =if(S2=TRUE,K2-F2,"") -> 0 | M2: 607.08 | N2: =if(S2=TRUE,K2-M2,"") -> 1162.92 | O2: =IF($R2, IFERROR(IF((F2+L2)>0, (F2+L2-M2)/(F2+L2), ""), ""), "") -> 0.65701695 | P2: =IFERROR(__xludf.DUMMYFUNCTION("IF(AND($R2, NOT(REGEXMATCH(UPPER($C2), ""INS""))), IFERROR(IF((F2+L2)>0, (F2+L2-M2)/(F2+L2), """"), """"), """")"),0.6570169491525424) -> 0.65701695 | Q2: =IFERROR(__xludf.DUMMYFUNCTION("IF(AND($R2, REGEXMATCH(UPPER($C2), ""INS"")), IFERROR(IF((F2+L2)>0, (F2+L2-M2)/(F2+L2), """"), """"), """")"),"") | R2: TRUE | S2: TRUE | T2: TRUE | U2: In Billing | V2: TRUE | W2: =O2 -> 0.65701695 | X2: =J2 -> 1770 | Y2: =F2 -> 1770 | Z2: =L2 -> 0 | AA2: =IFERROR(__xludf.DUMMYFUNCTION("""COMPUTED_VALUE"""),"") | AB2: =K2 -> 1770
A3: 1074 | B3: 20255002 | C3: Dennis Hong | D3: Roofing and Siding | E3: 45674.543 | F3: 0 | G3: 45742 | H3: 45743 | I3: Adam | J3: 0 | K3: 0 | L3: =if(S3=TRUE,K3-F3,"") -> 0 | M3: 0 | N3: =if(S3=TRUE,K3-M3,"") -> 0 | O3: =IF($R3, IFERROR(IF((F3+L3)>0, (F3+L3-M3)/(F3+L3), ""), ""), "") | P3: =IFERROR(__xludf.DUMMYFUNCTION("IF(AND($R3, NOT(REGEXMATCH(UPPER($C3), ""INS""))), IFERROR(IF((F3+L3)>0, (F3+L3-M3)/(F3+L3), """"), """"), """")"),"") | Q3: =IFERROR(__xludf.DUMMYFUNCTION("IF(AND($R3, REGEXMATCH(UPPER($C3), ""INS"")), IFERROR(IF((F3+L3)>0, (F3+L3-M3)/(F3+L3), """"), """"), """")"),"") | R3: TRUE | S3: TRUE | T3: FALSE | U3: In Billing | V3: TRUE | W3: =O3 | X3: =J3 -> 0 | Y3: =F3 -> 0 | Z3: =L3 -> 0 | AA3: =IFERROR(__xludf.DUMMYFUNCTION("""COMPUTED_VALUE"""),"") | AB3: =K3 -> 0
A4: 1083 | B4: 20255003 | C4: Doug Gregory | D4: Roofing and Siding | E4: 45674.544 | F4: 45266 | G4: 45827 | H4: 45827 | I4: James | J4: 47078.44 | K4: 47078.44 | L4: =if(S4=TRUE,K4-F4,"") -> 1812.44 | M4: 38797.66 | N4: =if(S4=TRUE,K4-M4,"") -> 8280.78 | O4: =IF($R4, IFERROR(IF((F4+L4)>0, (F4+L4-M4)/(F4+L4), ""), ""), "") -> 0.17589325 | P4: =IFERROR(__xludf.DUMMYFUNCTION("IF(AND($R4, NOT(REGEXMATCH(UPPER($C4), ""INS""))), IFERROR(IF((F4+L4)>0, (F4+L4-M4)/(F4+L4), """"), """"), """")"),0.17589325389711297) -> 0.17589325 | Q4: =IFERROR(__xludf.DUMMYFUNCTION("IF(AND($R4, REGEXMATCH(UPPER($C4), ""INS"")), IFERROR(IF((F4+L4)>0, (F4+L4-M4)/(F4+L4), """"), """"), """")"),"") | R4: TRUE | S4: TRUE | T4: FALSE | U4: In Billing | V4: TRUE | W4: =O4 -> 0.17589325 | X4: =J4 -> 47078.44 | Y4: =F4 -> 45266 | Z4: =L4 -> 1812.44 | AA4: =IFERROR(__xludf.DUMMYFUNCTION("""COMPUTED_VALUE"""),"") | AB4: =K4 -> 47078.44
A5: 1089 | B5: 20255004 | C5: Jennifer Willoughby | D5: Roofing and Siding | E5: 45678.496 | F5: 15873.24 | G5: 45743 | H5: 45743 | I5: Mike | J5: 15873.24 | K5: 15873.24 | L5: =if(S5=TRUE,K5-F5,"") -> 0 | M5: 6866.21 | N5: =if(S5=TRUE,K5-M5,"") -> 9007.03 | O5: =IF($R5, IFERROR(IF((F5+L5)>0, (F5+L5-M5)/(F5+L5), ""), ""), "") -> 0.56743488 | P5: =IFERROR(__xludf.DUMMYFUNCTION("IF(AND($R5, NOT(REGEXMATCH(UPPER($C5), ""INS""))), IFERROR(IF((F5+L5)>0, (F5+L5-M5)/(F5+L5), """"), """"), """")"),0.5674348778195252) -> 0.56743488 | Q5: =IFERROR(__xludf.DUMMYFUNCTION("IF(AND($R5, REGEXMATCH(UPPER($C5), ""INS"")), IFERROR(IF((F5+L5)>0, (F5+L5-M5)/(F5+L5), """"), """"), """")"),"") | R5: TRUE | S5: TRUE | T5: FALSE | U5: In Billing | V5: TRUE | W5: =O5 -> 0.56743488 | X5: =J5 -> 15873.24 | Y5: =F5 -> 15873.24 | Z5: =L5 -> 0 | AA5: =IFERROR(__xludf.DUMMYFUNCTION("""COMPUTED_VALUE"""),"") | AB5: =K5 -> 15873.24
A6: 1073 | B6: 20255005 | C6: INS - Stephanie Quintor | D6: Roofing and Siding | E6: 45678.517 | F6: 26697.13 | G6: 11/06/2025 | H6: 11/06/2025 | I6: Chris | J6: 36000 | K6: 48613.67 | L6: =if(S6=TRUE,K6-F6,"") -> 21916.54 | M6: 18394.18 | N6: =if(S6=TRUE,K6-M6,"") -> 30219.49 | O6: =IF($R6, IFERROR(IF((F6+L6)>0, (F6+L6-M6)/(F6+L6), ""), ""), "") -> 0.62162536 | P6: =IFERROR(__xludf.DUMMYFUNCTION("IF(AND($R6, NOT(REGEXMATCH(UPPER($C6), ""INS""))), IFERROR(IF((F6+L6)>0, (F6+L6-M6)/(F6+L6), """"), """"), """")"),"") | Q6: =IFERROR(__xludf.DUMMYFUNCTION("IF(AND($R6, REGEXMATCH(UPPER($C6), ""INS"")), IFERROR(IF((F6+L6)>0, (F6+L6-M6)/(F6+L6), """"), """"), """")"),0.6216253576411738) -> 0.62162536 | R6: TRUE | S6: TRUE | T6: TRUE | U6: In Billing | V6: TRUE | W6: =O6 -> 0.62162536 | X6: =J6 -> 36000 | Y6: =F6 -> 26697.13 | Z6: =L6 -> 21916.54 | AA6: =IFERROR(__xludf.DUMMYFUNCTION("""COMPUTED_VALUE"""),"") | AB6: =K6 -> 48613.67 | AC6: 45993
A7: 1052 | B7: 20255006 | C7: Bill Bechtel | D7: Roofing and Siding | E7: 45684.602 | F7: 169424.05 | G7: 45904 | H7: 45904 | I7: Adam | J7: 124535.04 | K7: 179061.6 | L7: =if(S7=TRUE,K7-F7,"") -> 9637.55 | M7: 133092.79 | N7: =if(S7=TRUE,K7-M7,"") -> 45968.81 | O7: =IF($R7, IFERROR(IF((F7+L7)>0, (F7+L7-M7)/(F7+L7), ""), ""), "") -> 0.25672065 | P7: =IFERROR(__xludf.DUMMYFUNCTION("IF(AND($R7, NOT(REGEXMATCH(UPPER($C7), ""INS""))), IFERROR(IF((F7+L7)>0, (F7+L7-M7)/(F7+L7), """"), """"), """")"),0.2567206480898192) -> 0.25672065 | Q7: =IFERROR(__xludf.DUMMYFUNCTION("IF(AND($R7, REGEXMATCH(UPPER($C7), ""INS"")), IFERROR(IF((F7+L7)>0, (F7+L7-M7)/(F7+L7), """"), """"), """")"),"") | R7: TRUE | S7: TRUE | T7: TRUE | U7: In Billing | V7: FALSE | W7: =O7 -> 0.25672065 | X7: =J7 -> 124535.04 | Y7: =F7 -> 169424.05 | Z7: =L7 -> 9637.55 | AA7: =IFERROR(__xludf.DUMMYFUNCTION("""COMPUTED_VALUE"""),"") | AB7: =K7 -> 179061.6
A8: 1080 | B8: 20255007 | C8: Nathan Thomsen | D8: Roofing and Siding | E8: 45684.606 | F8: 792.31 | G8: 45714 | H8: 45714 | I8: Mike | J8: 792.31 | K8: 792.31 | L8: =if(S8=TRUE,K8-F8,"") -> 0 | M8: 313.48 | N8: =if(S8=TRUE,K8-M8,"") -> 478.83 | O8: =IF($R8, IFERROR(IF((F8+L8)>0, (F8+L8-M8)/(F8+L8), ""), ""), "") -> 0.60434678 | P8: =IFERROR(__xludf.DUMMYFUNCTION("IF(AND($R8, NOT(REGEXMATCH(UPPER($C8), ""INS""))), IFERROR(IF((F8+L8)>0, (F8+L8-M8)/(F8+L8), """"), """"), """")"),0.6043467834559705) -> 0.60434678 | Q8: =IFERROR(__xludf.DUMMYFUNCTION("IF(AND($R8, REGEXMATCH(UPPER($C8), ""INS"")), IFERROR(IF((F8+L8)>0, (F8+L8-M8)/(F8+L8), """"), """"), """")"),"") | R8: TRUE | S8: TRUE | T8: FALSE | U8: In Billing | V8: TRUE | W8: =O8 -> 0.60434678 | X8: =J8 -> 792.31 | Y8: =F8 -> 792.31 | Z8: =L8 -> 0 | AA8: =IFERROR(__xludf.DUMMYFUNCTION("""COMPUTED_VALUE"""),"") | AB8: =K8 -> 792.31
A9: 1077 | B9: 20255008 | C9: Kathy Cornell | D9: Roofing and Siding | E9: 45688.39 | F9: 1908 | G9: 45698 | H9: 45698 | I9: Mike | J9: 1908 | K9: 1908 | L9: =if(S9=TRUE,K9-F9,"") -> 0 | M9: 840 | N9: =if(S9=TRUE,K9-M9,"") -> 1068 | O9: =IF($R9, IFERROR(IF((F9+L9)>0, (F9+L9-M9)/(F9+L9), ""), ""), "") -> 0.55974843 | P9: =IFERROR(__xludf.DUMMYFUNCTION("IF(AND($R9, NOT(REGEXMATCH(UPPER($C9), ""INS""))), IFERROR(IF((F9+L9)>0, (F9+L9-M9)/(F9+L9), """"), """"), """")"),0.559748427672956) -> 0.55974843 | Q9: =IFERROR(__xludf.DUMMYFUNCTION("IF(AND($R9, REGEXMATCH(UPPER($C9), ""INS"")), IFERROR(IF((F9+L9)>0, (F9+L9-M9)/(F9+L9), """"), """"), """")"),"") | R9: TRUE | S9: TRUE | T9: FALSE | U9: In Billing | V9: TRUE | W9: =O9 -> 0.55974843 | X9: =J9 -> 1908 | Y9: =F9 -> 1908 | Z9: =L9 -> 0 | AA9: =IFERROR(__xludf.DUMMYFUNCTION("""COMPUTED_VALUE"""),"") | AB9: =K9 -> 1908
A10: 1095 | B10: 20255009 | C10: Loren Westfall | D10: Construction | E10: 45688.391 | F10: 43510.79 | G10: 45911 | H10: 45911 | I10: James | J10: 53510.79 | K10: 43510.79 | L10: =if(S10=TRUE,K10-F10,"") -> 0 | M10: 35097.53 | N10: =if(S10=TRUE,K10-M10,"") -> 8413.26 | O10: =IF($R10, IFERROR(IF((F10+L10)>0, (F10+L10-M10)/(F10+L10), ""), ""), "") -> 0.19336031 | P10: =IFERROR(__xludf.DUMMYFUNCTION("IF(AND($R10, NOT(REGEXMATCH(UPPER($C10), ""INS""))), IFERROR(IF((F10+L10)>0, (F10+L10-M10)/(F10+L10), """"), """"), """")"),0.19336031361416334) -> 0.19336031 | Q10: =IFERROR(__xludf.DUMMYFUNCTION("IF(AND($R10, REGEXMATCH(UPPER($C10), ""INS"")), IFERROR(IF((F10+L10)>0, (F10+L10-M10)/(F10+L10), """"), """"), """")"),"") | R10: TRUE | S10: TRUE | T10: TRUE | U10: In Billing | V10: TRUE | W10: =O10 -> 0.19336031 | X10: =J10 -> 53510.79 | Y10: =F10 -> 43510.79 | Z10: =L10 -> 0 | AA10: =IFERROR(__xludf.DUMMYFUNCTION("""COMPUTED_VALUE"""),"") | AB10: =K10 -> 43510.79
A11: 1105 | B11: 20255010 | C11: Deborah Tippie | D11: Roofing and Siding | E11: 45700.385 | F11: 14404.4 | G11: 45714 | H11: 45715 | I11: Drew | J11: 14304.4 | K11: 14304.4 | L11: =if(S11=TRUE,K11-F11,"") -> -100 | M11: 8375.22 | N11: =if(S11=TRUE,K11-M11,"") -> 5929.18 | O11: =IF($R11, IFERROR(IF((F11+L11)>0, (F11+L11-M11)/(F11+L11), ""), ""), "") -> 0.41450043 | P11: =IFERROR(__xludf.DUMMYFUNCTION("IF(AND($R11, NOT(REGEXMATCH(UPPER($C11), ""INS""))), IFERROR(IF((F11+L11)>0, (F11+L11-M11)/(F11+L11), """"), """"), """")"),0.4145004334330696) -> 0.41450043 | Q11: =IFERROR(__xludf.DUMMYFUNCTION("IF(AND($R11, REGEXMATCH(UPPER($C11), ""INS"")), IFERROR(IF((F11+L11)>0, (F11+L11-M11)/(F11+L11), """"), """"), """")"),"") | R11: TRUE | S11: TRUE | T11: FALSE | U11: In Billing | V11: TRUE | W11: =O11 -> 0.41450043 | X11: =J11 -> 14304.4 | Y11: =F11 -> 14404.4 | Z11: =L11 -> -100 | AA11: =IFERROR(__xludf.DUMMYFUNCTION("""COMPUTED_VALUE"""),"Drew") -> Drew | AB11: =K11 -> 14304.4
A12: 1138 | B12: 20255011 | C12: Eric Lovely | D12: Construction | E12: 45714.571 | F12: 200 | G12: 45713 | H12: 45713 | I12: Cale | J12: 200 | K12: 200 | L12: =if(S12=TRUE,K12-F12,"") -> 0 | M12: 0.01 | N12: =if(S12=TRUE,K12-M12,"") -> 199.99 | O12: =IF($R12, IFERROR(IF((F12+L12)>0, (F12+L12-M12)/(F12+L12), ""), ""), "") -> 0.99995 | P12: =IFERROR(__xludf.DUMMYFUNCTION("IF(AND($R12, NOT(REGEXMATCH(UPPER($C12), ""INS""))), IFERROR(IF((F12+L12)>0, (F12+L12-M12)/(F12+L12), """"), """"), """")"),0.99995) -> 0.99995 | Q12: =IFERROR(__xludf.DUMMYFUNCTION("IF(AND($R12, REGEXMATCH(UPPER($C12), ""INS"")), IFERROR(IF((F12+L12)>0, (F12+L12-M12)/(F12+L12), """"), """"), """")"),"") | R12: TRUE | S12: TRUE | T12: FALSE | U12: In Billing | V12: TRUE | W12: =O12 -> 0.99995 | X12: =J12 -> 200 | Y12: =F12 -> 200 | Z12: =L12 -> 0 | AA12: =IFERROR(__xludf.DUMMYFUNCTION("""COMPUTED_VALUE"""),"") | AB12: =K12 -> 200
A13: 1107 | B13: 20255012 | C13: Troy Blanchard | D13: Roofing and Siding | E13: 45714.69 | F13: 1791.57 | G13: 45726 | H13: 45726 | I13: Mike | J13: 1791.57 | K13: 1791.57 | L13: =if(S13=TRUE,K13-F13,"") -> 0 | M13: 570.71 | N13: =if(S13=TRUE,K13-M13,"") -> 1220.86 | O13: =IF($R13, IFERROR(IF((F13+L13)>0, (F13+L13-M13)/(F13+L13), ""), ""), "") -> 0.681447 | P13: =IFERROR(__xludf.DUMMYFUNCTION("IF(AND($R13, NOT(REGEXMATCH(UPPER($C13), ""INS""))), IFERROR(IF((F13+L13)>0, (F13+L13-M13)/(F13+L13), """"), """"), """")"),0.6814469990008762) -> 0.681447 | Q13: =IFERROR(__xludf.DUMMYFUNCTION("IF(AND($R13, REGEXMATCH(UPPER($C13), ""INS"")), IFERROR(IF((F13+L13)>0, (F13+L13-M13)/(F13+L13), """"), """"), """")"),"") | R13: TRUE | S13: TRUE | T13: FALSE | U13: In Billing | V13: TRUE | W13: =O13 -> 0.681447 | X13: =J13 -> 1791.57 | Y13: =F13 -> 1791.57 | Z13: =L13 -> 0 | AA13: =IFERROR(__xludf.DUMMYFUNCTION("""COMPUTED_VALUE"""),"") | AB13: =K13 -> 1791.57
A14: 1116 | B14: 20255013 | C14: Steve Truskowski | D14: Roofing and Siding | E14: 45715.478 | F14: 1750 | G14: 45728 | H14: 45728 | I14: Mike | J14: 1750 | K14: 1750 | L14: =if(S14=TRUE,K14-F14,"") -> 0 | M14: 875 | N14: =if(S14=TRUE,K14-M14,"") -> 875 | O14: =IF($R14, IFERROR(IF((F14+L14)>0, (F14+L14-M14)/(F14+L14), ""), ""), "") -> 0.5 | P14: =IFERROR(__xludf.DUMMYFUNCTION("IF(AND($R14, NOT(REGEXMATCH(UPPER($C14), ""INS""))), IFERROR(IF((F14+L14)>0, (F14+L14-M14)/(F14+L14), """"), """"), """")"),0.5) -> 0.5 | Q14: =IFERROR(__xludf.DUMMYFUNCTION("IF(AND($R14, REGEXMATCH(UPPER($C14), ""INS"")), IFERROR(IF((F14+L14)>0, (F14+L14-M14)/(F14+L14), """"), """"), """")"),"") | R14: TRUE | S14: TRUE | T14: FALSE | U14: In Billing | V14: TRUE | W14: =O14 -> 0.5 | X14: =J14 -> 1750 | Y14: =F14 -> 1750 | Z14: =L14 -> 0 | AA14: =IFERROR(__xludf.DUMMYFUNCTION("""COMPUTED_VALUE"""),"") | AB14: =K14 -> 1750
A15: 1136 | B15: 20255014 | C15: HBC Garage Siding | D15: Roofing and Siding | E15: 45715.479 | F15: 4388 | G15: 45720 | H15: 45720 | I15: James | J15: 4238 | K15: 4238 | L15: =if(S15=TRUE,K15-F15,"") -> -150 | M15: 2581.52 | N15: =if(S15=TRUE,K15-M15,"") -> 1656.48 | O15: =IF($R15, IFERROR(IF((F15+L15)>0, (F15+L15-M15)/(F15+L15), ""), ""), "") -> 0.39086361 | P15: =IFERROR(__xludf.DUMMYFUNCTION("IF(AND($R15, NOT(REGEXMATCH(UPPER($C15), ""INS""))), IFERROR(IF((F15+L15)>0, (F15+L15-M15)/(F15+L15), """"), """"), """")"),0.39086361491269467) -> 0.39086361 | Q15: =IFERROR(__xludf.DUMMYFUNCTION("IF(AND($R15, REGEXMATCH(UPPER($C15), ""INS"")), IFERROR(IF((F15+L15)>0, (F15+L15-M15)/(F15+L15), """"), """"), """")"),"") | R15: TRUE | S15: TRUE | T15: FALSE | U15: In Billing | V15: TRUE | W15: =O15 -> 0.39086361 | X15: =J15 -> 4238 | Y15: =F15 -> 4388 | Z15: =L15 -> -150 | AA15: =IFERROR(__xludf.DUMMYFUNCTION("""COMPUTED_VALUE"""),"") | AB15: =K15 -> 4238
A16: 1143 | B16: 20255015 | C16: INS - Rachel Carr | D16: Roofing and Siding | E16: 45715.626 | F16: 12984.79 | G16: 45726 | H16: 45726 | I16: James | J16: 16962.79 | K16: 16962.79 | L16: =if(S16=TRUE,K16-F16,"") -> 3978 | M16: 9424.33 | N16: =if(S16=TRUE,K16-M16,"") -> 7538.46 | O16: =IF($R16, IFERROR(IF((F16+L16)>0, (F16+L16-M16)/(F16+L16), ""), ""), "") -> 0.44441156 | P16: =IFERROR(__xludf.DUMMYFUNCTION("IF(AND($R16, NOT(REGEXMATCH(UPPER($C16), ""INS""))), IFERROR(IF((F16+L16)>0, (F16+L16-M16)/(F16+L16), """"), """"), """")"),"") | Q16: =IFERROR(__xludf.DUMMYFUNCTION("IF(AND($R16, REGEXMATCH(UPPER($C16), ""INS"")), IFERROR(IF((F16+L16)>0, (F16+L16-M16)/(F16+L16), """"), """"), """")"),0.4444115620130887) -> 0.44441156 | R16: TRUE | S16: TRUE | T16: FALSE | U16: In Billing | V16: TRUE | W16: =O16 -> 0.44441156 | X16: =J16 -> 16962.79 | Y16: =F16 -> 12984.79 | Z16: =L16 -> 3978 | AA16: =IFERROR(__xludf.DUMMYFUNCTION("""COMPUTED_VALUE"""),"") | AB16: =K16 -> 16962.79
A17: 1119 | B17: 20255016 | C17: INS - Joshua Bonzelaar | D17: Roofing and Siding | E17: 45719.403 | F17: 20546.52 | G17: 10/09/2025 | H17: 10/09/2025 | I17: Mike | J17: 24640.83 | K17: 25747.27 | L17: =if(S17=TRUE,K17-F17,"") -> 5200.75 | M17: 11388.53 | N17: =if(S17=TRUE,K17-M17,"") -> 14358.74 | O17: =IF($R17, IFERROR(IF((F17+L17)>0, (F17+L17-M17)/(F17+L17), ""), ""), "") -> 0.5576801 | P17: =IFERROR(__xludf.DUMMYFUNCTION("IF(AND($R17, NOT(REGEXMATCH(UPPER($C17), ""INS""))), IFERROR(IF((F17+L17)>0, (F17+L17-M17)/(F17+L17), """"), """"), """")"),"") | Q17: =IFERROR(__xludf.DUMMYFUNCTION("IF(AND($R17, REGEXMATCH(UPPER($C17), ""INS"")), IFERROR(IF((F17+L17)>0, (F17+L17-M17)/(F17+L17), """"), """"), """")"),0.5576800957926802) -> 0.5576801 | R17: TRUE | S17: TRUE | T17: TRUE | U17: In Billing | V17: TRUE | W17: =O17 -> 0.5576801 | X17: =J17 -> 24640.83 | Y17: =F17 -> 20546.52 | Z17: =L17 -> 5200.75 | AA17: =IFERROR(__xludf.DUMMYFUNCTION("""COMPUTED_VALUE"""),"") | AB17: =K17 -> 25747.27
A18: 1173 | B18: 20255017 | C18: Gina Schweiterman | D18: Roofing and Siding | E18: 45727 | F18: 1039.98 | G18: 45743 | H18: 45743 | I18: Will | J18: 1039.98 | K18: 1039.98 | L18: =if(S18=TRUE,K18-F18,"") -> 0 | M18: 333.83 | N18: =if(S18=TRUE,K18-M18,"") -> 706.15 | O18: =IF($R18, IFERROR(IF((F18+L18)>0, (F18+L18-M18)/(F18+L18), ""), ""), "") -> 0.67900344 | P18: =IFERROR(__xludf.DUMMYFUNCTION("IF(AND($R18, NOT(REGEXMATCH(UPPER($C18), ""INS""))), IFERROR(IF((F18+L18)>0, (F18+L18-M18)/(F18+L18), """"), """"), """")"),0.6790034423738919) -> 0.67900344 | Q18: =IFERROR(__xludf.DUMMYFUNCTION("IF(AND($R18, REGEXMATCH(UPPER($C18), ""INS"")), IFERROR(IF((F18+L18)>0, (F18+L18-M18)/(F18+L18), """"), """"), """")"),"") | R18: TRUE | S18: TRUE | T18: FALSE | U18: In Billing | V18: TRUE | W18: =O18 -> 0.67900344 | X18: =J18 -> 1039.98 | Y18: =F18 -> 1039.98 | Z18: =L18 -> 0 | AA18: =IFERROR(__xludf.DUMMYFUNCTION("""COMPUTED_VALUE"""),"") | AB18: =K18 -> 1039.98
A19: 1170 | B19: 20255018 | C19: INS - Ryan Horan | D19: Roofing and Siding | E19: 45727 | F19: 48190.26 | G19: 45764 | H19: 45764 | I19: James | J19: 34830.67 | K19: 34830.67 | L19: =if(S19=TRUE,K19-F19,"") -> -13359.59 | M19: 14724.54 | N19: =if(S19=TRUE,K19-M19,"") -> 20106.13 | O19: =IF($R19, IFERROR(IF((F19+L19)>0, (F19+L19-M19)/(F19+L19), ""), ""), "") -> 0.57725361 | P19: =IFERROR(__xludf.DUMMYFUNCTION("IF(AND($R19, NOT(REGEXMATCH(UPPER($C19), ""INS""))), IFERROR(IF((F19+L19)>0, (F19+L19-M19)/(F19+L19), """"), """"), """")"),"") | Q19: =IFERROR(__xludf.DUMMYFUNCTION("IF(AND($R19, REGEXMATCH(UPPER($C19), ""INS"")), IFERROR(IF((F19+L19)>0, (F19+L19-M19)/(F19+L19), """"), """"), """")"),0.5772536101085624) -> 0.57725361 | R19: TRUE | S19: TRUE | T19: TRUE | U19: In Billing | V19: TRUE | W19: =O19 -> 0.57725361 | X19: =J19 -> 34830.67 | Y19: =F19 -> 48190.26 | Z19: =L19 -> -13359.59 | AA19: =IFERROR(__xludf.DUMMYFUNCTION("""COMPUTED_VALUE"""),"") | AB19: =K19 -> 34830.67
A20: 1154 | B20: 20255019 | C20: Andrew & Lynn Evans | D20: Roofing and Siding | E20: 45728 | F20: 16673.22 | G20: 45750 | H20: 45750 | I20: Brett | J20: 18598.22 | K20: 18598.22 | L20: =if(S20=TRUE,K20-F20,"") -> 1925 | M20: 10397.62 | N20: =if(S20=TRUE,K20-M20,"") -> 8200.6 | O20: =IF($R20, IFERROR(IF((F20+L20)>0, (F20+L20-M20)/(F20+L20), ""), ""), "") -> 0.44093467 | P20: =IFERROR(__xludf.DUMMYFUNCTION("IF(AND($R20, NOT(REGEXMATCH(UPPER($C20), ""INS""))), IFERROR(IF((F20+L20)>0, (F20+L20-M20)/(F20+L20), """"), """"), """")"),0.4409346700920841) -> 0.44093467 | Q20: =IFERROR(__xludf.DUMMYFUNCTION("IF(AND($R20, REGEXMATCH(UPPER($C20), ""INS"")), IFERROR(IF((F20+L20)>0, (F20+L20-M20)/(F20+L20), """"), """"), """")"),"") | R20: TRUE | S20: TRUE | T20: FALSE | U20: In Billing | V20: TRUE | W20: =O20 -> 0.44093467 | X20: =J20 -> 18598.22 | Y20: =F20 -> 16673.22 | Z20: =L20 -> 1925 | AA20: =IFERROR(__xludf.DUMMYFUNCTION("""COMPUTED_VALUE"""),"") | AB20: =K20 -> 18598.22
A21: 1127 | B21: 20255020 | C21: Lorraine Wood | D21: Roofing and Siding | E21: 45728 | F21: 18577.11 | G21: 45733 | H21: 45733 | I21: Brett | J21: 21712.11 | K21: 21712.11 | L21: =if(S21=TRUE,K21-F21,"") -> 3135 | M21: 11703.43 | N21: =if(S21=TRUE,K21-M21,"") -> 10008.68 | O21: =IF($R21, IFERROR(IF((F21+L21)>0, (F21+L21-M21)/(F21+L21), ""), ""), "") -> 0.46097224 | P21: =IFERROR(__xludf.DUMMYFUNCTION("IF(AND($R21, NOT(REGEXMATCH(UPPER($C21), ""INS""))), IFERROR(IF((F21+L21)>0, (F21+L21-M21)/(F21+L21), """"), """"), """")"),0.460972240837026) -> 0.46097224 | Q21: =IFERROR(__xludf.DUMMYFUNCTION("IF(AND($R21, REGEXMATCH(UPPER($C21), ""INS"")), IFERROR(IF((F21+L21)>0, (F21+L21-M21)/(F21+L21), """"), """"), """")"),"") | R21: TRUE | S21: TRUE | T21: FALSE | U21: In Billing | V21: TRUE | W21: =O21 -> 0.46097224 | X21: =J21 -> 21712.11 | Y21: =F21 -> 18577.11 | Z21: =L21 -> 3135 | AA21: =IFERROR(__xludf.DUMMYFUNCTION("""COMPUTED_VALUE"""),"") | AB21: =K21 -> 21712.11
A22: 1139 | B22: 20255021 | C22: Tom Watkin | D22: Construction | E22: 45728 | F22: 1714.29 | G22: 45764 | H22: 45764 | I22: Drew | J22: 1714.29 | K22: 1714.29 | L22: =if(S22=TRUE,K22-F22,"") -> 0 | M22: 1358.87 | N22: =if(S22=TRUE,K22-M22,"") -> 355.42 | O22: =IF($R22, IFERROR(IF((F22+L22)>0, (F22+L22-M22)/(F22+L22), ""), ""), "") -> 0.20732781 | P22: =IFERROR(__xludf.DUMMYFUNCTION("IF(AND($R22, NOT(REGEXMATCH(UPPER($C22), ""INS""))), IFERROR(IF((F22+L22)>0, (F22+L22-M22)/(F22+L22), """"), """"), """")"),0.20732781501379585) -> 0.20732781 | Q22: =IFERROR(__xludf.DUMMYFUNCTION("IF(AND($R22, REGEXMATCH(UPPER($C22), ""INS"")), IFERROR(IF((F22+L22)>0, (F22+L22-M22)/(F22+L22), """"), """"), """")"),"") | R22: TRUE | S22: TRUE | T22: FALSE | U22: In Billing | V22: TRUE | W22: =O22 -> 0.20732781 | X22: =J22 -> 1714.29 | Y22: =F22 -> 1714.29 | Z22: =L22 -> 0 | AA22: =IFERROR(__xludf.DUMMYFUNCTION("""COMPUTED_VALUE"""),"Drew") -> Drew | AB22: =K22 -> 1714.29
A23: 1179 | B23: 20255022 | C23: Janice Motz | D23: Roofing and Siding | E23: 45728 | F23: 12309.45 | G23: 45765 | H23: 45765 | I23: James | J23: 12909.45 | K23: 12909.45 | L23: =if(S23=TRUE,K23-F23,"") -> 600 | M23: 5640.54 | N23: =if(S23=TRUE,K23-M23,"") -> 7268.91 | O23: =IF($R23, IFERROR(IF((F23+L23)>0, (F23+L23-M23)/(F23+L23), ""), ""), "") -> 0.56306891 | P23: =IFERROR(__xludf.DUMMYFUNCTION("IF(AND($R23, NOT(REGEXMATCH(UPPER($C23), ""INS""))), IFERROR(IF((F23+L23)>0, (F23+L23-M23)/(F23+L23), """"), """"), """")"),0.5630689146323042) -> 0.56306891 | Q23: =IFERROR(__xludf.DUMMYFUNCTION("IF(AND($R23, REGEXMATCH(UPPER($C23), ""INS"")), IFERROR(IF((F23+L23)>0, (F23+L23-M23)/(F23+L23), """"), """"), """")"),"") | R23: TRUE | S23: TRUE | T23: FALSE | U23: In Billing | V23: TRUE | W23: =O23 -> 0.56306891 | X23: =J23 -> 12909.45 | Y23: =F23 -> 12309.45 | Z23: =L23 -> 600 | AA23: =IFERROR(__xludf.DUMMYFUNCTION("""COMPUTED_VALUE"""),"") | AB23: =K23 -> 12909.45
A24: 1159 | B24: 20255023 | C24: Cory Leckey | D24: Roofing and Siding | E24: 45728 | F24: 10824.89 | G24: 45743 | H24: 45743 | I24: Drew | J24: 11374.89 | K24: 11374.89 | L24: =if(S24=TRUE,K24-F24,"") -> 550 | M24: 6819.98 | N24: =if(S24=TRUE,K24-M24,"") -> 4554.91 | O24: =IF($R24, IFERROR(IF((F24+L24)>0, (F24+L24-M24)/(F24+L24), ""), ""), "") -> 0.40043552 | P24: =IFERROR(__xludf.DUMMYFUNCTION("IF(AND($R24, NOT(REGEXMATCH(UPPER($C24), ""INS""))), IFERROR(IF((F24+L24)>0, (F24+L24-M24)/(F24+L24), """"), """"), """")"),0.4004355206951452) -> 0.40043552 | Q24: =IFERROR(__xludf.DUMMYFUNCTION("IF(AND($R24, REGEXMATCH(UPPER($C24), ""INS"")), IFERROR(IF((F24+L24)>0, (F24+L24-M24)/(F24+L24), """"), """"), """")"),"") | R24: TRUE | S24: TRUE | T24: FALSE | U24: In Billing | V24: TRUE | W24: =O24 -> 0.40043552 | X24: =J24 -> 11374.89 | Y24: =F24 -> 10824.89 | Z24: =L24 -> 550 | AA24: =IFERROR(__xludf.DUMMYFUNCTION("""COMPUTED_VALUE"""),"Drew") -> Drew | AB24: =K24 -> 11374.89
A25: 1150 | B25: 20255024 | C25: Kimberleigh Cooper | D25: Roofing and Siding | E25: 45729 | F25: 2334.25 | G25: 45736 | H25: 45736 | I25: James | J25: 2334.25 | K25: 2334.25 | L25: =if(S25=TRUE,K25-F25,"") -> 0 | M25: 779.57 | N25: =if(S25=TRUE,K25-M25,"") -> 1554.68 | O25: =IF($R25, IFERROR(IF((F25+L25)>0, (F25+L25-M25)/(F25+L25), ""), ""), "") -> 0.66602977 | P25: =IFERROR(__xludf.DUMMYFUNCTION("IF(AND($R25, NOT(REGEXMATCH(UPPER($C25), ""INS""))), IFERROR(IF((F25+L25)>0, (F25+L25-M25)/(F25+L25), """"), """"), """")"),0.6660297740173503) -> 0.66602977 | Q25: =IFERROR(__xludf.DUMMYFUNCTION("IF(AND($R25, REGEXMATCH(UPPER($C25), ""INS"")), IFERROR(IF((F25+L25)>0, (F25+L25-M25)/(F25+L25), """"), """"), """")"),"") | R25: TRUE | S25: TRUE | T25: FALSE | U25: In Billing | V25: TRUE | W25: =O25 -> 0.66602977 | X25: =J25 -> 2334.25 | Y25: =F25 -> 2334.25 | Z25: =L25 -> 0 | AA25: =IFERROR(__xludf.DUMMYFUNCTION("""COMPUTED_VALUE"""),"") | AB25: =K25 -> 2334.25
A26: 1158 | B26: 20255025 | C26: Chris Falkowski | D26: Roofing and Siding | E26: 45729 | F26: 12289.16 | G26: 45883 | H26: 45883 | I26: James | J26: 13673.75 | K26: 13673.75 | L26: =if(S26=TRUE,K26-F26,"") -> 1384.59 | M26: 6580.49 | N26: =if(S26=TRUE,K26-M26,"") -> 7093.26 | O26: =IF($R26, IFERROR(IF((F26+L26)>0, (F26+L26-M26)/(F26+L26), ""), ""), "") -> 0.51875016 | P26: =IFERROR(__xludf.DUMMYFUNCTION("IF(AND($R26, NOT(REGEXMATCH(UPPER($C26), ""INS""))), IFERROR(IF((F26+L26)>0, (F26+L26-M26)/(F26+L26), """"), """"), """")"),0.5187501599780602) -> 0.51875016 | Q26: =IFERROR(__xludf.DUMMYFUNCTION("IF(AND($R26, REGEXMATCH(UPPER($C26), ""INS"")), IFERROR(IF((F26+L26)>0, (F26+L26-M26)/(F26+L26), """"), """"), """")"),"") | R26: TRUE | S26: TRUE | T26: FALSE | U26: In Billing | V26: TRUE | W26: =O26 -> 0.51875016 | X26: =J26 -> 13673.75 | Y26: =F26 -> 12289.16 | Z26: =L26 -> 1384.59 | AA26: =IFERROR(__xludf.DUMMYFUNCTION("""COMPUTED_VALUE"""),"") | AB26: =K26 -> 13673.75
A27: 1045 | B27: 20255026 | C27: Steve and Robin Bliss | D27: Roofing and Siding | E27: 45730 | F27: 1218.25 | G27: 45757 | H27: 45757 | I27: Brett | J27: 1218.25 | K27: 1218.25 | L27: =if(S27=TRUE,K27-F27,"") -> 0 | M27: 469.65 | N27: =if(S27=TRUE,K27-M27,"") -> 748.6 | O27: =IF($R27, IFERROR(IF((F27+L27)>0, (F27+L27-M27)/(F27+L27), ""), ""), "") -> 0.614488 | P27: =IFERROR(__xludf.DUMMYFUNCTION("IF(AND($R27, NOT(REGEXMATCH(UPPER($C27), ""INS""))), IFERROR(IF((F27+L27)>0, (F27+L27-M27)/(F27+L27), """"), """"), """")"),0.6144879950749026) -> 0.614488 | Q27: =IFERROR(__xludf.DUMMYFUNCTION("IF(AND($R27, REGEXMATCH(UPPER($C27), ""INS"")), IFERROR(IF((F27+L27)>0, (F27+L27-M27)/(F27+L27), """"), """"), """")"),"") | R27: TRUE | S27: TRUE | T27: FALSE | U27: In Billing | V27: TRUE | W27: =O27 -> 0.614488 | X27: =J27 -> 1218.25 | Y27: =F27 -> 1218.25 | Z27: =L27 -> 0 | AA27: =IFERROR(__xludf.DUMMYFUNCTION("""COMPUTED_VALUE"""),"") | AB27: =K27 -> 1218.25
A28: 1166 | B28: 20255027 | C28: INS - Tyler Goudy | D28: Roofing and Siding | E28: 45730 | F28: 27690.88 | G28: 09/25/2025 | H28: 09/25/2025 | I28: James | J28: 27965.88 | K28: 27965.88 | L28: =if(S28=TRUE,K28-F28,"") -> 275 | M28: 16743.67 | N28: =if(S28=TRUE,K28-M28,"") -> 11222.21 | O28: =IF($R28, IFERROR(IF((F28+L28)>0, (F28+L28-M28)/(F28+L28), ""), ""), "") -> 0.40128221 | P28: =IFERROR(__xludf.DUMMYFUNCTION("IF(AND($R28, NOT(REGEXMATCH(UPPER($C28), ""INS""))), IFERROR(IF((F28+L28)>0, (F28+L28-M28)/(F28+L28), """"), """"), """")"),"") | Q28: =IFERROR(__xludf.DUMMYFUNCTION("IF(AND($R28, REGEXMATCH(UPPER($C28), ""INS"")), IFERROR(IF((F28+L28)>0, (F28+L28-M28)/(F28+L28), """"), """"), """")"),0.40128220531590647) -> 0.40128221 | R28: TRUE | S28: TRUE | T28: TRUE | U28: In Billing | V28: TRUE | W28: =O28 -> 0.40128221 | X28: =J28 -> 27965.88 | Y28: =F28 -> 27690.88 | Z28: =L28 -> 275 | AA28: =IFERROR(__xludf.DUMMYFUNCTION("""COMPUTED_VALUE"""),"") | AB28: =K28 -> 27965.88
A29: 1114 | B29: 20255028 | C29: INS - Wes Beard | D29: Roofing and Siding | E29: 45731 | F29: 31456.65 | G29: 45806 | H29: 45806 | I29: Brett | J29: 36892.07 | K29: 36892.07 | L29: =if(S29=TRUE,K29-F29,"") -> 5435.42 | M29: 17372.87 | N29: =if(S29=TRUE,K29-M29,"") -> 19519.2 | O29: =IF($R29, IFERROR(IF((F29+L29)>0, (F29+L29-M29)/(F29+L29), ""), ""), "") -> 0.52908931 | P29: =IFERROR(__xludf.DUMMYFUNCTION("IF(AND($R29, NOT(REGEXMATCH(UPPER($C29), ""INS""))), IFERROR(IF((F29+L29)>0, (F29+L29-M29)/(F29+L29), """"), """"), """")"),"") | Q29: =IFERROR(__xludf.DUMMYFUNCTION("IF(AND($R29, REGEXMATCH(UPPER($C29), ""INS"")), IFERROR(IF((F29+L29)>0, (F29+L29-M29)/(F29+L29), """"), """"), """")"),0.5290893137739358) -> 0.52908931 | R29: TRUE | S29: TRUE | T29: FALSE | U29: In Billing | V29: TRUE | W29: =O29 -> 0.52908931 | X29: =J29 -> 36892.07 | Y29: =F29 -> 31456.65 | Z29: =L29 -> 5435.42 | AA29: =IFERROR(__xludf.DUMMYFUNCTION("""COMPUTED_VALUE"""),"") | AB29: =K29 -> 36892.07
A30: 1195 | B30: 20255029 | C30: Andrew Walter | D30: Roofing and Siding | E30: 45732 | F30: 1138.3 | G30: 45792 | H30: 45792 | I30: Drew | J30: 1138.3 | K30: 1138.3 | L30: =if(S30=TRUE,K30-F30,"") -> 0 | M30: 1006.07 | N30: =if(S30=TRUE,K30-M30,"") -> 132.23 | O30: =IF($R30, IFERROR(IF((F30+L30)>0, (F30+L30-M30)/(F30+L30), ""), ""), "") -> 0.11616446 | P30: =IFERROR(__xludf.DUMMYFUNCTION("IF(AND($R30, NOT(REGEXMATCH(UPPER($C30), ""INS""))), IFERROR(IF((F30+L30)>0, (F30+L30-M30)/(F30+L30), """"), """"), """")"),0.11616445576737232) -> 0.11616446 | Q30: =IFERROR(__xludf.DUMMYFUNCTION("IF(AND($R30, REGEXMATCH(UPPER($C30), ""INS"")), IFERROR(IF((F30+L30)>0, (F30+L30-M30)/(F30+L30), """"), """"), """")"),"") | R30: TRUE | S30: TRUE | T30: FALSE | U30: In Billing | V30: TRUE | W30: =O30 -> 0.11616446 | X30: =J30 -> 1138.3 | Y30: =F30 -> 1138.3 | Z30: =L30 -> 0 | AA30: =IFERROR(__xludf.DUMMYFUNCTION("""COMPUTED_VALUE"""),"Drew") -> Drew | AB30: =K30 -> 1138.3
A31: 1210 | B31: 20255030 | C31: Michael Hill | D31: Roofing and Siding | E31: 45736 | F31: 2169.35 | G31: 45785 | H31: 45785 | I31: Drew | J31: 2169.35 | K31: 2169.35 | L31: =if(S31=TRUE,K31-F31,"") -> 0 | M31: 975 | N31: =if(S31=TRUE,K31-M31,"") -> 1194.35 | O31: =IF($R31, IFERROR(IF((F31+L31)>0, (F31+L31-M31)/(F31+L31), ""), ""), "") -> 0.55055662 | P31: =IFERROR(__xludf.DUMMYFUNCTION("IF(AND($R31, NOT(REGEXMATCH(UPPER($C31), ""INS""))), IFERROR(IF((F31+L31)>0, (F31+L31-M31)/(F31+L31), """"), """"), """")"),0.5505566183418996) -> 0.55055662 | Q31: =IFERROR(__xludf.DUMMYFUNCTION("IF(AND($R31, REGEXMATCH(UPPER($C31), ""INS"")), IFERROR(IF((F31+L31)>0, (F31+L31-M31)/(F31+L31), """"), """"), """")"),"") | R31: TRUE | S31: TRUE | T31: FALSE | U31: In Billing | V31: TRUE | W31: =O31 -> 0.55055662 | X31: =J31 -> 2169.35 | Y31: =F31 -> 2169.35 | Z31: =L31 -> 0 | AA31: =IFERROR(__xludf.DUMMYFUNCTION("""COMPUTED_VALUE"""),"Drew") -> Drew | AB31: =K31 -> 2169.35
A32: 1218 | B32: 20255031 | C32: Darren Smith | D32: Roofing and Siding | E32: 45737 | F32: 582.69 | G32: 45750 | H32: 45750 | I32: James | J32: 582.69 | K32: 582.69 | L32: =if(S32=TRUE,K32-F32,"") -> 0 | M32: 357.59 | N32: =if(S32=TRUE,K32-M32,"") -> 225.1 | O32: =IF($R32, IFERROR(IF((F32+L32)>0, (F32+L32-M32)/(F32+L32), ""), ""), "") -> 0.38631176 | P32: =IFERROR(__xludf.DUMMYFUNCTION("IF(AND($R32, NOT(REGEXMATCH(UPPER($C32), ""INS""))), IFERROR(IF((F32+L32)>0, (F32+L32-M32)/(F32+L32), """"), """"), """")"),0.3863117609706706) -> 0.38631176 | Q32: =IFERROR(__xludf.DUMMYFUNCTION("IF(AND($R32, REGEXMATCH(UPPER($C32), ""INS"")), IFERROR(IF((F32+L32)>0, (F32+L32-M32)/(F32+L32), """"), """"), """")"),"") | R32: TRUE | S32: TRUE | T32: FALSE | U32: In Billing | V32: TRUE | W32: =O32 -> 0.38631176 | X32: =J32 -> 582.69 | Y32: =F32 -> 582.69 | Z32: =L32 -> 0 | AA32: =IFERROR(__xludf.DUMMYFUNCTION("""COMPUTED_VALUE"""),"") | AB32: =K32 -> 582.69
A33: 1094 | B33: 20255032 | C33: INS - Claude Copeland | D33: Roofing and Siding | E33: 45737 | F33: 11551.45 | G33: 45792 | H33: 45792 | I33: James | J33: 20633.62 | K33: 20633.62 | L33: =if(S33=TRUE,K33-F33,"") -> 9082.17 | M33: 9718.69 | N33: =if(S33=TRUE,K33-M33,"") -> 10914.93 | O33: =IF($R33, IFERROR(IF((F33+L33)>0, (F33+L33-M33)/(F33+L33), ""), ""), "") -> 0.52898764 | P33: =IFERROR(__xludf.DUMMYFUNCTION("IF(AND($R33, NOT(REGEXMATCH(UPPER($C33), ""INS""))), IFERROR(IF((F33+L33)>0, (F33+L33-M33)/(F33+L33), """"), """"), """")"),"") | Q33: =IFERROR(__xludf.DUMMYFUNCTION("IF(AND($R33, REGEXMATCH(UPPER($C33), ""INS"")), IFERROR(IF((F33+L33)>0, (F33+L33-M33)/(F33+L33), """"), """"), """")"),0.5289876424980202) -> 0.52898764 | R33: TRUE | S33: TRUE | T33: FALSE | U33: In Billing | V33: TRUE | W33: =O33 -> 0.52898764 | X33: =J33 -> 20633.62 | Y33: =F33 -> 11551.45 | Z33: =L33 -> 9082.17 | AA33: =IFERROR(__xludf.DUMMYFUNCTION("""COMPUTED_VALUE"""),"") | AB33: =K33 -> 20633.62
A34: 1227 | B34: 20255033 | C34: Jim Steinman | D34: Roofing and Siding | E34: 45741 | F34: 1298 | G34: 45764 | H34: 45764 | I34: James | J34: 1298 | K34: 1298 | L34: =if(S34=TRUE,K34-F34,"") -> 0 | M34: 820.25 | N34: =if(S34=TRUE,K34-M34,"") -> 477.75 | O34: =IF($R34, IFERROR(IF((F34+L34)>0, (F34+L34-M34)/(F34+L34), ""), ""), "") -> 0.36806626 | P34: =IFERROR(__xludf.DUMMYFUNCTION("IF(AND($R34, NOT(REGEXMATCH(UPPER($C34), ""INS""))), IFERROR(IF((F34+L34)>0, (F34+L34-M34)/(F34+L34), """"), """"), """")"),0.3680662557781202) -> 0.36806626 | Q34: =IFERROR(__xludf.DUMMYFUNCTION("IF(AND($R34, REGEXMATCH(UPPER($C34), ""INS"")), IFERROR(IF((F34+L34)>0, (F34+L34-M34)/(F34+L34), """"), """"), """")"),"") | R34: TRUE | S34: TRUE | T34: FALSE | U34: In Billing | V34: TRUE | W34: =O34 -> 0.36806626 | X34: =J34 -> 1298 | Y34: =F34 -> 1298 | Z34: =L34 -> 0 | AA34: =IFERROR(__xludf.DUMMYFUNCTION("""COMPUTED_VALUE"""),"") | AB34: =K34 -> 1298
A35: 1244 | B35: 20255034 | C35: Dalton Swafford | D35: Roofing and Siding | E35: 45741 | F35: 459.89 | G35: 45764 | H35: 45764 | I35: James | J35: 460 | K35: 460 | L35: =if(S35=TRUE,K35-F35,"") -> 0.11 | M35: 200 | N35: =if(S35=TRUE,K35-M35,"") -> 260 | O35: =IF($R35, IFERROR(IF((F35+L35)>0, (F35+L35-M35)/(F35+L35), ""), ""), "") -> 0.56521739 | P35: =IFERROR(__xludf.DUMMYFUNCTION("IF(AND($R35, NOT(REGEXMATCH(UPPER($C35), ""INS""))), IFERROR(IF((F35+L35)>0, (F35+L35-M35)/(F35+L35), """"), """"), """")"),0.5652173913043478) -> 0.56521739 | Q35: =IFERROR(__xludf.DUMMYFUNCTION("IF(AND($R35, REGEXMATCH(UPPER($C35), ""INS"")), IFERROR(IF((F35+L35)>0, (F35+L35-M35)/(F35+L35), """"), """"), """")"),"") | R35: TRUE | S35: TRUE | T35: FALSE | U35: In Billing | V35: TRUE | W35: =O35 -> 0.56521739 | X35: =J35 -> 460 | Y35: =F35 -> 459.89 | Z35: =L35 -> 0.11 | AA35: =IFERROR(__xludf.DUMMYFUNCTION("""COMPUTED_VALUE"""),"") | AB35: =K35 -> 460
A36: 1246 | B36: 20255035 | C36: Dave Nelson | D36: Roofing and Siding | E36: 45742 | F36: 2544 | G36: 45762 | H36: 45762 | I36: Adam | J36: 2544 | K36: 2544 | L36: =if(S36=TRUE,K36-F36,"") -> 0 | M36: 1300 | N36: =if(S36=TRUE,K36-M36,"") -> 1244 | O36: =IF($R36, IFERROR(IF((F36+L36)>0, (F36+L36-M36)/(F36+L36), ""), ""), "") -> 0.48899371 | P36: =IFERROR(__xludf.DUMMYFUNCTION("IF(AND($R36, NOT(REGEXMATCH(UPPER($C36), ""INS""))), IFERROR(IF((F36+L36)>0, (F36+L36-M36)/(F36+L36), """"), """"), """")"),0.4889937106918239) -> 0.48899371 | Q36: =IFERROR(__xludf.DUMMYFUNCTION("IF(AND($R36, REGEXMATCH(UPPER($C36), ""INS"")), IFERROR(IF((F36+L36)>0, (F36+L36-M36)/(F36+L36), """"), """"), """")"),"") | R36: TRUE | S36: TRUE | T36: FALSE | U36: In Billing | V36: TRUE | W36: =O36 -> 0.48899371 | X36: =J36 -> 2544 | Y36: =F36 -> 2544 | Z36: =L36 -> 0 | AA36: =IFERROR(__xludf.DUMMYFUNCTION("""COMPUTED_VALUE"""),"") | AB36: =K36 -> 2544
A37: 1245 | B37: 20255036 | C37: Dave Nelson | D37: Roofing and Siding | E37: 45742 | F37: 1640 | G37: 45771 | H37: 45771 | I37: Adam | J37: 1640 | K37: 1640 | L37: =if(S37=TRUE,K37-F37,"") -> 0 | M37: 825 | N37: =if(S37=TRUE,K37-M37,"") -> 815 | O37: =IF($R37, IFERROR(IF((F37+L37)>0, (F37+L37-M37)/(F37+L37), ""), ""), "") -> 0.49695122 | P37: =IFERROR(__xludf.DUMMYFUNCTION("IF(AND($R37, NOT(REGEXMATCH(UPPER($C37), ""INS""))), IFERROR(IF((F37+L37)>0, (F37+L37-M37)/(F37+L37), """"), """"), """")"),0.4969512195121951) -> 0.49695122 | Q37: =IFERROR(__xludf.DUMMYFUNCTION("IF(AND($R37, REGEXMATCH(UPPER($C37), ""INS"")), IFERROR(IF((F37+L37)>0, (F37+L37-M37)/(F37+L37), """"), """"), """")"),"") | R37: TRUE | S37: TRUE | T37: FALSE | U37: In Billing | V37: TRUE | W37: =O37 -> 0.49695122 | X37: =J37 -> 1640 | Y37: =F37 -> 1640 | Z37: =L37 -> 0 | AA37: =IFERROR(__xludf.DUMMYFUNCTION("""COMPUTED_VALUE"""),"") | AB37: =K37 -> 1640
A38: 1231 | B38: 20255037 | C38: Steve Oroszi | D38: Roofing and Siding | E38: 45744 | F38: 3788.19 | G38: 45792 | H38: 45792 | I38: James | J38: 3938.19 | K38: 3938.19 | L38: =if(S38=TRUE,K38-F38,"") -> 150 | M38: 2615.04 | N38: =if(S38=TRUE,K38-M38,"") -> 1323.15 | O38: =IF($R38, IFERROR(IF((F38+L38)>0, (F38+L38-M38)/(F38+L38), ""), ""), "") -> 0.33597922 | P38: =IFERROR(__xludf.DUMMYFUNCTION("IF(AND($R38, NOT(REGEXMATCH(UPPER($C38), ""INS""))), IFERROR(IF((F38+L38)>0, (F38+L38-M38)/(F38+L38), """"), """"), """")"),0.3359792188797392) -> 0.33597922 | Q38: =IFERROR(__xludf.DUMMYFUNCTION("IF(AND($R38, REGEXMATCH(UPPER($C38), ""INS"")), IFERROR(IF((F38+L38)>0, (F38+L38-M38)/(F38+L38), """"), """"), """")"),"") | R38: TRUE | S38: TRUE | T38: FALSE | U38: In Billing | V38: TRUE | W38: =O38 -> 0.33597922 | X38: =J38 -> 3938.19 | Y38: =F38 -> 3788.19 | Z38: =L38 -> 150 | AA38: =IFERROR(__xludf.DUMMYFUNCTION("""COMPUTED_VALUE"""),"") | AB38: =K38 -> 3938.19
A39: 1219 | B39: 20255038 | C39: Brandon Mix | D39: Roofing and Siding | E39: 45744 | F39: 4998.1 | G39: 45764 | H39: 45764 | I39: Drew | J39: 4998.1 | K39: 4998.1 | L39: =if(S39=TRUE,K39-F39,"") -> 0 | M39: 2525.85 | N39: =if(S39=TRUE,K39-M39,"") -> 2472.25 | O39: =IF($R39, IFERROR(IF((F39+L39)>0, (F39+L39-M39)/(F39+L39), ""), ""), "") -> 0.49463796 | P39: =IFERROR(__xludf.DUMMYFUNCTION("IF(AND($R39, NOT(REGEXMATCH(UPPER($C39), ""INS""))), IFERROR(IF((F39+L39)>0, (F39+L39-M39)/(F39+L39), """"), """"), """")"),0.49463796242572183) -> 0.49463796 | Q39: =IFERROR(__xludf.DUMMYFUNCTION("IF(AND($R39, REGEXMATCH(UPPER($C39), ""INS"")), IFERROR(IF((F39+L39)>0, (F39+L39-M39)/(F39+L39), """"), """"), """")"),"") | R39: TRUE | S39: TRUE | T39: FALSE | U39: In Billing | V39: TRUE | W39: =O39 -> 0.49463796 | X39: =J39 -> 4998.1 | Y39: =F39 -> 4998.1 | Z39: =L39 -> 0 | AA39: =IFERROR(__xludf.DUMMYFUNCTION("""COMPUTED_VALUE"""),"Drew") -> Drew | AB39: =K39 -> 4998.1
A40: 1194 | B40: 20255039 | C40: Mina Shafiei | D40: Roofing and Siding | E40: 45746 | F40: 12125.58 | G40: 45749 | H40: 45749 | I40: James | J40: 12125.58 | K40: 12125.58 | L40: =if(S40=TRUE,K40-F40,"") -> 0 | M40: 8102.12 | N40: =if(S40=TRUE,K40-M40,"") -> 4023.46 | O40: =IF($R40, IFERROR(IF((F40+L40)>0, (F40+L40-M40)/(F40+L40), ""), ""), "") -> 0.33181588 | P40: =IFERROR(__xludf.DUMMYFUNCTION("IF(AND($R40, NOT(REGEXMATCH(UPPER($C40), ""INS""))), IFERROR(IF((F40+L40)>0, (F40+L40-M40)/(F40+L40), """"), """"), """")"),0.33181588014758884) -> 0.33181588 | Q40: =IFERROR(__xludf.DUMMYFUNCTION("IF(AND($R40, REGEXMATCH(UPPER($C40), ""INS"")), IFERROR(IF((F40+L40)>0, (F40+L40-M40)/(F40+L40), """"), """"), """")"),"") | R40: TRUE | S40: TRUE | T40: FALSE | U40: In Billing | V40: TRUE | W40: =O40 -> 0.33181588 | X40: =J40 -> 12125.58 | Y40: =F40 -> 12125.58 | Z40: =L40 -> 0 | AA40: =IFERROR(__xludf.DUMMYFUNCTION("""COMPUTED_VALUE"""),"") | AB40: =K40 -> 12125.58
A41: 1151 | B41: 20255040 | C41: Ben McClurg | D41: Roofing and Siding | E41: 45746 | F41: 12928.29 | G41: 45764 | H41: 45764 | I41: James | J41: 12928.29 | K41: 12928.29 | L41: =if(S41=TRUE,K41-F41,"") -> 0 | M41: 8144.01 | N41: =if(S41=TRUE,K41-M41,"") -> 4784.28 | O41: =IF($R41, IFERROR(IF((F41+L41)>0, (F41+L41-M41)/(F41+L41), ""), ""), "") -> 0.37006286 | P41: =IFERROR(__xludf.DUMMYFUNCTION("IF(AND($R41, NOT(REGEXMATCH(UPPER($C41), ""INS""))), IFERROR(IF((F41+L41)>0, (F41+L41-M41)/(F41+L41), """"), """"), """")"),0.370062862141861) -> 0.37006286 | Q41: =IFERROR(__xludf.DUMMYFUNCTION("IF(AND($R41, REGEXMATCH(UPPER($C41), ""INS"")), IFERROR(IF((F41+L41)>0, (F41+L41-M41)/(F41+L41), """"), """"), """")"),"") | R41: TRUE | S41: TRUE | T41: FALSE | U41: In Billing | V41: TRUE | W41: =O41 -> 0.37006286 | X41: =J41 -> 12928.29 | Y41: =F41 -> 12928.29 | Z41: =L41 -> 0 | AA41: =IFERROR(__xludf.DUMMYFUNCTION("""COMPUTED_VALUE"""),"") | AB41: =K41 -> 12928.29
A42: 1240 | B42: 20255041 | C42: Zynell Clemons | D42: Roofing and Siding | E42: 45747 | F42: 0 | G42: 45866 | H42: 45866 | I42: James | L42: =if(S42=TRUE,K42-F42,"") -> 0 | N42: =if(S42=TRUE,K42-M42,"") -> 0 | O42: =IF($R42, IFERROR(IF((F42+L42)>0, (F42+L42-M42)/(F42+L42), ""), ""), "") | P42: =IFERROR(__xludf.DUMMYFUNCTION("IF(AND($R42, NOT(REGEXMATCH(UPPER($C42), ""INS""))), IFERROR(IF((F42+L42)>0, (F42+L42-M42)/(F42+L42), """"), """"), """")"),"") | Q42: =IFERROR(__xludf.DUMMYFUNCTION("IF(AND($R42, REGEXMATCH(UPPER($C42), ""INS"")), IFERROR(IF((F42+L42)>0, (F42+L42-M42)/(F42+L42), """"), """"), """")"),"") | R42: TRUE | S42: TRUE | T42: FALSE | U42: In Billing | V42: FALSE | W42: =O42 | X42: =J42 | Y42: =F42 -> 0 | Z42: =L42 -> 0 | AA42: =IFERROR(__xludf.DUMMYFUNCTION("""COMPUTED_VALUE"""),"") | AB42: =K42
A43: 1233 | B43: 20255042 | C43: Penny Willis | D43: Roofing and Siding | E43: 45748 | F43: 2100 | G43: 45771 | H43: 45771 | I43: James | J43: 2100 | K43: 2100 | L43: =if(S43=TRUE,K43-F43,"") -> 0 | M43: 1000 | N43: =if(S43=TRUE,K43-M43,"") -> 1100 | O43: =IF($R43, IFERROR(IF((F43+L43)>0, (F43+L43-M43)/(F43+L43), ""), ""), "") -> 0.52380952 | P43: =IFERROR(__xludf.DUMMYFUNCTION("IF(AND($R43, NOT(REGEXMATCH(UPPER($C43), ""INS""))), IFERROR(IF((F43+L43)>0, (F43+L43-M43)/(F43+L43), """"), """"), """")"),0.5238095238095238) -> 0.52380952 | Q43: =IFERROR(__xludf.DUMMYFUNCTION("IF(AND($R43, REGEXMATCH(UPPER($C43), ""INS"")), IFERROR(IF((F43+L43)>0, (F43+L43-M43)/(F43+L43), """"), """"), """")"),"") | R43: TRUE | S43: TRUE | T43: FALSE | U43: In Billing | V43: TRUE | W43: =O43 -> 0.52380952 | X43: =J43 -> 2100 | Y43: =F43 -> 2100 | Z43: =L43 -> 0 | AA43: =IFERROR(__xludf.DUMMYFUNCTION("""COMPUTED_VALUE"""),"") | AB43: =K43 -> 2100
A44: 1263 | B44: 20255043 | C44: Amy Stamps | D44: Roofing and Siding | E44: 45749 | F44: 400 | G44: 45749 | H44: 45749 | I44: Brett | J44: 400 | K44: 400 | L44: =if(S44=TRUE,K44-F44,"") -> 0 | M44: 0.01 | N44: =if(S44=TRUE,K44-M44,"") -> 399.99 | O44: =IF($R44, IFERROR(IF((F44+L44)>0, (F44+L44-M44)/(F44+L44), ""), ""), "") -> 0.999975 | P44: =IFERROR(__xludf.DUMMYFUNCTION("IF(AND($R44, NOT(REGEXMATCH(UPPER($C44), ""INS""))), IFERROR(IF((F44+L44)>0, (F44+L44-M44)/(F44+L44), """"), """"), """")"),0.9999750000000001) -> 0.999975 | Q44: =IFERROR(__xludf.DUMMYFUNCTION("IF(AND($R44, REGEXMATCH(UPPER($C44), ""INS"")), IFERROR(IF((F44+L44)>0, (F44+L44-M44)/(F44+L44), """"), """"), """")"),"") | R44: TRUE | S44: TRUE | T44: FALSE | U44: In Billing | V44: TRUE | W44: =O44 -> 0.999975 | X44: =J44 -> 400 | Y44: =F44 -> 400 | Z44: =L44 -> 0 | AA44: =IFERROR(__xludf.DUMMYFUNCTION("""COMPUTED_VALUE"""),"") | AB44: =K44 -> 400
A45: 1223 | B45: 20255044 | C45: INS - Tom Myers Siding | E45: 45749 | F45: 26207.57 | G45: 45789 | H45: 45791 | I45: Chris | J45: 26207.57 | K45: 26207.57 | L45: =if(S45=TRUE,K45-F45,"") -> 0 | M45: 14667.37 | N45: =if(S45=TRUE,K45-M45,"") -> 11540.2 | O45: =IF($R45, IFERROR(IF((F45+L45)>0, (F45+L45-M45)/(F45+L45), ""), ""), "") -> 0.44033842 | P45: =IFERROR(__xludf.DUMMYFUNCTION("IF(AND($R45, NOT(REGEXMATCH(UPPER($C45), ""INS""))), IFERROR(IF((F45+L45)>0, (F45+L45-M45)/(F45+L45), """"), """"), """")"),"") | Q45: =IFERROR(__xludf.DUMMYFUNCTION("IF(AND($R45, REGEXMATCH(UPPER($C45), ""INS"")), IFERROR(IF((F45+L45)>0, (F45+L45-M45)/(F45+L45), """"), """"), """")"),0.44033842130346307) -> 0.44033842 | R45: TRUE | S45: TRUE | T45: TRUE | U45: In Billing | V45: TRUE | W45: =O45 -> 0.44033842 | X45: =J45 -> 26207.57 | Y45: =F45 -> 26207.57 | Z45: =L45 -> 0 | AA45: =IFERROR(__xludf.DUMMYFUNCTION("""COMPUTED_VALUE"""),"") | AB45: =K45 -> 26207.57
A46: 1182 | B46: 20255045 | C46: Jennifer Colwell | E46: 45751 | F46: 4096.35 | G46: 45776 | H46: 45776 | I46: James | J46: 4151.35 | K46: 4151.35 | L46: =if(S46=TRUE,K46-F46,"") -> 55 | M46: 2799.17 | N46: =if(S46=TRUE,K46-M46,"") -> 1352.18 | O46: =IF($R46, IFERROR(IF((F46+L46)>0, (F46+L46-M46)/(F46+L46), ""), ""), "") -> 0.32572055 | P46: =IFERROR(__xludf.DUMMYFUNCTION("IF(AND($R46, NOT(REGEXMATCH(UPPER($C46), ""INS""))), IFERROR(IF((F46+L46)>0, (F46+L46-M46)/(F46+L46), """"), """"), """")"),0.32572054873715783) -> 0.32572055 | Q46: =IFERROR(__xludf.DUMMYFUNCTION("IF(AND($R46, REGEXMATCH(UPPER($C46), ""INS"")), IFERROR(IF((F46+L46)>0, (F46+L46-M46)/(F46+L46), """"), """"), """")"),"") | R46: TRUE | S46: TRUE | T46: FALSE | U46: In Billing | V46: TRUE | W46: =O46 -> 0.32572055 | X46: =J46 -> 4151.35 | Y46: =F46 -> 4096.35 | Z46: =L46 -> 55 | AA46: =IFERROR(__xludf.DUMMYFUNCTION("""COMPUTED_VALUE"""),"") | AB46: =K46 -> 4151.35
A47: 1271 | B47: 20255046 | C47: Mark Webster | E47: 45754 | F47: 640 | G47: 45778 | H47: 45778 | I47: Brett | J47: 640 | K47: 640 | L47: =if(S47=TRUE,K47-F47,"") -> 0 | M47: 300 | N47: =if(S47=TRUE,K47-M47,"") -> 340 | O47: =IF($R47, IFERROR(IF((F47+L47)>0, (F47+L47-M47)/(F47+L47), ""), ""), "") -> 0.53125 | P47: =IFERROR(__xludf.DUMMYFUNCTION("IF(AND($R47, NOT(REGEXMATCH(UPPER($C47), ""INS""))), IFERROR(IF((F47+L47)>0, (F47+L47-M47)/(F47+L47), """"), """"), """")"),0.53125) -> 0.53125 | Q47: =IFERROR(__xludf.DUMMYFUNCTION("IF(AND($R47, REGEXMATCH(UPPER($C47), ""INS"")), IFERROR(IF((F47+L47)>0, (F47+L47-M47)/(F47+L47), """"), """"), """")"),"") | R47: TRUE | S47: TRUE | T47: FALSE | U47: In Billing | V47: TRUE | W47: =O47 -> 0.53125 | X47: =J47 -> 640 | Y47: =F47 -> 640 | Z47: =L47 -> 0 | AA47: =IFERROR(__xludf.DUMMYFUNCTION("""COMPUTED_VALUE"""),"") | AB47: =K47 -> 640
A48: 1156 | B48: 20255047 | C48: Anthony Cruz | E48: 45755 | F48: 11392.42 | G48: 01/29/2026 | H48: 01/29/2026 | I48: James | J48: 175 | K48: 6155.69 | L48: =if(S48=TRUE,K48-F48,"") -> -5236.73 | M48: 5149.1 | N48: =if(S48=TRUE,K48-M48,"") -> 1006.59 | O48: =IF($R48, IFERROR(IF((F48+L48)>0, (F48+L48-M48)/(F48+L48), ""), ""), "") -> 0.16352188 | P48: =IFERROR(__xludf.DUMMYFUNCTION("IF(AND($R48, NOT(REGEXMATCH(UPPER($C48), ""INS""))), IFERROR(IF((F48+L48)>0, (F48+L48-M48)/(F48+L48), """"), """"), """")"),0.16352187975677776) -> 0.16352188 | Q48: =IFERROR(__xludf.DUMMYFUNCTION("IF(AND($R48, REGEXMATCH(UPPER($C48), ""INS"")), IFERROR(IF((F48+L48)>0, (F48+L48-M48)/(F48+L48), """"), """"), """")"),"") | R48: TRUE | S48: TRUE | T48: FALSE | U48: In Billing | V48: TRUE | W48: =O48 -> 0.16352188 | X48: =J48 -> 175 | Y48: =F48 -> 11392.42 | Z48: =L48 -> -5236.73 | AA48: =IFERROR(__xludf.DUMMYFUNCTION("""COMPUTED_VALUE"""),"") | AB48: =K48 -> 6155.69 | AC48: 46077
A49: 1076 | B49: 20255048 | C49: TJ Bernard | E49: 45755 | F49: 19220.17 | G49: 45771 | H49: 45771 | I49: Will | J49: 19220.17 | K49: 19220.17 | L49: =if(S49=TRUE,K49-F49,"") -> 0 | M49: 11973.64 | N49: =if(S49=TRUE,K49-M49,"") -> 7246.53 | O49: =IF($R49, IFERROR(IF((F49+L49)>0, (F49+L49-M49)/(F49+L49), ""), ""), "") -> 0.37702736 | P49: =IFERROR(__xludf.DUMMYFUNCTION("IF(AND($R49, NOT(REGEXMATCH(UPPER($C49), ""INS""))), IFERROR(IF((F49+L49)>0, (F49+L49-M49)/(F49+L49), """"), """"), """")"),0.37702736240106094) -> 0.37702736 | Q49: =IFERROR(__xludf.DUMMYFUNCTION("IF(AND($R49, REGEXMATCH(UPPER($C49), ""INS"")), IFERROR(IF((F49+L49)>0, (F49+L49-M49)/(F49+L49), """"), """"), """")"),"") | R49: TRUE | S49: TRUE | T49: TRUE | U49: In Billing | V49: TRUE | W49: =O49 -> 0.37702736 | X49: =J49 -> 19220.17 | Y49: =F49 -> 19220.17 | Z49: =L49 -> 0 | AA49: =IFERROR(__xludf.DUMMYFUNCTION("""COMPUTED_VALUE"""),"") | AB49: =K49 -> 19220.17
A50: 1238 | B50: 20255049 | C50: Pam Sizemore | E50: 45756 | F50: 7299.87 | G50: 45785 | H50: 45785 | I50: Brett | J50: 8079.87 | K50: 8079.87 | L50: =if(S50=TRUE,K50-F50,"") -> 780 | M50: 5109.88 | N50: =if(S50=TRUE,K50-M50,"") -> 2969.99 | O50: =IF($R50, IFERROR(IF((F50+L50)>0, (F50+L50-M50)/(F50+L50), ""), ""), "") -> 0.36757893 | P50: =IFERROR(__xludf.DUMMYFUNCTION("IF(AND($R50, NOT(REGEXMATCH(UPPER($C50), ""INS""))), IFERROR(IF((F50+L50)>0, (F50+L50-M50)/(F50+L50), """"), """"), """")"),0.36757893381947976) -> 0.36757893 | Q50: =IFERROR(__xludf.DUMMYFUNCTION("IF(AND($R50, REGEXMATCH(UPPER($C50), ""INS"")), IFERROR(IF((F50+L50)>0, (F50+L50-M50)/(F50+L50), """"), """"), """")"),"") | R50: TRUE | S50: TRUE | T50: FALSE | U50: In Billing | V50: TRUE | W50: =O50 -> 0.36757893 | X50: =J50 -> 8079.87 | Y50: =F50 -> 7299.87 | Z50: =L50 -> 780 | AA50: =IFERROR(__xludf.DUMMYFUNCTION("""COMPUTED_VALUE"""),"") | AB50: =K50 -> 8079.87
A51: 1276 | B51: 20255050 | C51: Kelly Thakkar | E51: 45757 | F51: 6349.21 | G51: 45778 | H51: 45778 | I51: Adam | J51: 6349.21 | K51: 6349.21 | L51: =if(S51=TRUE,K51-F51,"") -> 0 | M51: 3886.63 | N51: =if(S51=TRUE,K51-M51,"") -> 2462.58 | O51: =IF($R51, IFERROR(IF((F51+L51)>0, (F51+L51-M51)/(F51+L51), ""), ""), "") -> 0.38785613 | P51: =IFERROR(__xludf.DUMMYFUNCTION("IF(AND($R51, NOT(REGEXMATCH(UPPER($C51), ""INS""))), IFERROR(IF((F51+L51)>0, (F51+L51-M51)/(F51+L51), """"), """"), """")"),0.387856126982727) -> 0.38785613 | Q51: =IFERROR(__xludf.DUMMYFUNCTION("IF(AND($R51, REGEXMATCH(UPPER($C51), ""INS"")), IFERROR(IF((F51+L51)>0, (F51+L51-M51)/(F51+L51), """"), """"), """")"),"") | R51: TRUE | S51: TRUE | T51: FALSE | U51: In Billing | V51: TRUE | W51: =O51 -> 0.38785613 | X51: =J51 -> 6349.21 | Y51: =F51 -> 6349.21 | Z51: =L51 -> 0 | AA51: =IFERROR(__xludf.DUMMYFUNCTION("""COMPUTED_VALUE"""),"") | AB51: =K51 -> 6349.21
A52: 1169 | B52: 20255051 | C52: Dustin Johnson | E52: 45757 | F52: 25931.81 | G52: 12/09/2025 | H52: 12/09/2025 | I52: Drew | J52: 25931.81 | K52: 25931.81 | L52: =if(S52=TRUE,K52-F52,"") -> 0 | M52: 16936.61 | N52: =if(S52=TRUE,K52-M52,"") -> 8995.2 | O52: =IF($R52, IFERROR(IF((F52+L52)>0, (F52+L52-M52)/(F52+L52), ""), ""), "") -> 0.34687899 | P52: =IFERROR(__xludf.DUMMYFUNCTION("IF(AND($R52, NOT(REGEXMATCH(UPPER($C52), ""INS""))), IFERROR(IF((F52+L52)>0, (F52+L52-M52)/(F52+L52), """"), """"), """")"),0.3468789876217665) -> 0.34687899 | Q52: =IFERROR(__xludf.DUMMYFUNCTION("IF(AND($R52, REGEXMATCH(UPPER($C52), ""INS"")), IFERROR(IF((F52+L52)>0, (F52+L52-M52)/(F52+L52), """"), """"), """")"),"") | R52: TRUE | S52: TRUE | T52: FALSE | U52: In Billing | V52: TRUE | W52: =O52 -> 0.34687899 | X52: =J52 -> 25931.81 | Y52: =F52 -> 25931.81 | Z52: =L52 -> 0 | AA52: =IFERROR(__xludf.DUMMYFUNCTION("""COMPUTED_VALUE"""),"Drew") -> Drew | AB52: =K52 -> 25931.81
A53: 1264 | B53: 20255052 | C53: INS - Misty Dalykas | E53: 45757 | F53: 7395.46 | G53: 45778 | H53: 45778 | I53: James | J53: 10679.49 | K53: 10679.49 | L53: =if(S53=TRUE,K53-F53,"") -> 3284.03 | M53: 6329.02 | N53: =if(S53=TRUE,K53-M53,"") -> 4350.47 | O53: =IF($R53, IFERROR(IF((F53+L53)>0, (F53+L53-M53)/(F53+L53), ""), ""), "") -> 0.40736683 | P53: =IFERROR(__xludf.DUMMYFUNCTION("IF(AND($R53, NOT(REGEXMATCH(UPPER($C53), ""INS""))), IFERROR(IF((F53+L53)>0, (F53+L53-M53)/(F53+L53), """"), """"), """")"),"") | Q53: =IFERROR(__xludf.DUMMYFUNCTION("IF(AND($R53, REGEXMATCH(UPPER($C53), ""INS"")), IFERROR(IF((F53+L53)>0, (F53+L53-M53)/(F53+L53), """"), """"), """")"),0.40736683118763156) -> 0.40736683 | R53: TRUE | S53: TRUE | T53: FALSE | U53: In Billing | V53: TRUE | W53: =O53 -> 0.40736683 | X53: =J53 -> 10679.49 | Y53: =F53 -> 7395.46 | Z53: =L53 -> 3284.03 | AA53: =IFERROR(__xludf.DUMMYFUNCTION("""COMPUTED_VALUE"""),"") | AB53: =K53 -> 10679.49
A54: 1265 | B54: 20255053 | C54: Mark Wolfe | E54: 45761 | F54: 11800.9 | G54: 45820 | H54: 45820 | I54: Drew | J54: 11800.9 | K54: 11800.9 | L54: =if(S54=TRUE,K54-F54,"") -> 0 | M54: 6871.35 | N54: =if(S54=TRUE,K54-M54,"") -> 4929.55 | O54: =IF($R54, IFERROR(IF((F54+L54)>0, (F54+L54-M54)/(F54+L54), ""), ""), "") -> 0.41772661 | P54: =IFERROR(__xludf.DUMMYFUNCTION("IF(AND($R54, NOT(REGEXMATCH(UPPER($C54), ""INS""))), IFERROR(IF((F54+L54)>0, (F54+L54-M54)/(F54+L54), """"), """"), """")"),0.41772661407180806) -> 0.41772661 | Q54: =IFERROR(__xludf.DUMMYFUNCTION("IF(AND($R54, REGEXMATCH(UPPER($C54), ""INS"")), IFERROR(IF((F54+L54)>0, (F54+L54-M54)/(F54+L54), """"), """"), """")"),"") | R54: TRUE | S54: TRUE | T54: FALSE | U54: In Billing | V54: TRUE | W54: =O54 -> 0.41772661 | X54: =J54 -> 11800.9 | Y54: =F54 -> 11800.9 | Z54: =L54 -> 0 | AA54: =IFERROR(__xludf.DUMMYFUNCTION("""COMPUTED_VALUE"""),"Drew") -> Drew | AB54: =K54 -> 11800.9
A55: 1302 | B55: 20255054 | C55: Adam Sweigart | E55: 45764 | F55: 14509.04 | G55: 45778 | H55: 45778 | I55: Chris | J55: 14509.04 | K55: 14509.04 | L55: =if(S55=TRUE,K55-F55,"") -> 0 | M55: 8819.86 | N55: =if(S55=TRUE,K55-M55,"") -> 5689.18 | O55: =IF($R55, IFERROR(IF((F55+L55)>0, (F55+L55-M55)/(F55+L55), ""), ""), "") -> 0.39211278 | P55: =IFERROR(__xludf.DUMMYFUNCTION("IF(AND($R55, NOT(REGEXMATCH(UPPER($C55), ""INS""))), IFERROR(IF((F55+L55)>0, (F55+L55-M55)/(F55+L55), """"), """"), """")"),0.3921127793430854) -> 0.39211278 | Q55: =IFERROR(__xludf.DUMMYFUNCTION("IF(AND($R55, REGEXMATCH(UPPER($C55), ""INS"")), IFERROR(IF((F55+L55)>0, (F55+L55-M55)/(F55+L55), """"), """"), """")"),"") | R55: TRUE | S55: TRUE | T55: TRUE | U55: In Billing | V55: TRUE | W55: =O55 -> 0.39211278 | X55: =J55 -> 14509.04 | Y55: =F55 -> 14509.04 | Z55: =L55 -> 0 | AA55: =IFERROR(__xludf.DUMMYFUNCTION("""COMPUTED_VALUE"""),"") | AB55: =K55 -> 14509.04
A56: 1282 | B56: 20255055 | C56: INS - Kevin And Cheryl Sims | E56: 45768 | F56: 58303.98 | G56: 45890 | H56: 45890 | I56: James | J56: 51092.47 | K56: 51092.47 | L56: =if(S56=TRUE,K56-F56,"") | M56: 48435.26 | N56: =if(S56=TRUE,K56-M56,"") | O56: =IF($R56, IFERROR(IF((F56+L56)>0, (F56+L56-M56)/(F56+L56), ""), ""), "") | P56: =IFERROR(__xludf.DUMMYFUNCTION("IF(AND($R56, NOT(REGEXMATCH(UPPER($C56), ""INS""))), IFERROR(IF((F56+L56)>0, (F56+L56-M56)/(F56+L56), """"), """"), """")"),"") | Q56: =IFERROR(__xludf.DUMMYFUNCTION("IF(AND($R56, REGEXMATCH(UPPER($C56), ""INS"")), IFERROR(IF((F56+L56)>0, (F56+L56-M56)/(F56+L56), """"), """"), """")"),"") | R56: FALSE | S56: FALSE | T56: FALSE | U56: In Billing | V56: TRUE | W56: =O56 | X56: =J56 -> 51092.47 | Y56: =F56 -> 58303.98 | Z56: =L56 | AA56: =IFERROR(__xludf.DUMMYFUNCTION("""COMPUTED_VALUE"""),"") | AB56: =K56 -> 51092.47
A57: 1316 | B57: 20255056 | C57: INS - Ryan Bloomingdale | E57: 45768 | F57: 56343.02 | G57: 45883 | H57: 45883 | I57: James | J57: 46244.27 | K57: 58153.75 | L57: =if(S57=TRUE,K57-F57,"") -> 1810.73 | M57: 18539.22 | N57: =if(S57=TRUE,K57-M57,"") -> 39614.53 | O57: =IF($R57, IFERROR(IF((F57+L57)>0, (F57+L57-M57)/(F57+L57), ""), ""), "") -> 0.68120336 | P57: =IFERROR(__xludf.DUMMYFUNCTION("IF(AND($R57, NOT(REGEXMATCH(UPPER($C57), ""INS""))), IFERROR(IF((F57+L57)>0, (F57+L57-M57)/(F57+L57), """"), """"), """")"),"") | Q57: =IFERROR(__xludf.DUMMYFUNCTION("IF(AND($R57, REGEXMATCH(UPPER($C57), ""INS"")), IFERROR(IF((F57+L57)>0, (F57+L57-M57)/(F57+L57), """"), """"), """")"),0.6812033617780453) -> 0.68120336 | R57: TRUE | S57: TRUE | T57: FALSE | U57: In Billing | V57: TRUE | W57: =O57 -> 0.68120336 | X57: =J57 -> 46244.27 | Y57: =F57 -> 56343.02 | Z57: =L57 -> 1810.73 | AA57: =IFERROR(__xludf.DUMMYFUNCTION("""COMPUTED_VALUE"""),"") | AB57: =K57 -> 58153.75 | AC57: 46097
A58: 1155 | B58: 20255057 | C58: INS - Emily Hammel | E58: 45769 | F58: 21590.43 | G58: 45890 | H58: 45890 | I58: Brett | J58: 19516.94 | K58: 18712.23 | L58: =if(S58=TRUE,K58-F58,"") | M58: 11724.74 | N58: =if(S58=TRUE,K58-M58,"") | O58: =IF($R58, IFERROR(IF((F58+L58)>0, (F58+L58-M58)/(F58+L58), ""), ""), "") -> 0.45694736 | P58: =IFERROR(__xludf.DUMMYFUNCTION("IF(AND($R58, NOT(REGEXMATCH(UPPER($C58), ""INS""))), IFERROR(IF((F58+L58)>0, (F58+L58-M58)/(F58+L58), """"), """"), """")"),"") | Q58: =IFERROR(__xludf.DUMMYFUNCTION("IF(AND($R58, REGEXMATCH(UPPER($C58), ""INS"")), IFERROR(IF((F58+L58)>0, (F58+L58-M58)/(F58+L58), """"), """"), """")"),0.4569473604740619) -> 0.45694736 | R58: TRUE | S58: FALSE | T58: FALSE | U58: In Billing | V58: TRUE | W58: =O58 -> 0.45694736 | X58: =J58 -> 19516.94 | Y58: =F58 -> 21590.43 | Z58: =L58 | AA58: =IFERROR(__xludf.DUMMYFUNCTION("""COMPUTED_VALUE"""),"") | AB58: =K58 -> 18712.23
A59: 1319 | B59: 20255058 | C59: Dorothy Reed | E59: 45769 | F59: 1829.95 | G59: 45806 | H59: 45806 | I59: Drew | J59: 1226.11 | K59: 1226.11 | L59: =if(S59=TRUE,K59-F59,"") -> -603.84 | M59: 818.75 | N59: =if(S59=TRUE,K59-M59,"") -> 407.36 | O59: 0.3322 | P59: =IFERROR(__xludf.DUMMYFUNCTION("IF(AND($R59, NOT(REGEXMATCH(UPPER($C59), ""INS""))), IFERROR(IF((F59+L59)>0, (F59+L59-M59)/(F59+L59), """"), """"), """")"),0.3322377274469664) -> 0.33223773 | Q59: =IFERROR(__xludf.DUMMYFUNCTION("IF(AND($R59, REGEXMATCH(UPPER($C59), ""INS"")), IFERROR(IF((F59+L59)>0, (F59+L59-M59)/(F59+L59), """"), """"), """")"),"") | R59: TRUE | S59: TRUE | T59: FALSE | U59: In Billing | V59: TRUE | W59: =O59 -> 0.3322 | X59: =J59 -> 1226.11 | Y59: =F59 -> 1829.95 | Z59: =L59 -> -603.84 | AA59: =IFERROR(__xludf.DUMMYFUNCTION("""COMPUTED_VALUE"""),"Drew") -> Drew | AB59: =K59 -> 1226.11
A60: 1360 | B60: 20255059 | C60: Drew Haker | E60: 45771 | F60: 940 | G60: 45785 | H60: 45785 | I60: Drew | J60: 940 | K60: 940 | L60: =if(S60=TRUE,K60-F60,"") -> 0 | M60: 375 | N60: =if(S60=TRUE,K60-M60,"") -> 565 | O60: =IF($R60, IFERROR(IF((F60+L60)>0, (F60+L60-M60)/(F60+L60), ""), ""), "") -> 0.60106383 | P60: =IFERROR(__xludf.DUMMYFUNCTION("IF(AND($R60, NOT(REGEXMATCH(UPPER($C60), ""INS""))), IFERROR(IF((F60+L60)>0, (F60+L60-M60)/(F60+L60), """"), """"), """")"),0.601063829787234) -> 0.60106383 | Q60: =IFERROR(__xludf.DUMMYFUNCTION("IF(AND($R60, REGEXMATCH(UPPER($C60), ""INS"")), IFERROR(IF((F60+L60)>0, (F60+L60-M60)/(F60+L60), """"), """"), """")"),"") | R60: TRUE | S60: TRUE | T60: FALSE | U60: In Billing | V60: TRUE | W60: =O60 -> 0.60106383 | X60: =J60 -> 940 | Y60: =F60 -> 940 | Z60: =L60 -> 0 | AA60: =IFERROR(__xludf.DUMMYFUNCTION("""COMPUTED_VALUE"""),"Drew") -> Drew | AB60: =K60 -> 940
A61: 1350 | B61: 20255060 | C61: Rayce Robinon - Clocktower | E61: 45771 | F61: 175 | G61: 45779 | H61: 45779 | I61: James | J61: 175 | K61: 175 | L61: =if(S61=TRUE,K61-F61,"") -> 0 | M61: 175 | N61: =if(S61=TRUE,K61-M61,"") -> 0 | O61: =IF($R61, IFERROR(IF((F61+L61)>0, (F61+L61-M61)/(F61+L61), ""), ""), "") -> 0 | P61: =IFERROR(__xludf.DUMMYFUNCTION("IF(AND($R61, NOT(REGEXMATCH(UPPER($C61), ""INS""))), IFERROR(IF((F61+L61)>0, (F61+L61-M61)/(F61+L61), """"), """"), """")"),0.0) -> 0 | Q61: =IFERROR(__xludf.DUMMYFUNCTION("IF(AND($R61, REGEXMATCH(UPPER($C61), ""INS"")), IFERROR(IF((F61+L61)>0, (F61+L61-M61)/(F61+L61), """"), """"), """")"),"") | R61: TRUE | S61: TRUE | T61: FALSE | U61: In Billing | V61: TRUE | W61: =O61 -> 0 | X61: =J61 -> 175 | Y61: =F61 -> 175 | Z61: =L61 -> 0 | AA61: =IFERROR(__xludf.DUMMYFUNCTION("""COMPUTED_VALUE"""),"") | AB61: =K61 -> 175
A62: 1286 | B62: 20255061 | C62: David Torrence | E62: 45772 | F62: 10657.27 | G62: 45799 | H62: 45799 | I62: Brett | J62: 10767.27 | K62: 10767.27 | L62: =if(S62=TRUE,K62-F62,"") -> 110 | M62: 6535.58 | N62: =if(S62=TRUE,K62-M62,"") -> 4231.69 | O62: =IF($R62, IFERROR(IF((F62+L62)>0, (F62+L62-M62)/(F62+L62), ""), ""), "") -> 0.3930142 | P62: 0.393 | Q62: =IFERROR(__xludf.DUMMYFUNCTION("IF(AND($R62, REGEXMATCH(UPPER($C62), ""INS"")), IFERROR(IF((F62+L62)>0, (F62+L62-M62)/(F62+L62), """"), """"), """")"),"") | R62: TRUE | S62: TRUE | T62: FALSE | U62: In Billing | V62: TRUE | W62: =O62 -> 0.3930142 | X62: =J62 -> 10767.27 | Y62: =F62 -> 10657.27 | Z62: =L62 -> 110 | AA62: =IFERROR(__xludf.DUMMYFUNCTION("""COMPUTED_VALUE"""),"") | AB62: =K62 -> 10767.27
A63: 1356 | B63: 20255062 | C63: Shawn Vehr | E63: 45772 | F63: 10060.52 | G63: 45820 | H63: 45820 | I63: Drew | J63: 10060.52 | K63: 10060.52 | L63: =if(S63=TRUE,K63-F63,"") -> 0 | M63: 4376.48 | N63: =if(S63=TRUE,K63-M63,"") -> 5684.04 | O63: =IF($R63, IFERROR(IF((F63+L63)>0, (F63+L63-M63)/(F63+L63), ""), ""), "") -> 0.56498471 | P63: =IFERROR(__xludf.DUMMYFUNCTION("IF(AND($R63, NOT(REGEXMATCH(UPPER($C63), ""INS""))), IFERROR(IF((F63+L63)>0, (F63+L63-M63)/(F63+L63), """"), """"), """")"),0.5649847125198301) -> 0.56498471 | Q63: =IFERROR(__xludf.DUMMYFUNCTION("IF(AND($R63, REGEXMATCH(UPPER($C63), ""INS"")), IFERROR(IF((F63+L63)>0, (F63+L63-M63)/(F63+L63), """"), """"), """")"),"") | R63: TRUE | S63: TRUE | T63: FALSE | U63: In Billing | V63: TRUE | W63: =O63 -> 0.56498471 | X63: =J63 -> 10060.52 | Y63: =F63 -> 10060.52 | Z63: =L63 -> 0 | AA63: =IFERROR(__xludf.DUMMYFUNCTION("""COMPUTED_VALUE"""),"Drew") -> Drew | AB63: =K63 -> 10060.52
A64: 1153 | B64: 20255063 | C64: INS - Glen Shelley | E64: 45772 | F64: 12550.85 | G64: 45792 | H64: 45792 | I64: Brett | J64: 11109.02 | K64: 15711.62 | L64: =if(S64=TRUE,K64-F64,"") -> 3160.77 | M64: 8075.9 | N64: =if(S64=TRUE,K64-M64,"") -> 7635.72 | O64: =IF($R64, IFERROR(IF((F64+L64)>0, (F64+L64-M64)/(F64+L64), ""), ""), "") -> 0.4859919 | P64: =IFERROR(__xludf.DUMMYFUNCTION("IF(AND($R64, NOT(REGEXMATCH(UPPER($C64), ""INS""))), IFERROR(IF((F64+L64)>0, (F64+L64-M64)/(F64+L64), """"), """"), """")"),"") | Q64: =IFERROR(__xludf.DUMMYFUNCTION("IF(AND($R64, REGEXMATCH(UPPER($C64), ""INS"")), IFERROR(IF((F64+L64)>0, (F64+L64-M64)/(F64+L64), """"), """"), """")"),0.48599189644352403) -> 0.4859919 | R64: TRUE | S64: TRUE | T64: TRUE | U64: In Billing | V64: TRUE | W64: =O64 -> 0.4859919 | X64: =J64 -> 11109.02 | Y64: =F64 -> 12550.85 | Z64: =L64 -> 3160.77 | AA64: =IFERROR(__xludf.DUMMYFUNCTION("""COMPUTED_VALUE"""),"") | AB64: =K64 -> 15711.62 | AC64: 46007
A65: 1333 | B65: 20255064 | C65: INS - Katherine Clemmer | E65: 45774 | F65: 4427.24 | G65: 45799 | H65: 45799 | I65: Drew | J65: 6183.98 | K65: 6183.98 | L65: =if(S65=TRUE,K65-F65,"") -> 1756.74 | M65: 3014.59 | N65: =if(S65=TRUE,K65-M65,"") -> 3169.39 | O65: =IF($R65, IFERROR(IF((F65+L65)>0, (F65+L65-M65)/(F65+L65), ""), ""), "") -> 0.51251621 | P65: =IFERROR(__xludf.DUMMYFUNCTION("IF(AND($R65, NOT(REGEXMATCH(UPPER($C65), ""INS""))), IFERROR(IF((F65+L65)>0, (F65+L65-M65)/(F65+L65), """"), """"), """")"),"") | Q65: =IFERROR(__xludf.DUMMYFUNCTION("IF(AND($R65, REGEXMATCH(UPPER($C65), ""INS"")), IFERROR(IF((F65+L65)>0, (F65+L65-M65)/(F65+L65), """"), """"), """")"),0.5125162112425977) -> 0.51251621 | R65: TRUE | S65: TRUE | T65: FALSE | U65: In Billing | V65: TRUE | W65: =O65 -> 0.51251621 | X65: =J65 -> 6183.98 | Y65: =F65 -> 4427.24 | Z65: =L65 -> 1756.74 | AA65: =IFERROR(__xludf.DUMMYFUNCTION("""COMPUTED_VALUE"""),"Drew") -> Drew | AB65: =K65 -> 6183.98
A66: 1225 | B66: 20255065 | C66: Robert Cobb | E66: 45776 | F66: 15148.55 | G66: 45806 | H66: 45806 | I66: James | J66: 19558.36 | K66: 19558.36 | L66: =if(S66=TRUE,K66-F66,"") -> 4409.81 | M66: 11658.12 | N66: =if(S66=TRUE,K66-M66,"") -> 7900.24 | O66: =IF($R66, IFERROR(IF((F66+L66)>0, (F66+L66-M66)/(F66+L66), ""), ""), "") -> 0.40393162 | P66: =IFERROR(__xludf.DUMMYFUNCTION("IF(AND($R66, NOT(REGEXMATCH(UPPER($C66), ""INS""))), IFERROR(IF((F66+L66)>0, (F66+L66-M66)/(F66+L66), """"), """"), """")"),0.40393161798842026) -> 0.40393162 | Q66: =IFERROR(__xludf.DUMMYFUNCTION("IF(AND($R66, REGEXMATCH(UPPER($C66), ""INS"")), IFERROR(IF((F66+L66)>0, (F66+L66-M66)/(F66+L66), """"), """"), """")"),"") | R66: TRUE | S66: TRUE | T66: TRUE | U66: In Billing | V66: TRUE | W66: =O66 -> 0.40393162 | X66: =J66 -> 19558.36 | Y66: =F66 -> 15148.55 | Z66: =L66 -> 4409.81 | AA66: =IFERROR(__xludf.DUMMYFUNCTION("""COMPUTED_VALUE"""),"") | AB66: =K66 -> 19558.36
A67: 1200 | B67: 20255066 | C67: Jamie Coy | E67: 45776 | F67: 15148.55 | G67: 45799 | H67: 45799 | I67: Drew | J67: 22448.9 | K67: 22448.9 | L67: =if(S67=TRUE,K67-F67,"") -> 7300.35 | M67: 11476.22 | N67: =if(S67=TRUE,K67-M67,"") -> 10972.68 | O67: =IF($R67, IFERROR(IF((F67+L67)>0, (F67+L67-M67)/(F67+L67), ""), ""), "") -> 0.48878475 | P67: =IFERROR(__xludf.DUMMYFUNCTION("IF(AND($R67, NOT(REGEXMATCH(UPPER($C67), ""INS""))), IFERROR(IF((F67+L67)>0, (F67+L67-M67)/(F67+L67), """"), """"), """")"),0.48878475114593595) -> 0.48878475 | Q67: =IFERROR(__xludf.DUMMYFUNCTION("IF(AND($R67, REGEXMATCH(UPPER($C67), ""INS"")), IFERROR(IF((F67+L67)>0, (F67+L67-M67)/(F67+L67), """"), """"), """")"),"") | R67: TRUE | S67: TRUE | T67: FALSE | U67: In Billing | V67: TRUE | W67: =O67 -> 0.48878475 | X67: =J67 -> 22448.9 | Y67: =F67 -> 15148.55 | Z67: =L67 -> 7300.35 | AA67: =IFERROR(__xludf.DUMMYFUNCTION("""COMPUTED_VALUE"""),"Drew") -> Drew | AB67: =K67 -> 22448.9
A68: 1327 | B68: 20255067 | C68: Craig Kauffman | E68: 45777 | F68: 13858.29 | G68: 45800 | H68: 45800 | I68: Drew | J68: 14269.74 | K68: 14269.74 | L68: =if(S68=TRUE,K68-F68,"") -> 411.45 | M68: 8938.93 | N68: =if(S68=TRUE,K68-M68,"") -> 5330.81 | O68: =IF($R68, IFERROR(IF((F68+L68)>0, (F68+L68-M68)/(F68+L68), ""), ""), "") -> 0.37357443 | P68: =IFERROR(__xludf.DUMMYFUNCTION("IF(AND($R68, NOT(REGEXMATCH(UPPER($C68), ""INS""))), IFERROR(IF((F68+L68)>0, (F68+L68-M68)/(F68+L68), """"), """"), """")"),0.3735744309286644) -> 0.37357443 | Q68: =IFERROR(__xludf.DUMMYFUNCTION("IF(AND($R68, REGEXMATCH(UPPER($C68), ""INS"")), IFERROR(IF((F68+L68)>0, (F68+L68-M68)/(F68+L68), """"), """"), """")"),"") | R68: TRUE | S68: TRUE | T68: FALSE | U68: In Billing | V68: TRUE | W68: =O68 -> 0.37357443 | X68: =J68 -> 14269.74 | Y68: =F68 -> 13858.29 | Z68: =L68 -> 411.45 | AA68: =IFERROR(__xludf.DUMMYFUNCTION("""COMPUTED_VALUE"""),"Drew") -> Drew | AB68: =K68 -> 14269.74
A69: 1273 | B69: 20255068 | C69: INS - John Martin | E69: 45778 | F69: 11209.33 | G69: 45838 | H69: 45838 | I69: James | J69: 11319.33 | K69: 11319.33 | L69: =if(S69=TRUE,K69-F69,"") -> 110 | M69: 7320.48 | N69: =if(S69=TRUE,K69-M69,"") -> 3998.85 | O69: =IF($R69, IFERROR(IF((F69+L69)>0, (F69+L69-M69)/(F69+L69), ""), ""), "") -> 0.35327621 | P69: =IFERROR(__xludf.DUMMYFUNCTION("IF(AND($R69, NOT(REGEXMATCH(UPPER($C69), ""INS""))), IFERROR(IF((F69+L69)>0, (F69+L69-M69)/(F69+L69), """"), """"), """")"),"") | Q69: =IFERROR(__xludf.DUMMYFUNCTION("IF(AND($R69, REGEXMATCH(UPPER($C69), ""INS"")), IFERROR(IF((F69+L69)>0, (F69+L69-M69)/(F69+L69), """"), """"), """")"),0.35327620981100477) -> 0.35327621 | R69: TRUE | S69: TRUE | T69: FALSE | U69: In Billing | V69: TRUE | W69: =O69 -> 0.35327621 | X69: =J69 -> 11319.33 | Y69: =F69 -> 11209.33 | Z69: =L69 -> 110 | AA69: =IFERROR(__xludf.DUMMYFUNCTION("""COMPUTED_VALUE"""),"") | AB69: =K69 -> 11319.33
A70: 1299 | B70: 20255069 | C70: INS - New Jasper Fire Station | E70: 45778 | F70: 127206.86 | G70: 10/30/2025 | H70: 10/30/2025 | I70: Drew | J70: 130000 | K70: 161246.16 | L70: =if(S70=TRUE,K70-F70,"") -> 34039.3 | M70: 60012.3 | N70: =if(S70=TRUE,K70-M70,"") -> 101233.86 | O70: =IF($R70, IFERROR(IF((F70+L70)>0, (F70+L70-M70)/(F70+L70), ""), ""), "") -> 0.62782183 | P70: =IFERROR(__xludf.DUMMYFUNCTION("IF(AND($R70, NOT(REGEXMATCH(UPPER($C70), ""INS""))), IFERROR(IF((F70+L70)>0, (F70+L70-M70)/(F70+L70), """"), """"), """")"),"") | Q70: =IFERROR(__xludf.DUMMYFUNCTION("IF(AND($R70, REGEXMATCH(UPPER($C70), ""INS"")), IFERROR(IF((F70+L70)>0, (F70+L70-M70)/(F70+L70), """"), """"), """")"),0.6278218346408994) -> 0.62782183 | R70: TRUE | S70: TRUE | T70: FALSE | U70: In Billing | V70: TRUE | W70: =O70 -> 0.62782183 | X70: =J70 -> 130000 | Y70: =F70 -> 127206.86 | Z70: =L70 -> 34039.3 | AA70: =IFERROR(__xludf.DUMMYFUNCTION("""COMPUTED_VALUE"""),"Drew") -> Drew | AB70: =K70 -> 161246.16 | AC70: 46007
A71: 1309 | B71: 20255070 | C71: INS - Roger Hamilton | E71: 45779 | F71: 22774.8 | G71: 03/09/2026 | H71: 03/09/2026 | I71: Drew | J71: 20810.96 | K71: 74205.84 | L71: =if(S71=TRUE,K71-F71,"") | M71: 28627.28 | N71: =if(S71=TRUE,K71-M71,"") | O71: =IF($R71, IFERROR(IF((F71+L71)>0, (F71+L71-M71)/(F71+L71), ""), ""), "") | P71: =IFERROR(__xludf.DUMMYFUNCTION("IF(AND($R71, NOT(REGEXMATCH(UPPER($C71), ""INS""))), IFERROR(IF((F71+L71)>0, (F71+L71-M71)/(F71+L71), """"), """"), """")"),"") | Q71: =IFERROR(__xludf.DUMMYFUNCTION("IF(AND($R71, REGEXMATCH(UPPER($C71), ""INS"")), IFERROR(IF((F71+L71)>0, (F71+L71-M71)/(F71+L71), """"), """"), """")"),"") | R71: FALSE | S71: FALSE | T71: FALSE | U71: In Billing | V71: TRUE | W71: =O71 | X71: =J71 -> 20810.96 | Y71: =F71 -> 22774.8 | Z71: =L71 | AA71: =IFERROR(__xludf.DUMMYFUNCTION("""COMPUTED_VALUE"""),"Drew") -> Drew | AB71: =K71 -> 74205.84 | AC71: 46118
A72: 1226 | B72: 20255071 | C72: Manes Addition | E72: 45779 | F72: 9641.93 | G72: 45834 | H72: 45834 | I72: Brett | J72: 9216.93 | K72: 9216.93 | L72: =if(S72=TRUE,K72-F72,"") -> -425 | M72: 5463.23 | N72: =if(S72=TRUE,K72-M72,"") -> 3753.7 | O72: =IF($R72, IFERROR(IF((F72+L72)>0, (F72+L72-M72)/(F72+L72), ""), ""), "") -> 0.40726142 | P72: =IFERROR(__xludf.DUMMYFUNCTION("IF(AND($R72, NOT(REGEXMATCH(UPPER($C72), ""INS""))), IFERROR(IF((F72+L72)>0, (F72+L72-M72)/(F72+L72), """"), """"), """")"),0.4072614200172943) -> 0.40726142 | Q72: =IFERROR(__xludf.DUMMYFUNCTION("IF(AND($R72, REGEXMATCH(UPPER($C72), ""INS"")), IFERROR(IF((F72+L72)>0, (F72+L72-M72)/(F72+L72), """"), """"), """")"),"") | R72: TRUE | S72: TRUE | T72: FALSE | U72: In Billing | V72: TRUE | W72: =O72 -> 0.40726142 | X72: =J72 -> 9216.93 | Y72: =F72 -> 9641.93 | Z72: =L72 -> -425 | AA72: =IFERROR(__xludf.DUMMYFUNCTION("""COMPUTED_VALUE"""),"") | AB72: =K72 -> 9216.93
A73: 1317 | B73: 20255072 | C73: Kathy Hartman | E73: 45782 | F73: 1987.19 | G73: 45813 | H73: 45813 | I73: Brett | J73: 1987.19 | K73: 1987.19 | L73: =if(S73=TRUE,K73-F73,"") -> 0 | M73: 827.88 | N73: =if(S73=TRUE,K73-M73,"") -> 1159.31 | O73: =IF($R73, IFERROR(IF((F73+L73)>0, (F73+L73-M73)/(F73+L73), ""), ""), "") -> 0.58339162 | P73: =IFERROR(__xludf.DUMMYFUNCTION("IF(AND($R73, NOT(REGEXMATCH(UPPER($C73), ""INS""))), IFERROR(IF((F73+L73)>0, (F73+L73-M73)/(F73+L73), """"), """"), """")"),0.5833916233475409) -> 0.58339162 | Q73: =IFERROR(__xludf.DUMMYFUNCTION("IF(AND($R73, REGEXMATCH(UPPER($C73), ""INS"")), IFERROR(IF((F73+L73)>0, (F73+L73-M73)/(F73+L73), """"), """"), """")"),"") | R73: TRUE | S73: TRUE | T73: FALSE | U73: In Billing | V73: TRUE | W73: =O73 -> 0.58339162 | X73: =J73 -> 1987.19 | Y73: =F73 -> 1987.19 | Z73: =L73 -> 0 | AA73: =IFERROR(__xludf.DUMMYFUNCTION("""COMPUTED_VALUE"""),"") | AB73: =K73 -> 1987.19
A74: 1372 | B74: 20255073 | C74: Chris Falkowski - Master Bath | E74: 45782 | F74: 11843.8 | I74: James | J74: 12273.12 | K74: 12273.12 | L74: =if(S74=TRUE,K74-F74,"") -> 429.32 | M74: 8457.71 | N74: =if(S74=TRUE,K74-M74,"") -> 3815.41 | O74: =IF($R74, IFERROR(IF((F74+L74)>0, (F74+L74-M74)/(F74+L74), ""), ""), "") -> 0.31087531 | P74: =IFERROR(__xludf.DUMMYFUNCTION("IF(AND($R74, NOT(REGEXMATCH(UPPER($C74), ""INS""))), IFERROR(IF((F74+L74)>0, (F74+L74-M74)/(F74+L74), """"), """"), """")"),0.3108753112492994) -> 0.31087531 | Q74: =IFERROR(__xludf.DUMMYFUNCTION("IF(AND($R74, REGEXMATCH(UPPER($C74), ""INS"")), IFERROR(IF((F74+L74)>0, (F74+L74-M74)/(F74+L74), """"), """"), """")"),"") | R74: TRUE | S74: TRUE | T74: FALSE | U74: In Billing | V74: TRUE | W74: =O74 -> 0.31087531 | X74: =J74 -> 12273.12 | Y74: =F74 -> 11843.8 | Z74: =L74 -> 429.32 | AA74: =IFERROR(__xludf.DUMMYFUNCTION("""COMPUTED_VALUE"""),"") | AB74: =K74 -> 12273.12
A75: 1411 | B75: 20255074 | C75: Mike White | E75: 45782 | F75: 1224 | G75: 45820 | H75: 45820 | I75: Geoff | J75: 1224 | K75: 1224 | L75: =if(S75=TRUE,K75-F75,"") -> 0 | M75: 555.65 | N75: =if(S75=TRUE,K75-M75,"") -> 668.35 | O75: =IF($R75, IFERROR(IF((F75+L75)>0, (F75+L75-M75)/(F75+L75), ""), ""), "") -> 0.54603758 | P75: =IFERROR(__xludf.DUMMYFUNCTION("IF(AND($R75, NOT(REGEXMATCH(UPPER($C75), ""INS""))), IFERROR(IF((F75+L75)>0, (F75+L75-M75)/(F75+L75), """"), """"), """")"),0.5460375816993465) -> 0.54603758 | Q75: =IFERROR(__xludf.DUMMYFUNCTION("IF(AND($R75, REGEXMATCH(UPPER($C75), ""INS"")), IFERROR(IF((F75+L75)>0, (F75+L75-M75)/(F75+L75), """"), """"), """")"),"") | R75: TRUE | S75: TRUE | T75: FALSE | U75: In Billing | V75: TRUE | W75: =O75 -> 0.54603758 | X75: =J75 -> 1224 | Y75: =F75 -> 1224 | Z75: =L75 -> 0 | AA75: =IFERROR(__xludf.DUMMYFUNCTION("""COMPUTED_VALUE"""),"") | AB75: =K75 -> 1224
A76: 1211 | B76: 20255075 | C76: INS - Sovereign Grace | E76: 45783 | F76: 100030.28 | G76: 45904 | H76: 45904 | I76: Chris | J76: 100030.28 | K76: 101456.48 | L76: =if(S76=TRUE,K76-F76,"") -> 1426.2 | M76: 39864.25 | N76: =if(S76=TRUE,K76-M76,"") -> 61592.23 | O76: =IF($R76, IFERROR(IF((F76+L76)>0, (F76+L76-M76)/(F76+L76), ""), ""), "") -> 0.6070803 | P76: =IFERROR(__xludf.DUMMYFUNCTION("IF(AND($R76, NOT(REGEXMATCH(UPPER($C76), ""INS""))), IFERROR(IF((F76+L76)>0, (F76+L76-M76)/(F76+L76), """"), """"), """")"),"") | Q76: =IFERROR(__xludf.DUMMYFUNCTION("IF(AND($R76, REGEXMATCH(UPPER($C76), ""INS"")), IFERROR(IF((F76+L76)>0, (F76+L76-M76)/(F76+L76), """"), """"), """")"),0.6070802968918299) -> 0.6070803 | R76: TRUE | S76: TRUE | T76: TRUE | U76: In Billing | V76: TRUE | W76: =O76 -> 0.6070803 | X76: =J76 -> 100030.28 | Y76: =F76 -> 100030.28 | Z76: =L76 -> 1426.2 | AA76: =IFERROR(__xludf.DUMMYFUNCTION("""COMPUTED_VALUE"""),"") | AB76: =K76 -> 101456.48 | AC76: 46028
A77: 1268 | B77: 20255076 | C77: Susan Gayle | E77: 45783.508 | F77: 23722.25 | I77: Adam | J77: 24966.25 | K77: 24966.25 | L77: =if(S77=TRUE,K77-F77,"") -> 1244 | M77: 15271.38 | N77: =if(S77=TRUE,K77-M77,"") -> 9694.87 | O77: =IF($R77, IFERROR(IF((F77+L77)>0, (F77+L77-M77)/(F77+L77), ""), ""), "") -> 0.38831903 | P77: =IFERROR(__xludf.DUMMYFUNCTION("IF(AND($R77, NOT(REGEXMATCH(UPPER($C77), ""INS""))), IFERROR(IF((F77+L77)>0, (F77+L77-M77)/(F77+L77), """"), """"), """")"),0.3883190306914335) -> 0.38831903 | Q77: =IFERROR(__xludf.DUMMYFUNCTION("IF(AND($R77, REGEXMATCH(UPPER($C77), ""INS"")), IFERROR(IF((F77+L77)>0, (F77+L77-M77)/(F77+L77), """"), """"), """")"),"") | R77: TRUE | S77: TRUE | T77: TRUE | U77: In Billing | V77: TRUE | W77: =O77 -> 0.38831903 | X77: =J77 -> 24966.25 | Y77: =F77 -> 23722.25 | Z77: =L77 -> 1244 | AA77: =IFERROR(__xludf.DUMMYFUNCTION("""COMPUTED_VALUE"""),"") | AB77: =K77 -> 24966.25
A78: 1402 | B78: 20255077 | C78: Stacey Kinnison | E78: 45783 | F78: 13030.3 | G78: 45820 | H78: 45820 | I78: James | J78: 14525.49 | K78: 14525.49 | L78: =if(S78=TRUE,K78-F78,"") -> 1495.19 | M78: 8991.64 | N78: =if(S78=TRUE,K78-M78,"") -> 5533.85 | O78: =IF($R78, IFERROR(IF((F78+L78)>0, (F78+L78-M78)/(F78+L78), ""), ""), "") -> 0.3809751 | P78: =IFERROR(__xludf.DUMMYFUNCTION("IF(AND($R78, NOT(REGEXMATCH(UPPER($C78), ""INS""))), IFERROR(IF((F78+L78)>0, (F78+L78-M78)/(F78+L78), """"), """"), """")"),0.38097509963519305) -> 0.3809751 | Q78: =IFERROR(__xludf.DUMMYFUNCTION("IF(AND($R78, REGEXMATCH(UPPER($C78), ""INS"")), IFERROR(IF((F78+L78)>0, (F78+L78-M78)/(F78+L78), """"), """"), """")"),"") | R78: TRUE | S78: TRUE | T78: FALSE | U78: In Billing | V78: TRUE | W78: =O78 -> 0.3809751 | X78: =J78 -> 14525.49 | Y78: =F78 -> 13030.3 | Z78: =L78 -> 1495.19 | AA78: =IFERROR(__xludf.DUMMYFUNCTION("""COMPUTED_VALUE"""),"") | AB78: =K78 -> 14525.49
A79: 1415 | B79: 20255078 | C79: Ashley Deloatch | E79: 45783 | F79: 0 | G79: 45803 | H79: 45803 | I79: Drew | L79: =if(S79=TRUE,K79-F79,"") -> 0 | N79: =if(S79=TRUE,K79-M79,"") -> 0 | O79: =IF($R79, IFERROR(IF((F79+L79)>0, (F79+L79-M79)/(F79+L79), ""), ""), "") | P79: =IFERROR(__xludf.DUMMYFUNCTION("IF(AND($R79, NOT(REGEXMATCH(UPPER($C79), ""INS""))), IFERROR(IF((F79+L79)>0, (F79+L79-M79)/(F79+L79), """"), """"), """")"),"") | Q79: =IFERROR(__xludf.DUMMYFUNCTION("IF(AND($R79, REGEXMATCH(UPPER($C79), ""INS"")), IFERROR(IF((F79+L79)>0, (F79+L79-M79)/(F79+L79), """"), """"), """")"),"") | R79: TRUE | S79: TRUE | T79: FALSE | U79: In Billing | V79: TRUE | W79: =O79 | X79: =J79 | Y79: =F79 -> 0 | Z79: =L79 -> 0 | AA79: =IFERROR(__xludf.DUMMYFUNCTION("""COMPUTED_VALUE"""),"Drew") -> Drew | AB79: =K79
A80: 1345 | B80: 20255079 | C80: Heather Kennedy | E80: 45784 | F80: 2680 | G80: 45827 | H80: 45827 | I80: Chris | J80: 2680 | K80: 2680 | L80: =if(S80=TRUE,K80-F80,"") -> 0 | M80: 1360 | N80: =if(S80=TRUE,K80-M80,"") -> 1320 | O80: =IF($R80, IFERROR(IF((F80+L80)>0, (F80+L80-M80)/(F80+L80), ""), ""), "") -> 0.49253731 | P80: =IFERROR(__xludf.DUMMYFUNCTION("IF(AND($R80, NOT(REGEXMATCH(UPPER($C80), ""INS""))), IFERROR(IF((F80+L80)>0, (F80+L80-M80)/(F80+L80), """"), """"), """")"),0.4925373134328358) -> 0.49253731 | Q80: =IFERROR(__xludf.DUMMYFUNCTION("IF(AND($R80, REGEXMATCH(UPPER($C80), ""INS"")), IFERROR(IF((F80+L80)>0, (F80+L80-M80)/(F80+L80), """"), """"), """")"),"") | R80: TRUE | S80: TRUE | T80: TRUE | U80: In Billing | V80: TRUE | W80: =O80 -> 0.49253731 | X80: =J80 -> 2680 | Y80: =F80 -> 2680 | Z80: =L80 -> 0 | AA80: =IFERROR(__xludf.DUMMYFUNCTION("""COMPUTED_VALUE"""),"") | AB80: =K80 -> 2680
A81: 1418 | B81: 20255080 | C81: Kyle Piepmeyer | E81: 45784 | F81: 14422.18 | I81: Brett | J81: 15892.18 | K81: 15892.18 | L81: =if(S81=TRUE,K81-F81,"") -> 1470 | M81: 9482.21 | N81: =if(S81=TRUE,K81-M81,"") -> 6409.97 | O81: =IF($R81, IFERROR(IF((F81+L81)>0, (F81+L81-M81)/(F81+L81), ""), ""), "") -> 0.40334114 | P81: =IFERROR(__xludf.DUMMYFUNCTION("IF(AND($R81, NOT(REGEXMATCH(UPPER($C81), ""INS""))), IFERROR(IF((F81+L81)>0, (F81+L81-M81)/(F81+L81), """"), """"), """")"),0.4033411401079022) -> 0.40334114 | Q81: =IFERROR(__xludf.DUMMYFUNCTION("IF(AND($R81, REGEXMATCH(UPPER($C81), ""INS"")), IFERROR(IF((F81+L81)>0, (F81+L81-M81)/(F81+L81), """"), """"), """")"),"") | R81: TRUE | S81: TRUE | T81: FALSE | U81: In Billing | V81: TRUE | W81: =O81 -> 0.40334114 | X81: =J81 -> 15892.18 | Y81: =F81 -> 14422.18 | Z81: =L81 -> 1470 | AA81: =IFERROR(__xludf.DUMMYFUNCTION("""COMPUTED_VALUE"""),"") | AB81: =K81 -> 15892.18
A82: 1428 | B82: 20255081 | C82: Cindy Eubanks | E82: 45784 | F82: 23168.82 | G82: 45820 | H82: 45820 | I82: Brett | J82: 23608.82 | K82: 23608.82 | L82: =if(S82=TRUE,K82-F82,"") -> 440 | M82: 13442.81 | N82: =if(S82=TRUE,K82-M82,"") -> 10166.01 | O82: =IF($R82, IFERROR(IF((F82+L82)>0, (F82+L82-M82)/(F82+L82), ""), ""), "") -> 0.43060221 | P82: =IFERROR(__xludf.DUMMYFUNCTION("IF(AND($R82, NOT(REGEXMATCH(UPPER($C82), ""INS""))), IFERROR(IF((F82+L82)>0, (F82+L82-M82)/(F82+L82), """"), """"), """")"),0.43060220714122943) -> 0.43060221 | Q82: =IFERROR(__xludf.DUMMYFUNCTION("IF(AND($R82, REGEXMATCH(UPPER($C82), ""INS"")), IFERROR(IF((F82+L82)>0, (F82+L82-M82)/(F82+L82), """"), """"), """")"),"") | R82: TRUE | S82: TRUE | T82: FALSE | U82: In Billing | V82: TRUE | W82: =O82 -> 0.43060221 | X82: =J82 -> 23608.82 | Y82: =F82 -> 23168.82 | Z82: =L82 -> 440 | AA82: =IFERROR(__xludf.DUMMYFUNCTION("""COMPUTED_VALUE"""),"") | AB82: =K82 -> 23608.82
A83: 1266 | B83: 20255082 | C83: Chris Kelly | E83: 45785 | F83: 34900 | G83: 45918 | H83: 45918 | I83: James | J83: 40439.69 | K83: 40339.69 | L83: =if(S83=TRUE,K83-F83,"") -> 5439.69 | M83: 25098.68 | N83: =if(S83=TRUE,K83-M83,"") -> 15241.01 | O83: =IF($R83, IFERROR(IF((F83+L83)>0, (F83+L83-M83)/(F83+L83), ""), ""), "") -> 0.37781674 | P83: =IFERROR(__xludf.DUMMYFUNCTION("IF(AND($R83, NOT(REGEXMATCH(UPPER($C83), ""INS""))), IFERROR(IF((F83+L83)>0, (F83+L83-M83)/(F83+L83), """"), """"), """")"),0.3778167358251886) -> 0.37781674 | Q83: =IFERROR(__xludf.DUMMYFUNCTION("IF(AND($R83, REGEXMATCH(UPPER($C83), ""INS"")), IFERROR(IF((F83+L83)>0, (F83+L83-M83)/(F83+L83), """"), """"), """")"),"") | R83: TRUE | S83: TRUE | T83: TRUE | U83: In Billing | V83: TRUE | W83: =O83 -> 0.37781674 | X83: =J83 -> 40439.69 | Y83: =F83 -> 34900 | Z83: =L83 -> 5439.69 | AA83: =IFERROR(__xludf.DUMMYFUNCTION("""COMPUTED_VALUE"""),"") | AB83: =K83 -> 40339.69
A84: 1398 | B84: 20255083 | C84: Eric Whitney | E84: 45785 | F84: 2567.11 | G84: 45820 | H84: 45820 | I84: Geoff | J84: 2567.11 | K84: 2567.11 | L84: =if(S84=TRUE,K84-F84,"") -> 0 | M84: 1084.93 | N84: =if(S84=TRUE,K84-M84,"") -> 1482.18 | O84: =IF($R84, IFERROR(IF((F84+L84)>0, (F84+L84-M84)/(F84+L84), ""), ""), "") -> 0.577373 | P84: =IFERROR(__xludf.DUMMYFUNCTION("IF(AND($R84, NOT(REGEXMATCH(UPPER($C84), ""INS""))), IFERROR(IF((F84+L84)>0, (F84+L84-M84)/(F84+L84), """"), """"), """")"),0.5773729992092275) -> 0.577373 | Q84: =IFERROR(__xludf.DUMMYFUNCTION("IF(AND($R84, REGEXMATCH(UPPER($C84), ""INS"")), IFERROR(IF((F84+L84)>0, (F84+L84-M84)/(F84+L84), """"), """"), """")"),"") | R84: TRUE | S84: TRUE | T84: FALSE | U84: In Billing | V84: TRUE | W84: =O84 -> 0.577373 | X84: =J84 -> 2567.11 | Y84: =F84 -> 2567.11 | Z84: =L84 -> 0 | AA84: =IFERROR(__xludf.DUMMYFUNCTION("""COMPUTED_VALUE"""),"") | AB84: =K84 -> 2567.11
A85: 1300 | B85: 20255084 | C85: INS - Ben Shideler | E85: 45787 | F85: 3620.29 | I85: Drew | J85: 826.92 | K85: 826.92 | L85: =if(S85=TRUE,K85-F85,"") | N85: =if(S85=TRUE,K85-M85,"") | O85: =IF($R85, IFERROR(IF((F85+L85)>0, (F85+L85-M85)/(F85+L85), ""), ""), "") -> 1 | P85: =IFERROR(__xludf.DUMMYFUNCTION("IF(AND($R85, NOT(REGEXMATCH(UPPER($C85), ""INS""))), IFERROR(IF((F85+L85)>0, (F85+L85-M85)/(F85+L85), """"), """"), """")"),"") | Q85: =IFERROR(__xludf.DUMMYFUNCTION("IF(AND($R85, REGEXMATCH(UPPER($C85), ""INS"")), IFERROR(IF((F85+L85)>0, (F85+L85-M85)/(F85+L85), """"), """"), """")"),1.0) -> 1 | R85: TRUE | S85: FALSE | T85: FALSE | U85: Pending Insurance Approval | V85: TRUE | W85: =O85 -> 1 | X85: =J85 -> 826.92 | Y85: =F85 -> 3620.29 | Z85: =L85 | AA85: =IFERROR(__xludf.DUMMYFUNCTION("""COMPUTED_VALUE"""),"Drew") -> Drew | AB85: =K85 -> 826.92 | AC85: 46035
A86: 1311 | B86: 20255085 | C86: Caroline Mantkowski | E86: 45788 | F86: 4029.31 | G86: 45827 | H86: 45827 | I86: Brett | J86: 4029.31 | K86: 4029.31 | L86: =if(S86=TRUE,K86-F86,"") -> 0 | M86: 723.24 | N86: =if(S86=TRUE,K86-M86,"") -> 3306.07 | O86: =IF($R86, IFERROR(IF((F86+L86)>0, (F86+L86-M86)/(F86+L86), ""), ""), "") -> 0.82050525 | P86: =IFERROR(__xludf.DUMMYFUNCTION("IF(AND($R86, NOT(REGEXMATCH(UPPER($C86), ""INS""))), IFERROR(IF((F86+L86)>0, (F86+L86-M86)/(F86+L86), """"), """"), """")"),0.8205052477967691) -> 0.82050525 | Q86: =IFERROR(__xludf.DUMMYFUNCTION("IF(AND($R86, REGEXMATCH(UPPER($C86), ""INS"")), IFERROR(IF((F86+L86)>0, (F86+L86-M86)/(F86+L86), """"), """"), """")"),"") | R86: TRUE | S86: TRUE | T86: FALSE | U86: In Billing | V86: TRUE | W86: =O86 -> 0.82050525 | X86: =J86 -> 4029.31 | Y86: =F86 -> 4029.31 | Z86: =L86 -> 0 | AA86: =IFERROR(__xludf.DUMMYFUNCTION("""COMPUTED_VALUE"""),"") | AB86: =K86 -> 4029.31
A87: 1455 | B87: 20255086 | C87: Joanne Stocksdale | E87: 45790 | F87: 15954.68 | G87: 45820 | H87: 45820 | I87: James | J87: 16064.68 | K87: 16064.68 | L87: =if(S87=TRUE,K87-F87,"") -> 110 | M87: 9856.95 | N87: =if(S87=TRUE,K87-M87,"") -> 6207.73 | O87: =IF($R87, IFERROR(IF((F87+L87)>0, (F87+L87-M87)/(F87+L87), ""), ""), "") -> 0.38642102 | P87: =IFERROR(__xludf.DUMMYFUNCTION("IF(AND($R87, NOT(REGEXMATCH(UPPER($C87), ""INS""))), IFERROR(IF((F87+L87)>0, (F87+L87-M87)/(F87+L87), """"), """"), """")"),0.3864210180345951) -> 0.38642102 | Q87: =IFERROR(__xludf.DUMMYFUNCTION("IF(AND($R87, REGEXMATCH(UPPER($C87), ""INS"")), IFERROR(IF((F87+L87)>0, (F87+L87-M87)/(F87+L87), """"), """"), """")"),"") | R87: TRUE | S87: TRUE | T87: FALSE | U87: In Billing | V87: TRUE | W87: =O87 -> 0.38642102 | X87: =J87 -> 16064.68 | Y87: =F87 -> 15954.68 | Z87: =L87 -> 110 | AA87: =IFERROR(__xludf.DUMMYFUNCTION("""COMPUTED_VALUE"""),"") | AB87: =K87 -> 16064.68
A88: 1399 | B88: 20255087 | C88: INS - Carol Morgan (Beth Lainhart) | E88: 45791 | F88: 14514.38 | G88: 01/08/2026 | H88: 01/08/2026 | I88: Brett | J88: 7510.2 | K88: 7510.2 | L88: =if(S88=TRUE,K88-F88,"") | M88: 5846.9 | N88: =if(S88=TRUE,K88-M88,"") | O88: =IF($R88, IFERROR(IF((F88+L88)>0, (F88+L88-M88)/(F88+L88), ""), ""), "") -> 0.59716502 | P88: =IFERROR(__xludf.DUMMYFUNCTION("IF(AND($R88, NOT(REGEXMATCH(UPPER($C88), ""INS""))), IFERROR(IF((F88+L88)>0, (F88+L88-M88)/(F88+L88), """"), """"), """")"),"") | Q88: =IFERROR(__xludf.DUMMYFUNCTION("IF(AND($R88, REGEXMATCH(UPPER($C88), ""INS"")), IFERROR(IF((F88+L88)>0, (F88+L88-M88)/(F88+L88), """"), """"), """")"),0.597165018416219) -> 0.59716502 | R88: TRUE | S88: FALSE | T88: FALSE | U88: Job Scheduled | V88: FALSE | W88: =O88 -> 0.59716502 | X88: =J88 -> 7510.2 | Y88: =F88 -> 14514.38 | Z88: =L88 | AA88: =IFERROR(__xludf.DUMMYFUNCTION("""COMPUTED_VALUE"""),"") | AB88: =K88 -> 7510.2 | AC88: 46062
A89: 1436 | B89: 20255088 | C89: Bruce Stapleton | E89: 45793 | F89: 1450.2 | G89: 45827 | H89: 45827 | I89: Geoff | J89: 1450.2 | K89: 1450.2 | L89: =if(S89=TRUE,K89-F89,"") -> 0 | M89: 490.17 | N89: =if(S89=TRUE,K89-M89,"") -> 960.03 | O89: =IF($R89, IFERROR(IF((F89+L89)>0, (F89+L89-M89)/(F89+L89), ""), ""), "") -> 0.66199835 | P89: =IFERROR(__xludf.DUMMYFUNCTION("IF(AND($R89, NOT(REGEXMATCH(UPPER($C89), ""INS""))), IFERROR(IF((F89+L89)>0, (F89+L89-M89)/(F89+L89), """"), """"), """")"),0.6619983450558543) -> 0.66199835 | Q89: =IFERROR(__xludf.DUMMYFUNCTION("IF(AND($R89, REGEXMATCH(UPPER($C89), ""INS"")), IFERROR(IF((F89+L89)>0, (F89+L89-M89)/(F89+L89), """"), """"), """")"),"") | R89: TRUE | S89: TRUE | T89: FALSE | U89: In Billing | V89: TRUE | W89: =O89 -> 0.66199835 | X89: =J89 -> 1450.2 | Y89: =F89 -> 1450.2 | Z89: =L89 -> 0 | AA89: =IFERROR(__xludf.DUMMYFUNCTION("""COMPUTED_VALUE"""),"") | AB89: =K89 -> 1450.2
A90: 1477 | B90: 20255089 | C90: Codi Santos | E90: 45796 | F90: 1551.96 | G90: 45827 | H90: 45827 | I90: Drew | J90: 1551.96 | K90: 1551.96 | L90: =if(S90=TRUE,K90-F90,"") -> 0 | M90: 556 | N90: =if(S90=TRUE,K90-M90,"") -> 995.96 | O90: =IF($R90, IFERROR(IF((F90+L90)>0, (F90+L90-M90)/(F90+L90), ""), ""), "") -> 0.64174334 | P90: =IFERROR(__xludf.DUMMYFUNCTION("IF(AND($R90, NOT(REGEXMATCH(UPPER($C90), ""INS""))), IFERROR(IF((F90+L90)>0, (F90+L90-M90)/(F90+L90), """"), """"), """")"),0.641743343900616) -> 0.64174334 | Q90: =IFERROR(__xludf.DUMMYFUNCTION("IF(AND($R90, REGEXMATCH(UPPER($C90), ""INS"")), IFERROR(IF((F90+L90)>0, (F90+L90-M90)/(F90+L90), """"), """"), """")"),"") | R90: TRUE | S90: TRUE | T90: FALSE | U90: In Billing | V90: TRUE | W90: =O90 -> 0.64174334 | X90: =J90 -> 1551.96 | Y90: =F90 -> 1551.96 | Z90: =L90 -> 0 | AA90: =IFERROR(__xludf.DUMMYFUNCTION("""COMPUTED_VALUE"""),"Drew") -> Drew | AB90: =K90 -> 1551.96
A91: 1470 | B91: 20255090 | C91: Scott Earhart | E91: 45796 | F91: 11544.97 | G91: 45834 | H91: 45834 | I91: James | J91: 11544.97 | K91: 11544.97 | L91: =if(S91=TRUE,K91-F91,"") -> 0 | M91: 5313.68 | N91: =if(S91=TRUE,K91-M91,"") -> 6231.29 | O91: =IF($R91, IFERROR(IF((F91+L91)>0, (F91+L91-M91)/(F91+L91), ""), ""), "") -> 0.53974068 | P91: =IFERROR(__xludf.DUMMYFUNCTION("IF(AND($R91, NOT(REGEXMATCH(UPPER($C91), ""INS""))), IFERROR(IF((F91+L91)>0, (F91+L91-M91)/(F91+L91), """"), """"), """")"),0.5397406836050678) -> 0.53974068 | Q91: =IFERROR(__xludf.DUMMYFUNCTION("IF(AND($R91, REGEXMATCH(UPPER($C91), ""INS"")), IFERROR(IF((F91+L91)>0, (F91+L91-M91)/(F91+L91), """"), """"), """")"),"") | R91: TRUE | S91: TRUE | T91: FALSE | U91: In Billing | V91: TRUE | W91: =O91 -> 0.53974068 | X91: =J91 -> 11544.97 | Y91: =F91 -> 11544.97 | Z91: =L91 -> 0 | AA91: =IFERROR(__xludf.DUMMYFUNCTION("""COMPUTED_VALUE"""),"") | AB91: =K91 -> 11544.97
A92: 1480 | B92: 20255091 | C92: Pete Avnaim | E92: 45797 | F92: 0 | G92: 45817 | H92: 45817 | I92: Geoff | L92: =if(S92=TRUE,K92-F92,"") -> 0 | N92: =if(S92=TRUE,K92-M92,"") -> 0 | O92: =IF($R92, IFERROR(IF((F92+L92)>0, (F92+L92-M92)/(F92+L92), ""), ""), "") | P92: =IFERROR(__xludf.DUMMYFUNCTION("IF(AND($R92, NOT(REGEXMATCH(UPPER($C92), ""INS""))), IFERROR(IF((F92+L92)>0, (F92+L92-M92)/(F92+L92), """"), """"), """")"),"") | Q92: =IFERROR(__xludf.DUMMYFUNCTION("IF(AND($R92, REGEXMATCH(UPPER($C92), ""INS"")), IFERROR(IF((F92+L92)>0, (F92+L92-M92)/(F92+L92), """"), """"), """")"),"") | R92: TRUE | S92: TRUE | T92: FALSE | U92: In Billing | V92: TRUE | W92: =O92 | X92: =J92 | Y92: =F92 -> 0 | Z92: =L92 -> 0 | AA92: =IFERROR(__xludf.DUMMYFUNCTION("""COMPUTED_VALUE"""),"") | AB92: =K92
A93: 1288 | B93: 20255092 | C93: INS - Pete Battaglia | E93: 45797 | F93: 81583.85 | G93: 04/14/2026 | H93: 04/15/2026 | I93: Chris | J93: 66990.88 | K93: 66990.88 | L93: =if(S93=TRUE,K93-F93,"") | N93: =if(S93=TRUE,K93-M93,"") | O93: =IF($R93, IFERROR(IF((F93+L93)>0, (F93+L93-M93)/(F93+L93), ""), ""), "") | P93: =IFERROR(__xludf.DUMMYFUNCTION("IF(AND($R93, NOT(REGEXMATCH(UPPER($C93), ""INS""))), IFERROR(IF((F93+L93)>0, (F93+L93-M93)/(F93+L93), """"), """"), """")"),"") | Q93: =IFERROR(__xludf.DUMMYFUNCTION("IF(AND($R93, REGEXMATCH(UPPER($C93), ""INS"")), IFERROR(IF((F93+L93)>0, (F93+L93-M93)/(F93+L93), """"), """"), """")"),"") | R93: FALSE | S93: FALSE | T93: TRUE | U93: Job Scheduled | V93: FALSE | W93: =O93 | X93: =J93 -> 66990.88 | Y93: =F93 -> 81583.85 | Z93: =L93 | AA93: =IFERROR(__xludf.DUMMYFUNCTION("""COMPUTED_VALUE"""),"") | AB93: =K93 -> 66990.88
A94: 1177 | B94: 20255093 | C94: Level MB - The Maxwell | E94: 45799 | F94: 19549.51 | G94: 45862 | H94: 45862 | I94: Brett | J94: 21734.51 | K94: 21734.51 | L94: =if(S94=TRUE,K94-F94,"") -> 2185 | M94: 12954.74 | N94: =if(S94=TRUE,K94-M94,"") -> 8779.77 | O94: =IF($R94, IFERROR(IF((F94+L94)>0, (F94+L94-M94)/(F94+L94), ""), ""), "") -> 0.40395528 | P94: =IFERROR(__xludf.DUMMYFUNCTION("IF(AND($R94, NOT(REGEXMATCH(UPPER($C94), ""INS""))), IFERROR(IF((F94+L94)>0, (F94+L94-M94)/(F94+L94), """"), """"), """")"),0.4039552766545001) -> 0.40395528 | Q94: =IFERROR(__xludf.DUMMYFUNCTION("IF(AND($R94, REGEXMATCH(UPPER($C94), ""INS"")), IFERROR(IF((F94+L94)>0, (F94+L94-M94)/(F94+L94), """"), """"), """")"),"") | R94: TRUE | S94: TRUE | T94: FALSE | U94: In Billing | V94: TRUE | W94: =O94 -> 0.40395528 | X94: =J94 -> 21734.51 | Y94: =F94 -> 19549.51 | Z94: =L94 -> 2185 | AA94: =IFERROR(__xludf.DUMMYFUNCTION("""COMPUTED_VALUE"""),"") | AB94: =K94 -> 21734.51
A95: 1308 | B95: 20255094 | C95: INS - James (Andy) Dean | E95: 45798 | F95: 45878.52 | G95: 01/15/2026 | H95: 01/15/2026 | I95: Drew | J95: 82334.51 | K95: 94483.35 | L95: =if(S95=TRUE,K95-F95,"") -> 48604.83 | M95: 40849.18 | N95: =if(S95=TRUE,K95-M95,"") -> 53634.17 | O95: =IF($R95, IFERROR(IF((F95+L95)>0, (F95+L95-M95)/(F95+L95), ""), ""), "") -> 0.56765737 | P95: =IFERROR(__xludf.DUMMYFUNCTION("IF(AND($R95, NOT(REGEXMATCH(UPPER($C95), ""INS""))), IFERROR(IF((F95+L95)>0, (F95+L95-M95)/(F95+L95), """"), """"), """")"),"") | Q95: =IFERROR(__xludf.DUMMYFUNCTION("IF(AND($R95, REGEXMATCH(UPPER($C95), ""INS"")), IFERROR(IF((F95+L95)>0, (F95+L95-M95)/(F95+L95), """"), """"), """")"),0.5676573703197442) -> 0.56765737 | R95: TRUE | S95: TRUE | T95: FALSE | U95: In Billing | V95: TRUE | W95: =O95 -> 0.56765737 | X95: =J95 -> 82334.51 | Y95: =F95 -> 45878.52 | Z95: =L95 -> 48604.83 | AA95: =IFERROR(__xludf.DUMMYFUNCTION("""COMPUTED_VALUE"""),"Drew") -> Drew | AB95: =K95 -> 94483.35 | AC95: 46064.441
A96: 1491 | B96: 20255095 | C96: Carlene McNamara | E96: 45800 | F96: 862.79 | G96: 45827 | H96: 45827 | I96: James | J96: 862.79 | K96: 862.79 | L96: =if(S96=TRUE,K96-F96,"") -> 0 | M96: 370.85 | N96: =if(S96=TRUE,K96-M96,"") -> 491.94 | O96: =IF($R96, IFERROR(IF((F96+L96)>0, (F96+L96-M96)/(F96+L96), ""), ""), "") -> 0.57017351 | P96: =IFERROR(__xludf.DUMMYFUNCTION("IF(AND($R96, NOT(REGEXMATCH(UPPER($C96), ""INS""))), IFERROR(IF((F96+L96)>0, (F96+L96-M96)/(F96+L96), """"), """"), """")"),0.5701735068788465) -> 0.57017351 | Q96: =IFERROR(__xludf.DUMMYFUNCTION("IF(AND($R96, REGEXMATCH(UPPER($C96), ""INS"")), IFERROR(IF((F96+L96)>0, (F96+L96-M96)/(F96+L96), """"), """"), """")"),"") | R96: TRUE | S96: TRUE | T96: FALSE | U96: In Billing | V96: TRUE | W96: =O96 -> 0.57017351 | X96: =J96 -> 862.79 | Y96: =F96 -> 862.79 | Z96: =L96 -> 0 | AA96: =IFERROR(__xludf.DUMMYFUNCTION("""COMPUTED_VALUE"""),"") | AB96: =K96 -> 862.79 | AC96: 46079
A97: 1502 | B97: 20255096 | C97: Keith Smart | E97: 45805 | F97: 1275.59 | G97: 45841 | H97: 45841 | I97: Drew | J97: 1275.59 | K97: 1275.59 | L97: =if(S97=TRUE,K97-F97,"") -> 0 | M97: 310.02 | N97: =if(S97=TRUE,K97-M97,"") -> 965.57 | O97: =IF($R97, IFERROR(IF((F97+L97)>0, (F97+L97-M97)/(F97+L97), ""), ""), "") -> 0.75695952 | P97: =IFERROR(__xludf.DUMMYFUNCTION("IF(AND($R97, NOT(REGEXMATCH(UPPER($C97), ""INS""))), IFERROR(IF((F97+L97)>0, (F97+L97-M97)/(F97+L97), """"), """"), """")"),0.7569595246121402) -> 0.75695952 | Q97: =IFERROR(__xludf.DUMMYFUNCTION("IF(AND($R97, REGEXMATCH(UPPER($C97), ""INS"")), IFERROR(IF((F97+L97)>0, (F97+L97-M97)/(F97+L97), """"), """"), """")"),"") | R97: TRUE | S97: TRUE | T97: FALSE | U97: In Billing | V97: TRUE | W97: =O97 -> 0.75695952 | X97: =J97 -> 1275.59 | Y97: =F97 -> 1275.59 | Z97: =L97 -> 0 | AA97: =IFERROR(__xludf.DUMMYFUNCTION("""COMPUTED_VALUE"""),"Drew") -> Drew | AB97: =K97 -> 1275.59
A98: 1251 | B98: 20255097 | C98: Brian Moore | E98: 45806 | F98: 21691.79 | G98: 45883 | H98: 45883 | I98: Drew | J98: 20795.98 | K98: 20795.98 | L98: =if(S98=TRUE,K98-F98,"") -> -895.81 | M98: 12245.58 | N98: =if(S98=TRUE,K98-M98,"") -> 8550.4 | O98: =IF($R98, IFERROR(IF((F98+L98)>0, (F98+L98-M98)/(F98+L98), ""), ""), "") -> 0.41115639 | P98: =IFERROR(__xludf.DUMMYFUNCTION("IF(AND($R98, NOT(REGEXMATCH(UPPER($C98), ""INS""))), IFERROR(IF((F98+L98)>0, (F98+L98-M98)/(F98+L98), """"), """"), """")"),0.41115638695555595) -> 0.41115639 | Q98: =IFERROR(__xludf.DUMMYFUNCTION("IF(AND($R98, REGEXMATCH(UPPER($C98), ""INS"")), IFERROR(IF((F98+L98)>0, (F98+L98-M98)/(F98+L98), """"), """"), """")"),"") | R98: TRUE | S98: TRUE | T98: TRUE | U98: In Billing | V98: TRUE | W98: =O98 -> 0.41115639 | X98: =J98 -> 20795.98 | Y98: =F98 -> 21691.79 | Z98: =L98 -> -895.81 | AA98: =IFERROR(__xludf.DUMMYFUNCTION("""COMPUTED_VALUE"""),"Drew") -> Drew | AB98: =K98 -> 20795.98
A99: 1512 | B99: 20255098 | C99: Maria Beimly | E99: 45806 | F99: 10001.48 | G99: 45862 | H99: 45862 | I99: Drew | J99: 10221.48 | K99: 10221.48 | L99: =if(S99=TRUE,K99-F99,"") -> 220 | M99: 5293.43 | N99: =if(S99=TRUE,K99-M99,"") -> 4928.05 | O99: =IF($R99, IFERROR(IF((F99+L99)>0, (F99+L99-M99)/(F99+L99), ""), ""), "") -> 0.48212685 | P99: =IFERROR(__xludf.DUMMYFUNCTION("IF(AND($R99, NOT(REGEXMATCH(UPPER($C99), ""INS""))), IFERROR(IF((F99+L99)>0, (F99+L99-M99)/(F99+L99), """"), """"), """")"),0.4821268544281258) -> 0.48212685 | Q99: =IFERROR(__xludf.DUMMYFUNCTION("IF(AND($R99, REGEXMATCH(UPPER($C99), ""INS"")), IFERROR(IF((F99+L99)>0, (F99+L99-M99)/(F99+L99), """"), """"), """")"),"") | R99: TRUE | S99: TRUE | T99: FALSE | U99: In Billing | V99: TRUE | W99: =O99 -> 0.48212685 | X99: =J99 -> 10221.48 | Y99: =F99 -> 10001.48 | Z99: =L99 -> 220 | AA99: =IFERROR(__xludf.DUMMYFUNCTION("""COMPUTED_VALUE"""),"Drew") -> Drew | AB99: =K99 -> 10221.48
A100: 1397 | B100: 20255099 | C100: Ray Marker | E100: 45810 | F100: 1825.96 | G100: 45911 | H100: 45911 | I100: Brett | J100: 1825.96 | K100: 1825.96 | L100: =if(S100=TRUE,K100-F100,"") -> 0 | M100: 1561.25 | N100: =if(S100=TRUE,K100-M100,"") -> 264.71 | O100: =IF($R100, IFERROR(IF((F100+L100)>0, (F100+L100-M100)/(F100+L100), ""), ""), "") -> 0.14497032 | P100: =IFERROR(__xludf.DUMMYFUNCTION("IF(AND($R100, NOT(REGEXMATCH(UPPER($C100), ""INS""))), IFERROR(IF((F100+L100)>0, (F100+L100-M100)/(F100+L100), """"), """"), """")"),0.14497031698394272) -> 0.14497032 | Q100: =IFERROR(__xludf.DUMMYFUNCTION("IF(AND($R100, REGEXMATCH(UPPER($C100), ""INS"")), IFERROR(IF((F100+L100)>0, (F100+L100-M100)/(F100+L100), """"), """"), """")"),"") | R100: TRUE | S100: TRUE | T100: TRUE | U100: In Billing | V100: TRUE | W100: =O100 -> 0.14497032 | X100: =J100 -> 1825.96 | Y100: =F100 -> 1825.96 | Z100: =L100 -> 0 | AA100: =IFERROR(__xludf.DUMMYFUNCTION("""COMPUTED_VALUE"""),"") | AB100: =K100 -> 1825.96
...

Sheet 2025 Breakdown

Sheet 2025 AM Totals
I1: Average GP | J1: Average per contract | K1: Open Jobs
I2: =G2 -> 0.51352018 | J2: =E2/B2 -> 27108.786 | K2: =COUNTIFS('2025'!I:I,"Adam",'2025'!U:U,"<>In Billing") -> 0
I3: =(G3+H3)/2 -> 0.48559301 | J3: =E3/B3 -> 12338.799 | K3: =COUNTIFS('2025'!I:I,"Brett",'2025'!U:U,"<>In Billing") -> 4
I4: =G4 -> 0.99995 | J4: =E4/B4 -> 200 | K4: =COUNTIFS('2025'!I:I,"Cale",'2025'!U:U,"<>In Billing") -> 0
I5: =(G5+H5)/2 -> 0.60655555 | J5: =E5/B5 -> 46479.818 | K5: =COUNTIFS('2025'!I:I,"Chris",'2025'!U:U,"<>In Billing") -> 6
I6: =(G6+H6)/2 -> 0.56538884 | J6: =E6/B6 -> 16851.348 | K6: =COUNTIFS('2025'!I:I,"Drew",'2025'!U:U,"<>In Billing") -> 4
